Workbook

Sheet Master Sheet
A1: ProductId | B1: SkuId | C1: SkuTitle | D1: TermDuration | E1: BillingPlan | F1: ERP Price | G1: UnitPrice | H1: Tags | I1: Standard Percentage | J1: Segment | K1: Promo (If new to MS) | L1: Distributor Core Rebate | M1: Distributor Product Tier 1 | N1: Distributor Product Tier 2 | O1: Distributor Growth Accelerator | P1: Partner Core rebate | Q1: Partner Product Tier 1 | R1: Partner Product Tier 2 | S1: Partner Growth Accelerator
A2: CFQ7TTC0HL8Z | B2: 1 | C2: 10-Year Audit Log Retention Add On | D2: P1Y | E2: Monthly | F2: 2079 | G2: 1663.2 | H2: License | I2: =1-(G2/F2) -> 0.2 | J2: Commercial | K2: 0.05
A3: CFQ7TTC0HL8Z | B3: 1 | C3: 10-Year Audit Log Retention Add On | D3: P1Y | E3: Annual | F3: 1980 | G3: 1584 | H3: License | I3: =1-(G3/F3) -> 0.2 | J3: Commercial
A4: CFQ7TTC0HL8Z | B4: 5 | C4: 10-Year Audit Log Retention Add On for FLW | D4: P1Y | E4: Monthly | F4: 1386 | G4: 1108.8 | H4: License | I4: =1-(G4/F4) -> 0.2 | J4: Commercial
A5: CFQ7TTC0HL8Z | B5: 4 | C5: 10-Year Audit Log Retention Add On (Education Pricing) | D5: P1Y | E5: Annual | F5: 1980 | G5: 1584 | H5: License | I5: =1-(G5/F5) -> 0.2 | J5: Education
A6: CFQ7TTC0HL8Z | B6: 5 | C6: 10-Year Audit Log Retention Add On for FLW | D6: P1Y | E6: Annual | F6: 1320 | G6: 1056 | H6: License | I6: =1-(G6/F6) -> 0.2 | J6: Commercial
A7: CFQ7TTC0HL8Z | B7: 1 | C7: 10-Year Audit Log Retention Add On | D7: P1M | E7: Monthly | F7: 198 | G7: 158.4 | H7: License | I7: =1-(G7/F7) -> 0.2 | J7: Commercial
A8: CFQ7TTC0HL8Z | B8: 4 | C8: 10-Year Audit Log Retention Add On (Education Pricing) | D8: P1M | E8: Monthly | F8: 198 | G8: 158.4 | H8: License | I8: =1-(G8/F8) -> 0.2 | J8: Education
A9: CFQ7TTC0HL8Z | B9: 5 | C9: 10-Year Audit Log Retention Add On for FLW | D9: P1M | E9: Monthly | F9: 132 | G9: 105.6 | H9: License | I9: =1-(G9/F9) -> 0.2 | J9: Commercial
A10: CFQ7TTC0HL8Z | B10: 4 | C10: 10-Year Audit Log Retention Add On (Education Pricing) | D10: P1Y | E10: Monthly | F10: 2079 | G10: 1663.2 | H10: License | I10: =1-(G10/F10) -> 0.2 | J10: Education
A11: CFQ7TTC0RN26 | B11: 1 | C11: Advanced Data Residency | D11: P1Y | E11: Monthly | F11: 2079 | G11: 1663.2 | H11: License | I11: =1-(G11/F11) -> 0.2 | J11: Commercial
A12: CFQ7TTC0RN26 | B12: 1 | C12: Advanced Data Residency | D12: P3Y | E12: Triennial | F12: 5940 | G12: 4752 | H12: License | I12: =1-(G12/F12) -> 0.2 | J12: Commercial
A13: CFQ7TTC0RN26 | B13: 1 | C13: Advanced Data Residency | D13: P1Y | E13: Annual | F13: 1980 | G13: 1584 | H13: License | I13: =1-(G13/F13) -> 0.2 | J13: Commercial
A14: CFQ7TTC0RN26 | B14: 1 | C14: Advanced Data Residency | D14: P3Y | E14: Annual | F14: 5940 | G14: 4752 | H14: License | I14: =1-(G14/F14) -> 0.2 | J14: Commercial
A15: CFQ7TTC0HDK0 | B15: 000B | C15: Advanced Communications (Non-Profit Pricing) | D15: P1Y | E15: Monthly | F15: 5040 | G15: 4536 | H15: License | I15: =1-(G15/F15) -> 0.1 | J15: Charity
A16: CFQ7TTC0HDK0 | B16: 000D | C16: Advanced Communications (Education Student Pricing) | D16: P1Y | E16: Monthly | F16: 1890 | G16: 1512 | H16: License | I16: =1-(G16/F16) -> 0.2 | J16: Education
A17: CFQ7TTC0HDK0 | B17: 000C | C17: Advanced Communications (Education Faculty Pricing) | D17: P1Y | E17: Monthly | F17: 2520 | G17: 2016 | H17: License | I17: =1-(G17/F17) -> 0.2 | J17: Education
A18: CFQ7TTC0HDK0 | B18: 000C | C18: Advanced Communications (Education Faculty Pricing) | D18: P1Y | E18: Annual | F18: 2400 | G18: 1920 | H18: License | I18: =1-(G18/F18) -> 0.2 | J18: Education
A19: CFQ7TTC0HDK0 | B19: 000B | C19: Advanced Communications (Non-Profit Pricing) | D19: P1M | E19: Monthly | F19: 480 | G19: 432 | H19: License | I19: =1-(G19/F19) -> 0.1 | J19: Charity
A20: CFQ7TTC0HDK0 | B20: 000D | C20: Advanced Communications (Education Student Pricing) | D20: P1M | E20: Monthly | F20: 180 | G20: 144 | H20: License | I20: =1-(G20/F20) -> 0.2 | J20: Education
A21: CFQ7TTC0HDK0 | B21: 1 | C21: Advanced Communications | D21: P1M | E21: Monthly | F21: 1200 | G21: 960 | H21: License | I21: =1-(G21/F21) -> 0.2 | J21: Commercial
A22: CFQ7TTC0HDK0 | B22: 000B | C22: Advanced Communications (Non-Profit Pricing) | D22: P1Y | E22: Annual | F22: 4800 | G22: 4320 | H22: License | I22: =1-(G22/F22) -> 0.1 | J22: Charity
A23: CFQ7TTC0HDK0 | B23: 1 | C23: Advanced Communications | D23: P1Y | E23: Annual | F23: 12000 | G23: 9600 | H23: License | I23: =1-(G23/F23) -> 0.2 | J23: Commercial
A24: CFQ7TTC0HDK0 | B24: 1 | C24: Advanced Communications | D24: P1Y | E24: Monthly | F24: 12600 | G24: 10080 | H24: License | I24: =1-(G24/F24) -> 0.2 | J24: Commercial
A25: CFQ7TTC0HDK0 | B25: 000D | C25: Advanced Communications (Education Student Pricing) | D25: P1Y | E25: Annual | F25: 1800 | G25: 1440 | H25: License | I25: =1-(G25/F25) -> 0.2 | J25: Education
A26: CFQ7TTC0HDK0 | B26: 000C | C26: Advanced Communications (Education Faculty Pricing) | D26: P1M | E26: Monthly | F26: 240 | G26: 192 | H26: License | I26: =1-(G26/F26) -> 0.2 | J26: Education
A27: CFQ7TTC0LHQD | B27: 4 | C27: Advanced eDiscovery Storage (Education Faculty Pricing) | D27: P1M | E27: Monthly | F27: 1998 | G27: 1598.4 | H27: License | I27: =1-(G27/F27) -> 0.2 | J27: Education
A28: CFQ7TTC0LHQD | B28: 4 | C28: Advanced eDiscovery Storage (Education Faculty Pricing) | D28: P1Y | E28: Monthly | F28: 20979 | G28: 16783.2 | H28: License | I28: =1-(G28/F28) -> 0.2 | J28: Education
A29: CFQ7TTC0LHQD | B29: 4 | C29: Advanced eDiscovery Storage (Education Faculty Pricing) | D29: P1Y | E29: Annual | F29: 19980 | G29: 15984 | H29: License | I29: =1-(G29/F29) -> 0.2 | J29: Education
A30: CFQ7TTC0LHQD | B30: 1 | C30: Advanced eDiscovery Storage | D30: P1Y | E30: Monthly | F30: 104832 | G30: 83865.6 | H30: License | I30: =1-(G30/F30) -> 0.2 | J30: Commercial
A31: CFQ7TTC0LHQD | B31: 5 | C31: Advanced eDiscovery Storage (Non-Profit Pricing) | D31: P1Y | E31: Monthly | F31: 41958 | G31: 37762.2 | H31: License | I31: =1-(G31/F31) -> 0.1 | J31: Charity
A32: CFQ7TTC0LHQD | B32: 1 | C32: Advanced eDiscovery Storage | D32: P1Y | E32: Annual | F32: 99840 | G32: 79872 | H32: License | I32: =1-(G32/F32) -> 0.2 | J32: Commercial
A33: CFQ7TTC0LHQD | B33: 5 | C33: Advanced eDiscovery Storage (Non-Profit Pricing) | D33: P1M | E33: Monthly | F33: 3996 | G33: 3596.4 | H33: License | I33: =1-(G33/F33) -> 0.1 | J33: Charity
A34: CFQ7TTC0LHQD | B34: 5 | C34: Advanced eDiscovery Storage (Non-Profit Pricing) | D34: P1Y | E34: Annual | F34: 39960 | G34: 35964 | H34: License | I34: =1-(G34/F34) -> 0.1 | J34: Charity
A35: CFQ7TTC0LHQD | B35: 1 | C35: Advanced eDiscovery Storage | D35: P1M | E35: Monthly | F35: 9984 | G35: 7987.2 | H35: License | I35: =1-(G35/F35) -> 0.2 | J35: Commercial
A36: CFQ7TTC10RSN | B36: 3 | C36: Microsoft Defender and Purview Suites for Microsoft 365 Business Premium | D36: P1Y | E36: Monthly | F36: 15750 | G36: 12600 | H36: License | I36: =1-(G36/F36) -> 0.2 | J36: Commercial
A37: CFQ7TTC10RSN | B37: 1 | C37: Microsoft Defender Suite for Microsoft 365 Business Premium | D37: P1Y | E37: Monthly | F37: 10458 | G37: 8366.4 | H37: License | I37: =1-(G37/F37) -> 0.2 | J37: Commercial
A38: CFQ7TTC10RSN | B38: 7 | C38: Microsoft Purview Suite for Microsoft 365 Business Premium (Non-Profit Pricing) | D38: P1Y | E38: Monthly | F38: 4221 | G38: 3798.96 | H38: License | I38: =1-(G38/F38) -> 0.099985785 | J38: Charity
... A72: CFQ7TTC0LHRL | B72: 2 | C72: Dataverse Database Capacity add-on | D72: P1Y | E72: Annual | F72: 39960 | G72: 29970 | H72: License | I72: =1-(G72/F72) -> 0.25 | J72: Commercial
A73: CFQ7TTC0LHRL | B73: 000H | C73: Dataverse Database Capacity add-on (Education Pricing) | D73: P1M | E73: Monthly | F73: 2796 | G73: 2097 | H73: License | I73: =1-(G73/F73) -> 0.25 | J73: Education
A74: CFQ7TTC0LHRL | B74: 2 | C74: Dataverse Database Capacity add-on | D74: P1M | E74: Monthly | F74: 3996 | G74: 2997 | H74: License | I74: =1-(G74/F74) -> 0.25 | J74: Commercial
A75: CFQ7TTC0LHRL | B75: 000J | C75: Dataverse Database Capacity add-on (Non-Profit Pricing) | D75: P1Y | E75: Monthly | F75: 29358 | G75: 26422.2 | H75: License | I75: =1-(G75/F75) -> 0.1 | J75: Charity
A76: CFQ7TTC0LHRL | B76: 2 | C76: Dataverse Database Capacity add-on | D76: P1Y | E76: Monthly | F76: 41958 | G76: 31468.56 | H76: License | I76: =1-(G76/F76) -> 0.24999857 | J76: Commercial
A77: CFQ7TTC0LHRL | B77: 000H | C77: Dataverse Database Capacity add-on (Education Pricing) | D77: P1Y | E77: Monthly | F77: 29358 | G77: 22018.56 | H77: License | I77: =1-(G77/F77) -> 0.24999796 | J77: Education
A78: CFQ7TTC0LHRL | B78: 000J | C78: Dataverse Database Capacity add-on (Non-Profit Pricing) | D78: P1M | E78: Monthly | F78: 2796 | G78: 2516.4 | H78: License | I78: =1-(G78/F78) -> 0.1 | J78: Charity
A79: CFQ7TTC0LHRL | B79: 000H | C79: Dataverse Database Capacity add-on (Education Pricing) | D79: P1Y | E79: Annual | F79: 27960 | G79: 20970 | H79: License | I79: =1-(G79/F79) -> 0.25 | J79: Education
A80: CFQ7TTC0LHRL | B80: 000J | C80: Dataverse Database Capacity add-on (Non-Profit Pricing) | D80: P1Y | E80: Annual | F80: 27960 | G80: 25164 | H80: License | I80: =1-(G80/F80) -> 0.1 | J80: Charity
A81: CFQ7TTC0NCD7 | B81: 3 | C81: Dataverse Database Capacity add-on Tier 2 (Min 1000GB) | D81: P1M | E81: Monthly | F81: 2994 | G81: 2245.5 | H81: License | I81: =1-(G81/F81) -> 0.25 | J81: Commercial
A82: CFQ7TTC0NCD7 | B82: 3 | C82: Dataverse Database Capacity add-on Tier 2 (Min 1000GB) | D82: P1Y | E82: Annual | F82: 29940 | G82: 22455 | H82: License | I82: =1-(G82/F82) -> 0.25 | J82: Commercial
A83: CFQ7TTC0NCD7 | B83: 3 | C83: Dataverse Database Capacity add-on Tier 2 (Min 1000GB) | D83: P1Y | E83: Monthly | F83: 31437 | G83: 23577.72 | H83: License | I83: =1-(G83/F83) -> 0.25000095 | J83: Commercial
A84: CFQ7TTC0NCD7 | B84: 2 | C84: Dataverse Database Capacity add-on Tier 2 (Min 1000GB) | D84: P1M | E84: None | F84: 0 | G84: 0 | H84: License;Trial | I84: =1-(G84/F84) -> #DIV/0! | J84: Commercial
A85: CFQ7TTC0LHQ3 | B85: 1 | C85: Dataverse File Capacity add-on | D85: P1Y | E85: Monthly | F85: 2079 | G85: 1559.28 | H85: License | I85: =1-(G85/F85) -> 0.24998557 | J85: Commercial
A86: CFQ7TTC0LHQ3 | B86: 000G | C86: Dataverse File Capacity add-on (Non-Profit Pricing) | D86: P1Y | E86: Monthly | F86: 1449 | G86: 1304.16 | H86: License | I86: =1-(G86/F86) -> 0.099958592 | J86: Charity
A87: CFQ7TTC0LHQ3 | B87: 1 | C87: Dataverse File Capacity add-on | D87: P1Y | E87: Annual | F87: 1980 | G87: 1485 | H87: License | I87: =1-(G87/F87) -> 0.25 | J87: Commercial
A88: CFQ7TTC0LHQ3 | B88: 000G | C88: Dataverse File Capacity add-on (Non-Profit Pricing) | D88: P1Y | E88: Annual | F88: 1380 | G88: 1242 | H88: License | I88: =1-(G88/F88) -> 0.1 | J88: Charity
A89: CFQ7TTC0LHQ3 | B89: 000H | C89: Dataverse File Capacity add-on (Education Pricing) | D89: P1Y | E89: Annual | F89: 1380 | G89: 1035 | H89: License | I89: =1-(G89/F89) -> 0.25 | J89: Education
A90: CFQ7TTC0LHQ3 | B90: 000H | C90: Dataverse File Capacity add-on (Education Pricing) | D90: P1Y | E90: Monthly | F90: 1449 | G90: 1086.72 | H90: License | I90: =1-(G90/F90) -> 0.2500207 | J90: Education
A91: CFQ7TTC0LHQ3 | B91: 1 | C91: Dataverse File Capacity add-on | D91: P1M | E91: Monthly | F91: 198 | G91: 148.5 | H91: License | I91: =1-(G91/F91) -> 0.25 | J91: Commercial
A92: CFQ7TTC0LHQ3 | B92: 000G | C92: Dataverse File Capacity add-on (Non-Profit Pricing) | D92: P1M | E92: Monthly | F92: 138 | G92: 124.2 | H92: License | I92: =1-(G92/F92) -> 0.1 | J92: Charity
A93: CFQ7TTC0LHQ3 | B93: 000H | C93: Dataverse File Capacity add-on (Education Pricing) | D93: P1M | E93: Monthly | F93: 138 | G93: 103.5 | H93: License | I93: =1-(G93/F93) -> 0.25 | J93: Education
A94: CFQ7TTC0HBSL | B94: 000G | C94: Dataverse Log Capacity add-on (Non-Profit Pricing) | D94: P1Y | E94: Monthly | F94: 7308 | G94: 6577.2 | H94: License | I94: =1-(G94/F94) -> 0.1 | J94: Charity
A95: CFQ7TTC0HBSL | B95: 1 | C95: Dataverse Log Capacity add-on | D95: P1M | E95: Monthly | F95: 996 | G95: 747 | H95: License | I95: =1-(G95/F95) -> 0.25 | J95: Commercial
A96: CFQ7TTC0HBSL | B96: 1 | C96: Dataverse Log Capacity add-on | D96: P1Y | E96: Monthly | F96: 10458 | G96: 7843.56 | H96: License | I96: =1-(G96/F96) -> 0.24999426 | J96: Commercial
A97: CFQ7TTC0HBSL | B97: 1 | C97: Dataverse Log Capacity add-on | D97: P1Y | E97: Annual | F97: 9960 | G97: 7470 | H97: License | I97: =1-(G97/F97) -> 0.25 | J97: Commercial
A98: CFQ7TTC0HBSL | B98: 000G | C98: Dataverse Log Capacity add-on (Non-Profit Pricing) | D98: P1Y | E98: Annual | F98: 6960 | G98: 6264 | H98: License | I98: =1-(G98/F98) -> 0.1 | J98: Charity
A99: CFQ7TTC0HBSL | B99: 000H | C99: Dataverse Log Capacity add-on (Education Pricing) | D99: P1Y | E99: Monthly | F99: 7308 | G99: 5481 | H99: License | I99: =1-(G99/F99) -> 0.25 | J99: Education
A100: CFQ7TTC0HBSL | B100: 000H | C100: Dataverse Log Capacity add-on (Education Pricing) | D100: P1Y | E100: Annual | F100: 6960 | G100: 5220 | H100: License | I100: =1-(G100/F100) -> 0.25 | J100: Education
A101: CFQ7TTC0HBSL | B101: 000G | C101: Dataverse Log Capacity add-on (Non-Profit Pricing) | D101: P1M | E101: Monthly | F101: 696 | G101: 626.4 | H101: License | I101: =1-(G101/F101) -> 0.1 | J101: Charity
A102: CFQ7TTC0HBSL | B102: 000H | C102: Dataverse Log Capacity add-on (Education Pricing) | D102: P1M | E102: Monthly | F102: 696 | G102: 522 | H102: License | I102: =1-(G102/F102) -> 0.25 | J102: Education
A103: CFQ7TTC0LHXR | B103: 000B | C103: Dynamics 365 Operations-Order Lines (Education Pricing) | D103: P1M | E103: Monthly | F103: 34944 | G103: 24460.8 | H103: License | I103: =1-(G103/F103) -> 0.3 | J103: Education
A104: CFQ7TTC0LHXR | B104: 1 | C104: Dynamics 365 Operations – Order Lines | D104: P1M | E104: Monthly | F104: 49914 | G104: 34939.8 | H104: License | I104: =1-(G104/F104) -> 0.3 | J104: Commercial
A105: CFQ7TTC0LHXR | B105: 1 | C105: Dynamics 365 Operations – Order Lines | D105: P1Y | E105: Annual | F105: 499140 | G105: 349398 | H105: License | I105: =1-(G105/F105) -> 0.3 | J105: Commercial
A106: CFQ7TTC0LHXR | B106: 1 | C106: Dynamics 365 Operations – Order Lines | D106: P1Y | E106: Monthly | F106: 524097 | G106: 366868 | H106: License | I106: =1-(G106/F106) -> 0.29999981 | J106: Commercial
A107: CFQ7TTC0LHXR | B107: 000G | C107: Dynamics 365 Operations – Order Lines (Non-Profit Pricing) | D107: P1Y | E107: Monthly | F107: 131040 | G107: 117936 | H107: License | I107: =1-(G107/F107) -> 0.1 | J107: Charity
A108: CFQ7TTC0LHXR | B108: 000B | C108: Dynamics 365 Operations-Order Lines (Education Pricing) | D108: P1Y | E108: Monthly | F108: 366912 | G108: 256838.4 | H108: License | I108: =1-(G108/F108) -> 0.3 | J108: Education
A109: CFQ7TTC0LHXR | B109: 000B | C109: Dynamics 365 Operations-Order Lines (Education Pricing) | D109: P1Y | E109: Annual | F109: 349440 | G109: 244608 | H109: License | I109: =1-(G109/F109) -> 0.3 | J109: Education
A110: CFQ7TTC0LHXR | B110: 000G | C110: Dynamics 365 Operations – Order Lines (Non-Profit Pricing) | D110: P1M | E110: Monthly | F110: 12480 | G110: 11232 | H110: License | I110: =1-(G110/F110) -> 0.1 | J110: Charity
A111: CFQ7TTC0LHXR | B111: 000G | C111: Dynamics 365 Operations – Order Lines (Non-Profit Pricing) | D111: P1Y | E111: Annual | F111: 124800 | G111: 112320 | H111: License | I111: =1-(G111/F111) -> 0.1 | J111: Charity
A112: CFQ7TTC0LHWJ | B112: 1 | C112: Dynamics 365 Asset Management Addl Assets | D112: P1M | E112: Monthly | F112: 9984 | G112: 6988.8 | H112: License | I112: =1-(G112/F112) -> 0.3 | J112: Commercial
A113: CFQ7TTC0LHWJ | B113: 1 | C113: Dynamics 365 Asset Management Addl Assets | D113: P3Y | E113: Monthly | F113: 314496 | G113: 220147.2 | H113: License | I113: =1-(G113/F113) -> 0.3 | J113: Commercial
A114: CFQ7TTC0LHWJ | B114: 000C | C114: Dynamics 365 Asset Management Addl Assets (Education Faculty Pricing) | D114: P1Y | E114: Monthly | F114: 73395 | G114: 51376.56 | H114: License | I114: =1-(G114/F114) -> 0.29999918 | J114: Education
A115: CFQ7TTC0LHWJ | B115: 1 | C115: Dynamics 365 Asset Management Addl Assets | D115: P1Y | E115: Annual | F115: 99840 | G115: 69888 | H115: License | I115: =1-(G115/F115) -> 0.3 | J115: Commercial
A116: CFQ7TTC0LHWJ | B116: 000C | C116: Dynamics 365 Asset Management Addl Assets (Education Faculty Pricing) | D116: P1Y | E116: Annual | F116: 69900 | G116: 48930 | H116: License | I116: =1-(G116/F116) -> 0.3 | J116: Education
A117: CFQ7TTC0LHWJ | B117: 000B | C117: Dynamics 365 Asset Management Addl Assets (Non-Profit Pricing) | D117: P1Y | E117: Annual | F117: 69900 | G117: 62910 | H117: License | I117: =1-(G117/F117) -> 0.1 | J117: Charity
A118: CFQ7TTC0LHWJ | B118: 000B | C118: Dynamics 365 Asset Management Addl Assets (Non-Profit Pricing) | D118: P1M | E118: Monthly | F118: 6990 | G118: 6291 | H118: License | I118: =1-(G118/F118) -> 0.1 | J118: Charity
A119: CFQ7TTC0LHWJ | B119: 000C | C119: Dynamics 365 Asset Management Addl Assets (Education Faculty Pricing) | D119: P1M | E119: Monthly | F119: 6990 | G119: 4893 | H119: License | I119: =1-(G119/F119) -> 0.3 | J119: Education
A120: CFQ7TTC0LHWJ | B120: 1 | C120: Dynamics 365 Asset Management Addl Assets | D120: P3Y | E120: Triennial | F120: 299520 | G120: 209664 | H120: License | I120: =1-(G120/F120) -> 0.3 | J120: Commercial
A121: CFQ7TTC0LHWJ | B121: 000B | C121: Dynamics 365 Asset Management Addl Assets (Non-Profit Pricing) | D121: P1Y | E121: Monthly | F121: 73395 | G121: 66055.56 | H121: License | I121: =1-(G121/F121) -> 0.099999183 | J121: Charity
A122: CFQ7TTC0LHWJ | B122: 1 | C122: Dynamics 365 Asset Management Addl Assets | D122: P3Y | E122: Annual | F122: 299520 | G122: 209664 | H122: License | I122: =1-(G122/F122) -> 0.3 | J122: Commercial
A123: CFQ7TTC0LHWJ | B123: 1 | C123: Dynamics 365 Asset Management Addl Assets | D123: P1Y | E123: Monthly | F123: 104832 | G123: 73382.4 | H123: License | I123: =1-(G123/F123) -> 0.3 | J123: Commercial
A124: CFQ7TTC0HD7P | B124: 3 | C124: Dynamics 365 Business Central Additional Environment Addon (Education Faculty Pricing) | D124: P1Y | E124: Annual | F124: 164700 | G124: 115290 | H124: License | I124: =1-(G124/F124) -> 0.3 | J124: Education
A125: CFQ7TTC0HD7P | B125: 1 | C125: Dynamics 365 Business Central Additional Environment Addon | D125: P1M | E125: Monthly | F125: 29952 | G125: 20966.4 | H125: License | I125: =1-(G125/F125) -> 0.3 | J125: Commercial
A126: CFQ7TTC0HD7P | B126: 4 | C126: Dynamics 365 Business Central Additional Environment Addon (Non-Profit Pricing) | D126: P1Y | E126: Annual | F126: 119820 | G126: 107838 | H126: License | I126: =1-(G126/F126) -> 0.1 | J126: Charity
A127: CFQ7TTC0HD7P | B127: 3 | C127: Dynamics 365 Business Central Additional Environment Addon (Education Faculty Pricing) | D127: P1M | E127: Monthly | F127: 16470 | G127: 11529 | H127: License | I127: =1-(G127/F127) -> 0.3 | J127: Education
A128: CFQ7TTC0HD7P | B128: 1 | C128: Dynamics 365 Business Central Additional Environment Addon | D128: P1Y | E128: Monthly | F128: 314496 | G128: 220147.2 | H128: License | I128: =1-(G128/F128) -> 0.3 | J128: Commercial
A129: CFQ7TTC0HD7P | B129: 4 | C129: Dynamics 365 Business Central Additional Environment Addon (Non-Profit Pricing) | D129: P1Y | E129: Monthly | F129: 125811 | G129: 113230 | H129: License | I129: =1-(G129/F129) -> 0.099999205 | J129: Charity
A130: CFQ7TTC0HD7P | B130: 1 | C130: Dynamics 365 Business Central Additional Environment Addon | D130: P1Y | E130: Annual | F130: 299520 | G130: 209664 | H130: License | I130: =1-(G130/F130) -> 0.3 | J130: Commercial
A131: CFQ7TTC0HD7P | B131: 4 | C131: Dynamics 365 Business Central Additional Environment Addon (Non-Profit Pricing) | D131: P1M | E131: Monthly | F131: 11982 | G131: 10783.8 | H131: License | I131: =1-(G131/F131) -> 0.1 | J131: Charity
A132: CFQ7TTC0HD7P | B132: 3 | C132: Dynamics 365 Business Central Additional Environment Addon (Education Faculty Pricing) | D132: P1Y | E132: Monthly | F132: 172935 | G132: 121054.6 | H132: License | I132: =1-(G132/F132) -> 0.29999942 | J132: Education
A133: CFQ7TTC0HD3R | B133: 7 | C133: Dynamics 365 Business Central Database Capacity (Education Faculty Pricing) | D133: P1M | E133: Monthly | F133: 552 | G133: 386.4 | H133: License | I133: =1-(G133/F133) -> 0.3 | J133: Education
...

Sheet Calcuations
A1: ProductId | B1: SkuId | C1: SkuTitle | D1: TermDuration | E1: BillingPlan | F1: ERP Price | G1: UnitPrice/Catalogue | H1: Promo (If new to MS) | I1: Net to MS | J1: Distributor Core Rebate | K1: Distributor Product Tier 1 | L1: Distributor Product Tier 2 | M1: Distributor Growth Accelerator | N1: Disti Landing with Promo | O1: Disti Landing without Promo | P1: Partner Core rebate | Q1: Partner Product Tier 1 | R1: Partner Product Tier 2 | S1: Partner Growth Accelerator | T1: Skysecure Landing with Promo | U1: Skysecure Without Promo | V1: Expected Disti Discount | W1: Expected Disti Pricing with Promo | X1: Expected Disti Pricing without Promo | Y1: Expected Partner Discounting Excluding 5% / 7.5 % | Z1: Expected Partner Pricing with Promo | AA1: Expected Partner Pricing without Promo
A2: ='Master Sheet'!A2 -> CFQ7TTC0HL8Z | B2: ='Master Sheet'!B2 -> 1 | C2: ='Master Sheet'!C2 -> 10-Year Audit Log Retention Add On | D2: ='Master Sheet'!D2 -> P1Y | E2: ='Master Sheet'!E2 -> Monthly | F2: ='Master Sheet'!F2 -> 2079 | G2: ='Master Sheet'!G2 -> 1663.2 | H2: ='Master Sheet'!K2 -> 0.05 | I2: =G2-(G2*H2) -> 1580.04 | J2: ='Master Sheet'!L2 -> 0 | K2: ='Master Sheet'!M2 -> 0 | L2: ='Master Sheet'!N2 -> 0 | M2: ='Master Sheet'!O2 -> 0 | N2: =I2-(I2*SUM(J2:M2)) -> 1580.04 | O2: =G2-(G2*SUM(J2:M2)) -> 1663.2 | P2: ='Master Sheet'!P2 -> 0 | Q2: ='Master Sheet'!Q2 -> 0 | R2: ='Master Sheet'!R2 -> 0 | S2: ='Master Sheet'!S2 -> 0 | T2: =N2-(N2*(SUM(P2:S2))) -> 1580.04 | U2: =O2-(O2*(SUM(P2:S2))) -> 1663.2 | V2: =MAX(0,SUM(J2:M2)-IF(D2="P3Y",7.5%,5%)) -> 0 | W2: =N2-(N2*V2) -> 1580.04 | X2: =O2-(O2*V2) -> 1663.2 | Y2: =MAX(0,SUM(P2:S2)-IF(D2="P3Y",7.5%,5%)) -> 0 | Z2: =W2-(W2*Y2) -> 1580.04 | AA2: =X2-(X2*Y2) -> 1663.2
A3: ='Master Sheet'!A3 -> CFQ7TTC0HL8Z | B3: ='Master Sheet'!B3 -> 1 | C3: ='Master Sheet'!C3 -> 10-Year Audit Log Retention Add On | D3: ='Master Sheet'!D3 -> P1Y | E3: ='Master Sheet'!E3 -> Annual | F3: ='Master Sheet'!F3 -> 1980 | G3: ='Master Sheet'!G3 -> 1584 | H3: ='Master Sheet'!K3 -> 0 | I3: =G3-(G3*H3) -> 1584 | J3: ='Master Sheet'!L3 -> 0 | K3: ='Master Sheet'!M3 -> 0 | L3: ='Master Sheet'!N3 -> 0 | M3: ='Master Sheet'!O3 -> 0 | N3: =I3-(I3*SUM(J3:M3)) -> 1584 | O3: =G3-(G3*SUM(J3:M3)) -> 1584 | P3: ='Master Sheet'!P3 -> 0 | Q3: ='Master Sheet'!Q3 -> 0 | R3: ='Master Sheet'!R3 -> 0 | S3: ='Master Sheet'!S3 -> 0 | T3: =N3-(N3*(SUM(P3:S3))) -> 1584 | U3: =O3-(O3*(SUM(P3:S3))) -> 1584 | V3: =MAX(0,SUM(J3:M3)-IF(D3="P3Y",7.5%,5%)) -> 0 | W3: =N3-(N3*V3) -> 1584 | X3: =O3-(O3*V3) -> 1584 | Y3: =MAX(0,SUM(P3:S3)-IF(D3="P3Y",7.5%,5%)) -> 0 | Z3: =W3-(W3*Y3) -> 1584 | AA3: =X3-(X3*Y3) -> 1584
A4: ='Master Sheet'!A4 -> CFQ7TTC0HL8Z | B4: ='Master Sheet'!B4 -> 5 | C4: ='Master Sheet'!C4 -> 10-Year Audit Log Retention Add On for FLW | D4: ='Master Sheet'!D4 -> P1Y | E4: ='Master Sheet'!E4 -> Monthly | F4: ='Master Sheet'!F4 -> 1386 | G4: ='Master Sheet'!G4 -> 1108.8 | H4: ='Master Sheet'!K4 -> 0 | I4: =G4-(G4*H4) -> 1108.8 | J4: ='Master Sheet'!L4 -> 0 | K4: ='Master Sheet'!M4 -> 0 | L4: ='Master Sheet'!N4 -> 0 | M4: ='Master Sheet'!O4 -> 0 | N4: =I4-(I4*SUM(J4:M4)) -> 1108.8 | O4: =G4-(G4*SUM(J4:M4)) -> 1108.8 | P4: ='Master Sheet'!P4 -> 0 | Q4: ='Master Sheet'!Q4 -> 0 | R4: ='Master Sheet'!R4 -> 0 | S4: ='Master Sheet'!S4 -> 0 | T4: =N4-(N4*(SUM(P4:S4))) -> 1108.8 | U4: =O4-(O4*(SUM(P4:S4))) -> 1108.8 | V4: =MAX(0,SUM(J4:M4)-IF(D4="P3Y",7.5%,5%)) -> 0 | W4: =N4-(N4*V4) -> 1108.8 | X4: =O4-(O4*V4) -> 1108.8 | Y4: =MAX(0,SUM(P4:S4)-IF(D4="P3Y",7.5%,5%)) -> 0 | Z4: =W4-(W4*Y4) -> 1108.8 | AA4: =X4-(X4*Y4) -> 1108.8
A5: ='Master Sheet'!A5 -> CFQ7TTC0HL8Z | B5: ='Master Sheet'!B5 -> 4 | C5: ='Master Sheet'!C5 -> 10-Year Audit Log Retention Add On (Education Pricing) | D5: ='Master Sheet'!D5 -> P1Y | E5: ='Master Sheet'!E5 -> Annual | F5: ='Master Sheet'!F5 -> 1980 | G5: ='Master Sheet'!G5 -> 1584 | H5: ='Master Sheet'!K5 -> 0 | I5: =G5-(G5*H5) -> 1584 | J5: ='Master Sheet'!L5 -> 0 | K5: ='Master Sheet'!M5 -> 0 | L5: ='Master Sheet'!N5 -> 0 | M5: ='Master Sheet'!O5 -> 0 | N5: =I5-(I5*SUM(J5:M5)) -> 1584 | O5: =G5-(G5*SUM(J5:M5)) -> 1584 | P5: ='Master Sheet'!P5 -> 0 | Q5: ='Master Sheet'!Q5 -> 0 | R5: ='Master Sheet'!R5 -> 0 | S5: ='Master Sheet'!S5 -> 0 | T5: =N5-(N5*(SUM(P5:S5))) -> 1584 | U5: =O5-(O5*(SUM(P5:S5))) -> 1584 | V5: =MAX(0,SUM(J5:M5)-IF(D5="P3Y",7.5%,5%)) -> 0 | W5: =N5-(N5*V5) -> 1584 | X5: =O5-(O5*V5) -> 1584 | Y5: =MAX(0,SUM(P5:S5)-IF(D5="P3Y",7.5%,5%)) -> 0 | Z5: =W5-(W5*Y5) -> 1584 | AA5: =X5-(X5*Y5) -> 1584
A6: ='Master Sheet'!A6 -> CFQ7TTC0HL8Z | B6: ='Master Sheet'!B6 -> 5 | C6: ='Master Sheet'!C6 -> 10-Year Audit Log Retention Add On for FLW | D6: ='Master Sheet'!D6 -> P1Y | E6: ='Master Sheet'!E6 -> Annual | F6: ='Master Sheet'!F6 -> 1320 | G6: ='Master Sheet'!G6 -> 1056 | H6: ='Master Sheet'!K6 -> 0 | I6: =G6-(G6*H6) -> 1056 | J6: ='Master Sheet'!L6 -> 0 | K6: ='Master Sheet'!M6 -> 0 | L6: ='Master Sheet'!N6 -> 0 | M6: ='Master Sheet'!O6 -> 0 | N6: =I6-(I6*SUM(J6:M6)) -> 1056 | O6: =G6-(G6*SUM(J6:M6)) -> 1056 | P6: ='Master Sheet'!P6 -> 0 | Q6: ='Master Sheet'!Q6 -> 0 | R6: ='Master Sheet'!R6 -> 0 | S6: ='Master Sheet'!S6 -> 0 | T6: =N6-(N6*(SUM(P6:S6))) -> 1056 | U6: =O6-(O6*(SUM(P6:S6))) -> 1056 | V6: =MAX(0,SUM(J6:M6)-IF(D6="P3Y",7.5%,5%)) -> 0 | W6: =N6-(N6*V6) -> 1056 | X6: =O6-(O6*V6) -> 1056 | Y6: =MAX(0,SUM(P6:S6)-IF(D6="P3Y",7.5%,5%)) -> 0 | Z6: =W6-(W6*Y6) -> 1056 | AA6: =X6-(X6*Y6) -> 1056
A7: ='Master Sheet'!A7 -> CFQ7TTC0HL8Z | B7: ='Master Sheet'!B7 -> 1 | C7: ='Master Sheet'!C7 -> 10-Year Audit Log Retention Add On | D7: ='Master Sheet'!D7 -> P1M | E7: ='Master Sheet'!E7 -> Monthly | F7: ='Master Sheet'!F7 -> 198 | G7: ='Master Sheet'!G7 -> 158.4 | H7: ='Master Sheet'!K7 -> 0 | I7: =G7-(G7*H7) -> 158.4 | J7: ='Master Sheet'!L7 -> 0 | K7: ='Master Sheet'!M7 -> 0 | L7: ='Master Sheet'!N7 -> 0 | M7: ='Master Sheet'!O7 -> 0 | N7: =I7-(I7*SUM(J7:M7)) -> 158.4 | O7: =G7-(G7*SUM(J7:M7)) -> 158.4 | P7: ='Master Sheet'!P7 -> 0 | Q7: ='Master Sheet'!Q7 -> 0 | R7: ='Master Sheet'!R7 -> 0 | S7: ='Master Sheet'!S7 -> 0 | T7: =N7-(N7*(SUM(P7:S7))) -> 158.4 | U7: =O7-(O7*(SUM(P7:S7))) -> 158.4 | V7: =MAX(0,SUM(J7:M7)-IF(D7="P3Y",7.5%,5%)) -> 0 | W7: =N7-(N7*V7) -> 158.4 | X7: =O7-(O7*V7) -> 158.4 | Y7: =MAX(0,SUM(P7:S7)-IF(D7="P3Y",7.5%,5%)) -> 0 | Z7: =W7-(W7*Y7) -> 158.4 | AA7: =X7-(X7*Y7) -> 158.4
A8: ='Master Sheet'!A8 -> CFQ7TTC0HL8Z | B8: ='Master Sheet'!B8 -> 4 | C8: ='Master Sheet'!C8 -> 10-Year Audit Log Retention Add On (Education Pricing) | D8: ='Master Sheet'!D8 -> P1M | E8: ='Master Sheet'!E8 -> Monthly | F8: ='Master Sheet'!F8 -> 198 | G8: ='Master Sheet'!G8 -> 158.4 | H8: ='Master Sheet'!K8 -> 0 | I8: =G8-(G8*H8) -> 158.4 | J8: ='Master Sheet'!L8 -> 0 | K8: ='Master Sheet'!M8 -> 0 | L8: ='Master Sheet'!N8 -> 0 | M8: ='Master Sheet'!O8 -> 0 | N8: =I8-(I8*SUM(J8:M8)) -> 158.4 | O8: =G8-(G8*SUM(J8:M8)) -> 158.4 | P8: ='Master Sheet'!P8 -> 0 | Q8: ='Master Sheet'!Q8 -> 0 | R8: ='Master Sheet'!R8 -> 0 | S8: ='Master Sheet'!S8 -> 0 | T8: =N8-(N8*(SUM(P8:S8))) -> 158.4 | U8: =O8-(O8*(SUM(P8:S8))) -> 158.4 | V8: =MAX(0,SUM(J8:M8)-IF(D8="P3Y",7.5%,5%)) -> 0 | W8: =N8-(N8*V8) -> 158.4 | X8: =O8-(O8*V8) -> 158.4 | Y8: =MAX(0,SUM(P8:S8)-IF(D8="P3Y",7.5%,5%)) -> 0 | Z8: =W8-(W8*Y8) -> 158.4 | AA8: =X8-(X8*Y8) -> 158.4
A9: ='Master Sheet'!A9 -> CFQ7TTC0HL8Z | B9: ='Master Sheet'!B9 -> 5 | C9: ='Master Sheet'!C9 -> 10-Year Audit Log Retention Add On for FLW | D9: ='Master Sheet'!D9 -> P1M | E9: ='Master Sheet'!E9 -> Monthly | F9: ='Master Sheet'!F9 -> 132 | G9: ='Master Sheet'!G9 -> 105.6 | H9: ='Master Sheet'!K9 -> 0 | I9: =G9-(G9*H9) -> 105.6 | J9: ='Master Sheet'!L9 -> 0 | K9: ='Master Sheet'!M9 -> 0 | L9: ='Master Sheet'!N9 -> 0 | M9: ='Master Sheet'!O9 -> 0 | N9: =I9-(I9*SUM(J9:M9)) -> 105.6 | O9: =G9-(G9*SUM(J9:M9)) -> 105.6 | P9: ='Master Sheet'!P9 -> 0 | Q9: ='Master Sheet'!Q9 -> 0 | R9: ='Master Sheet'!R9 -> 0 | S9: ='Master Sheet'!S9 -> 0 | T9: =N9-(N9*(SUM(P9:S9))) -> 105.6 | U9: =O9-(O9*(SUM(P9:S9))) -> 105.6 | V9: =MAX(0,SUM(J9:M9)-IF(D9="P3Y",7.5%,5%)) -> 0 | W9: =N9-(N9*V9) -> 105.6 | X9: =O9-(O9*V9) -> 105.6 | Y9: =MAX(0,SUM(P9:S9)-IF(D9="P3Y",7.5%,5%)) -> 0 | Z9: =W9-(W9*Y9) -> 105.6 | AA9: =X9-(X9*Y9) -> 105.6
A10: ='Master Sheet'!A10 -> CFQ7TTC0HL8Z | B10: ='Master Sheet'!B10 -> 4 | C10: ='Master Sheet'!C10 -> 10-Year Audit Log Retention Add On (Education Pricing) | D10: ='Master Sheet'!D10 -> P1Y | E10: ='Master Sheet'!E10 -> Monthly | F10: ='Master Sheet'!F10 -> 2079 | G10: ='Master Sheet'!G10 -> 1663.2 | H10: ='Master Sheet'!K10 -> 0 | I10: =G10-(G10*H10) -> 1663.2 | J10: ='Master Sheet'!L10 -> 0 | K10: ='Master Sheet'!M10 -> 0 | L10: ='Master Sheet'!N10 -> 0 | M10: ='Master Sheet'!O10 -> 0 | N10: =I10-(I10*SUM(J10:M10)) -> 1663.2 | O10: =G10-(G10*SUM(J10:M10)) -> 1663.2 | P10: ='Master Sheet'!P10 -> 0 | Q10: ='Master Sheet'!Q10 -> 0 | R10: ='Master Sheet'!R10 -> 0 | S10: ='Master Sheet'!S10 -> 0 | T10: =N10-(N10*(SUM(P10:S10))) -> 1663.2 | U10: =O10-(O10*(SUM(P10:S10))) -> 1663.2 | V10: =MAX(0,SUM(J10:M10)-IF(D10="P3Y",7.5%,5%)) -> 0 | W10: =N10-(N10*V10) -> 1663.2 | X10: =O10-(O10*V10) -> 1663.2 | Y10: =MAX(0,SUM(P10:S10)-IF(D10="P3Y",7.5%,5%)) -> 0 | Z10: =W10-(W10*Y10) -> 1663.2 | AA10: =X10-(X10*Y10) -> 1663.2
A11: ='Master Sheet'!A11 -> CFQ7TTC0RN26 | B11: ='Master Sheet'!B11 -> 1 | C11: ='Master Sheet'!C11 -> Advanced Data Residency | D11: ='Master Sheet'!D11 -> P1Y | E11: ='Master Sheet'!E11 -> Monthly | F11: ='Master Sheet'!F11 -> 2079 | G11: ='Master Sheet'!G11 -> 1663.2 | H11: ='Master Sheet'!K11 -> 0 | I11: =G11-(G11*H11) -> 1663.2 | J11: ='Master Sheet'!L11 -> 0 | K11: ='Master Sheet'!M11 -> 0 | L11: ='Master Sheet'!N11 -> 0 | M11: ='Master Sheet'!O11 -> 0 | N11: =I11-(I11*SUM(J11:M11)) -> 1663.2 | O11: =G11-(G11*SUM(J11:M11)) -> 1663.2 | P11: ='Master Sheet'!P11 -> 0 | Q11: ='Master Sheet'!Q11 -> 0 | R11: ='Master Sheet'!R11 -> 0 | S11: ='Master Sheet'!S11 -> 0 | T11: =N11-(N11*(SUM(P11:S11))) -> 1663.2 | U11: =O11-(O11*(SUM(P11:S11))) -> 1663.2 | V11: =MAX(0,SUM(J11:M11)-IF(D11="P3Y",7.5%,5%)) -> 0 | W11: =N11-(N11*V11) -> 1663.2 | X11: =O11-(O11*V11) -> 1663.2 | Y11: =MAX(0,SUM(P11:S11)-IF(D11="P3Y",7.5%,5%)) -> 0 | Z11: =W11-(W11*Y11) -> 1663.2 | AA11: =X11-(X11*Y11) -> 1663.2
A12: ='Master Sheet'!A12 -> CFQ7TTC0RN26 | B12: ='Master Sheet'!B12 -> 1 | C12: ='Master Sheet'!C12 -> Advanced Data Residency | D12: ='Master Sheet'!D12 -> P3Y | E12: ='Master Sheet'!E12 -> Triennial | F12: ='Master Sheet'!F12 -> 5940 | G12: ='Master Sheet'!G12 -> 4752 | H12: ='Master Sheet'!K12 -> 0 | I12: =G12-(G12*H12) -> 4752 | J12: ='Master Sheet'!L12 -> 0 | K12: ='Master Sheet'!M12 -> 0 | L12: ='Master Sheet'!N12 -> 0 | M12: ='Master Sheet'!O12 -> 0 | N12: =I12-(I12*SUM(J12:M12)) -> 4752 | O12: =G12-(G12*SUM(J12:M12)) -> 4752 | P12: ='Master Sheet'!P12 -> 0 | Q12: ='Master Sheet'!Q12 -> 0 | R12: ='Master Sheet'!R12 -> 0 | S12: ='Master Sheet'!S12 -> 0 | T12: =N12-(N12*(SUM(P12:S12))) -> 4752 | U12: =O12-(O12*(SUM(P12:S12))) -> 4752 | V12: =MAX(0,SUM(J12:M12)-IF(D12="P3Y",7.5%,5%)) -> 0 | W12: =N12-(N12*V12) -> 4752 | X12: =O12-(O12*V12) -> 4752 | Y12: =MAX(0,SUM(P12:S12)-IF(D12="P3Y",7.5%,5%)) -> 0 | Z12: =W12-(W12*Y12) -> 4752 | AA12: =X12-(X12*Y12) -> 4752
A13: ='Master Sheet'!A13 -> CFQ7TTC0RN26 | B13: ='Master Sheet'!B13 -> 1 | C13: ='Master Sheet'!C13 -> Advanced Data Residency | D13: ='Master Sheet'!D13 -> P1Y | E13: ='Master Sheet'!E13 -> Annual | F13: ='Master Sheet'!F13 -> 1980 | G13: ='Master Sheet'!G13 -> 1584 | H13: ='Master Sheet'!K13 -> 0 | I13: =G13-(G13*H13) -> 1584 | J13: ='Master Sheet'!L13 -> 0 | K13: ='Master Sheet'!M13 -> 0 | L13: ='Master Sheet'!N13 -> 0 | M13: ='Master Sheet'!O13 -> 0 | N13: =I13-(I13*SUM(J13:M13)) -> 1584 | O13: =G13-(G13*SUM(J13:M13)) -> 1584 | P13: ='Master Sheet'!P13 -> 0 | Q13: ='Master Sheet'!Q13 -> 0 | R13: ='Master Sheet'!R13 -> 0 | S13: ='Master Sheet'!S13 -> 0 | T13: =N13-(N13*(SUM(P13:S13))) -> 1584 | U13: =O13-(O13*(SUM(P13:S13))) -> 1584 | V13: =MAX(0,SUM(J13:M13)-IF(D13="P3Y",7.5%,5%)) -> 0 | W13: =N13-(N13*V13) -> 1584 | X13: =O13-(O13*V13) -> 1584 | Y13: =MAX(0,SUM(P13:S13)-IF(D13="P3Y",7.5%,5%)) -> 0 | Z13: =W13-(W13*Y13) -> 1584 | AA13: =X13-(X13*Y13) -> 1584
... A4031: ='Master Sheet'!A4031 -> 0 | B4031: ='Master Sheet'!B4031 -> 0 | C4031: ='Master Sheet'!C4031 -> Word LTSC for Mac 2024 | D4031: ='Master Sheet'!D4031 -> 0 | E4031: ='Master Sheet'!E4031 -> OneTime | F4031: ='Master Sheet'!F4031 -> 1954 | G4031: ='Master Sheet'!G4031 -> 1911.989 | H4031: ='Master Sheet'!K4031 -> 0 | I4031: =G4031-(G4031*H4031) -> 1911.989 | J4031: ='Master Sheet'!L4031 -> 0 | K4031: ='Master Sheet'!M4031 -> 0 | L4031: ='Master Sheet'!N4031 -> 0 | M4031: ='Master Sheet'!O4031 -> 0 | N4031: =I4031-(I4031*SUM(J4031:M4031)) -> 1911.989 | O4031: =G4031-(G4031*SUM(J4031:M4031)) -> 1911.989 | P4031: ='Master Sheet'!P4031 -> 0 | Q4031: ='Master Sheet'!Q4031 -> 0 | R4031: ='Master Sheet'!R4031 -> 0 | S4031: ='Master Sheet'!S4031 -> 0 | T4031: =N4031-(N4031*(SUM(P4031:S4031))) -> 1911.989 | U4031: =O4031-(O4031*(SUM(P4031:S4031))) -> 1911.989 | V4031: =MAX(0,SUM(J4031:M4031)-IF(D4031="P3Y",7.5%,5%)) -> 0 | W4031: =N4031-(N4031*V4031) -> 1911.989 | X4031: =O4031-(O4031*V4031) -> 1911.989 | Y4031: =MAX(0,SUM(P4031:S4031)-IF(D4031="P3Y",7.5%,5%)) -> 0 | Z4031: =W4031-(W4031*Y4031) -> 1911.989 | AA4031: =X4031-(X4031*Y4031) -> 1911.989

Sheet Outcome Sheet
A1: ProductId | B1: SkuId | C1: SkuTitle | D1: TermDuration | E1: BillingPlan | F1: ERP Price | G1: UnitPrice/Catalogue | H1: Promo (If new to MS) | I1: Net to MS | J1: Expected Partner Pricing with Promo | K1: Expected Partner Pricing without Promo | L1: Initial Quote With Promo | M1: Initial Quote Without Promo
A2: =Calcuations!A2 -> CFQ7TTC0HL8Z | B2: =Calcuations!B2 -> 1 | C2: =Calcuations!C2 -> 10-Year Audit Log Retention Add On | D2: =Calcuations!D2 -> P1Y | E2: =Calcuations!E2 -> Monthly | F2: =Calcuations!F2 -> 2079 | G2: =Calcuations!G2 -> 1663.2 | H2: =Calcuations!H2 -> 0.05 | I2: =Calcuations!I2 -> 1580.04 | J2: =Calcuations!Z2 -> 1580.04 | K2: =Calcuations!AA2 -> 1663.2 | L2: =J2+(J2*0.05) -> 1659.042 | M2: =K2+(K2*0.05) -> 1746.36
A3: =Calcuations!A3 -> CFQ7TTC0HL8Z | B3: =Calcuations!B3 -> 1 | C3: =Calcuations!C3 -> 10-Year Audit Log Retention Add On | D3: =Calcuations!D3 -> P1Y | E3: =Calcuations!E3 -> Annual | F3: =Calcuations!F3 -> 1980 | G3: =Calcuations!G3 -> 1584 | H3: =Calcuations!H3 -> 0 | I3: =Calcuations!I3 -> 1584 | J3: =Calcuations!Z3 -> 1584 | K3: =Calcuations!AA3 -> 1584 | L3: =J3+(J3*0.05) -> 1663.2 | M3: =K3+(K3*0.05) -> 1663.2
A4: =Calcuations!A4 -> CFQ7TTC0HL8Z | B4: =Calcuations!B4 -> 5 | C4: =Calcuations!C4 -> 10-Year Audit Log Retention Add On for FLW | D4: =Calcuations!D4 -> P1Y | E4: =Calcuations!E4 -> Monthly | F4: =Calcuations!F4 -> 1386 | G4: =Calcuations!G4 -> 1108.8 | H4: =Calcuations!H4 -> 0 | I4: =Calcuations!I4 -> 1108.8 | J4: =Calcuations!Z4 -> 1108.8 | K4: =Calcuations!AA4 -> 1108.8 | L4: =J4+(J4*0.05) -> 1164.24 | M4: =K4+(K4*0.05) -> 1164.24
A5: =Calcuations!A5 -> CFQ7TTC0HL8Z | B5: =Calcuations!B5 -> 4 | C5: =Calcuations!C5 -> 10-Year Audit Log Retention Add On (Education Pricing) | D5: =Calcuations!D5 -> P1Y | E5: =Calcuations!E5 -> Annual | F5: =Calcuations!F5 -> 1980 | G5: =Calcuations!G5 -> 1584 | H5: =Calcuations!H5 -> 0 | I5: =Calcuations!I5 -> 1584 | J5: =Calcuations!Z5 -> 1584 | K5: =Calcuations!AA5 -> 1584 | L5: =J5+(J5*0.05) -> 1663.2 | M5: =K5+(K5*0.05) -> 1663.2
A6: =Calcuations!A6 -> CFQ7TTC0HL8Z | B6: =Calcuations!B6 -> 5 | C6: =Calcuations!C6 -> 10-Year Audit Log Retention Add On for FLW | D6: =Calcuations!D6 -> P1Y | E6: =Calcuations!E6 -> Annual | F6: =Calcuations!F6 -> 1320 | G6: =Calcuations!G6 -> 1056 | H6: =Calcuations!H6 -> 0 | I6: =Calcuations!I6 -> 1056 | J6: =Calcuations!Z6 -> 1056 | K6: =Calcuations!AA6 -> 1056 | L6: =J6+(J6*0.05) -> 1108.8 | M6: =K6+(K6*0.05) -> 1108.8
A7: =Calcuations!A7 -> CFQ7TTC0HL8Z | B7: =Calcuations!B7 -> 1 | C7: =Calcuations!C7 -> 10-Year Audit Log Retention Add On | D7: =Calcuations!D7 -> P1M | E7: =Calcuations!E7 -> Monthly | F7: =Calcuations!F7 -> 198 | G7: =Calcuations!G7 -> 158.4 | H7: =Calcuations!H7 -> 0 | I7: =Calcuations!I7 -> 158.4 | J7: =Calcuations!Z7 -> 158.4 | K7: =Calcuations!AA7 -> 158.4 | L7: =J7+(J7*0.05) -> 166.32 | M7: =K7+(K7*0.05) -> 166.32
A8: =Calcuations!A8 -> CFQ7TTC0HL8Z | B8: =Calcuations!B8 -> 4 | C8: =Calcuations!C8 -> 10-Year Audit Log Retention Add On (Education Pricing) | D8: =Calcuations!D8 -> P1M | E8: =Calcuations!E8 -> Monthly | F8: =Calcuations!F8 -> 198 | G8: =Calcuations!G8 -> 158.4 | H8: =Calcuations!H8 -> 0 | I8: =Calcuations!I8 -> 158.4 | J8: =Calcuations!Z8 -> 158.4 | K8: =Calcuations!AA8 -> 158.4 | L8: =J8+(J8*0.05) -> 166.32 | M8: =K8+(K8*0.05) -> 166.32
A9: =Calcuations!A9 -> CFQ7TTC0HL8Z | B9: =Calcuations!B9 -> 5 | C9: =Calcuations!C9 -> 10-Year Audit Log Retention Add On for FLW | D9: =Calcuations!D9 -> P1M | E9: =Calcuations!E9 -> Monthly | F9: =Calcuations!F9 -> 132 | G9: =Calcuations!G9 -> 105.6 | H9: =Calcuations!H9 -> 0 | I9: =Calcuations!I9 -> 105.6 | J9: =Calcuations!Z9 -> 105.6 | K9: =Calcuations!AA9 -> 105.6 | L9: =J9+(J9*0.05) -> 110.88 | M9: =K9+(K9*0.05) -> 110.88
A10: =Calcuations!A10 -> CFQ7TTC0HL8Z | B10: =Calcuations!B10 -> 4 | C10: =Calcuations!C10 -> 10-Year Audit Log Retention Add On (Education Pricing) | D10: =Calcuations!D10 -> P1Y | E10: =Calcuations!E10 -> Monthly | F10: =Calcuations!F10 -> 2079 | G10: =Calcuations!G10 -> 1663.2 | H10: =Calcuations!H10 -> 0 | I10: =Calcuations!I10 -> 1663.2 | J10: =Calcuations!Z10 -> 1663.2 | K10: =Calcuations!AA10 -> 1663.2 | L10: =J10+(J10*0.05) -> 1746.36 | M10: =K10+(K10*0.05) -> 1746.36
A11: =Calcuations!A11 -> CFQ7TTC0RN26 | B11: =Calcuations!B11 -> 1 | C11: =Calcuations!C11 -> Advanced Data Residency | D11: =Calcuations!D11 -> P1Y | E11: =Calcuations!E11 -> Monthly | F11: =Calcuations!F11 -> 2079 | G11: =Calcuations!G11 -> 1663.2 | H11: =Calcuations!H11 -> 0 | I11: =Calcuations!I11 -> 1663.2 | J11: =Calcuations!Z11 -> 1663.2 | K11: =Calcuations!AA11 -> 1663.2 | L11: =J11+(J11*0.05) -> 1746.36 | M11: =K11+(K11*0.05) -> 1746.36
A12: =Calcuations!A12 -> CFQ7TTC0RN26 | B12: =Calcuations!B12 -> 1 | C12: =Calcuations!C12 -> Advanced Data Residency | D12: =Calcuations!D12 -> P3Y | E12: =Calcuations!E12 -> Triennial | F12: =Calcuations!F12 -> 5940 | G12: =Calcuations!G12 -> 4752 | H12: =Calcuations!H12 -> 0 | I12: =Calcuations!I12 -> 4752 | J12: =Calcuations!Z12 -> 4752 | K12: =Calcuations!AA12 -> 4752 | L12: =J12+(J12*0.05) -> 4989.6 | M12: =K12+(K12*0.05) -> 4989.6
A13: =Calcuations!A13 -> CFQ7TTC0RN26 | B13: =Calcuations!B13 -> 1 | C13: =Calcuations!C13 -> Advanced Data Residency | D13: =Calcuations!D13 -> P1Y | E13: =Calcuations!E13 -> Annual | F13: =Calcuations!F13 -> 1980 | G13: =Calcuations!G13 -> 1584 | H13: =Calcuations!H13 -> 0 | I13: =Calcuations!I13 -> 1584 | J13: =Calcuations!Z13 -> 1584 | K13: =Calcuations!AA13 -> 1584 | L13: =J13+(J13*0.05) -> 1663.2 | M13: =K13+(K13*0.05) -> 1663.2
... A4031: =Calcuations!A4031 -> 0 | B4031: =Calcuations!B4031 -> 0 | C4031: =Calcuations!C4031 -> Word LTSC for Mac 2024 | D4031: =Calcuations!D4031 -> 0 | E4031: =Calcuations!E4031 -> OneTime | F4031: =Calcuations!F4031 -> 1954 | G4031: =Calcuations!G4031 -> 1911.989 | H4031: =Calcuations!H4031 -> 0 | I4031: =Calcuations!I4031 -> 1911.989 | J4031: =Calcuations!Z4031 -> 1911.989 | K4031: =Calcuations!AA4031 -> 1911.989 | L4031: =J4031+(J4031*0.05) -> 2007.5884 | M4031: =K4031+(K4031*0.05) -> 2007.5884
