Workbook

Sheet Addendum
E2: Engagement: Microsoft 365 CSP incentive
A3: Product Name | B3: Product SKU Name | C3: Product ID | D3: SKU ID | E3: M365 CSP Core | F3: M365 CSP Global Strategic Product Accelerator – Tier 1 | G3: M365 CSP Global Strategic Product Accelerator – Tier 2 | H3: M365 CSP Global Calling and Conference PSTN Accelerator | I3: M365 CSP Growth Accelerator
A4: 10-year audit log retention | B4: 10-Year Audit Log Retention Add On | C4: CFQ7TTC0HL8Z | D4: 0001 | E4: x
A5: 10-year audit log retention | B5: 10-Year Audit Log Retention Add On - Extended Service Term | C5: CFQ7TTC0HL8Z | D5: 000B | E5: x
A6: 10-year audit log retention | B6: 10-Year Audit Log Retention Add On for EDU | C6: CFQ7TTC0HL8Z | D6: 0004 | E6: x
A7: 10-year audit log retention | B7: 10-Year Audit Log Retention Add On for EDU - Extended Service Term | C7: CFQ7TTC0HL8Z | D7: 000C | E7: x
A8: 10-year audit log retention | B8: 10-Year Audit Log Retention Add On for FLW | C8: CFQ7TTC0HL8Z | D8: 0005 | E8: x
A9: 10-year audit log retention | B9: 10-Year Audit Log Retention Add On for FLW - Extended Service Term | C9: CFQ7TTC0HL8Z | D9: 000D | E9: x
A10: Advanced Communications | B10: Advanced Communications | C10: CFQ7TTC0HDK0 | D10: 000B | E10: x
A11: Advanced Communications | B11: Advanced Communications | C11: CFQ7TTC0HDK0 | D11: 0001 | E11: x
A12: Advanced Communications | B12: Advanced Communications - Extended Service Term | C12: CFQ7TTC0HDK0 | D12: 000N | E12: x
A13: Advanced Communications | B13: Advanced Communications - Extended Service Term | C13: CFQ7TTC0HDK0 | D13: 000R | E13: x
A14: Advanced Communications | B14: Advanced Communications for faculty | C14: CFQ7TTC0HDK0 | D14: 000C | E14: x
A15: Advanced Communications | B15: Advanced Communications for faculty - Extended Service Term | C15: CFQ7TTC0HDK0 | D15: 000L | E15: x
... A19: Advanced Communications | B19: Advanced Communications for students - Extended Service Term | C19: CFQ7TTC0HDK0 | D19: 000M | E19: x
A20: Advanced Security Add-ons for Business Premium | B20: Microsoft Defender and Purview Suites for Microsoft 365 Business Premium - New | C20: CFQ7TTC10RSN | D20: 0003 | E20: x | F20: x | I20: x
A21: Advanced Security Add-ons for Business Premium | B21: Microsoft Defender and Purview Suites for Microsoft 365 Business Premium - New | C21: CFQ7TTC10RSN | D21: 0009 | E21: x | F21: x | I21: x
A22: Advanced Security Add-ons for Business Premium | B22: Microsoft Defender and Purview Suites for Microsoft 365 Business Premium - New - Extended Service Term | C22: CFQ7TTC10RSN | D22: 000P | E22: x | F22: x | I22: x
A23: Advanced Security Add-ons for Business Premium | B23: Microsoft Defender and Purview Suites for Microsoft 365 Business Premium - New - Extended Service Term | C23: CFQ7TTC10RSN | D23: 000L | E23: x | F23: x | I23: x
A24: Advanced Security Add-ons for Business Premium | B24: Microsoft Defender Suite for Microsoft 365 Business Premium - New | C24: CFQ7TTC10RSN | D24: 0001 | E24: x | F24: x | I24: x
A25: Advanced Security Add-ons for Business Premium | B25: Microsoft Defender Suite for Microsoft 365 Business Premium - New | C25: CFQ7TTC10RSN | D25: 0008 | E25: x | F25: x | I25: x
A26: Advanced Security Add-ons for Business Premium | B26: Microsoft Defender Suite for Microsoft 365 Business Premium - New - Extended Service Term | C26: CFQ7TTC10RSN | D26: 000M | E26: x | F26: x | I26: x
A27: Advanced Security Add-ons for Business Premium | B27: Microsoft Defender Suite for Microsoft 365 Business Premium - New - Extended Service Term | C27: CFQ7TTC10RSN | D27: 000K | E27: x | F27: x | I27: x
A28: Advanced Security Add-ons for Business Premium | B28: Microsoft Purview Suite for Microsoft 365 Business Premium - New | C28: CFQ7TTC10RSN | D28: 0002 | E28: x | F28: x | I28: x
A29: Advanced Security Add-ons for Business Premium | B29: Microsoft Purview Suite for Microsoft 365 Business Premium - New | C29: CFQ7TTC10RSN | D29: 0007 | E29: x | F29: x | I29: x
A30: Advanced Security Add-ons for Business Premium | B30: Microsoft Purview Suite for Microsoft 365 Business Premium - New - Extended Service Term | C30: CFQ7TTC10RSN | D30: 000N | E30: x | F30: x | I30: x
A31: Advanced Security Add-ons for Business Premium | B31: Microsoft Purview Suite for Microsoft 365 Business Premium - New - Extended Service Term | C31: CFQ7TTC10RSN | D31: 000J | E31: x | F31: x | I31: x
A32: Agent 365 | B32: Agent 365 | C32: CFQ7TTBZZR6G | D32: 0002 | E32: x | G32: x | I32: x
A33: Agent 365 | B33: Agent 365 - Extended Service Term | C33: CFQ7TTBZZR6G | D33: 0003 | E33: x | G33: x | I33: x
A34: Agent 365 | B34: Agent 365 (Education Faculty) | C34: CFQ7TTBZZR6G | D34: 0005 | E34: x | G34: x | I34: x
A35: Agent 365 | B35: Agent 365 (Education Faculty) | C35: CFQ7TTBZZR6G | D35: 0006 | E35: x | G35: x | I35: x
A36: Agent 365 | B36: Agent 365 (Education Faculty) - Extended Service Term | C36: CFQ7TTBZZR6G | D36: 0008 | E36: x | G36: x | I36: x
A37: Agent 365 | B37: Agent 365 (Education Student) | C37: CFQ7TTBZZR6G | D37: 0004 | E37: x | G37: x | I37: x
A38: Agent 365 | B38: Agent 365 (Education Student) | C38: CFQ7TTBZZR6G | D38: 0009 | E38: x | G38: x | I38: x
A39: Agent 365 | B39: Agent 365 (Education Student) - Extended Service Term | C39: CFQ7TTBZZR6G | D39: 0007 | E39: x | G39: x | I39: x
A40: Audio Conferencing (outbound, outside-US) | B40: Audio Conferencing (outbound, outside-US) | C40: CFQ7TTC0JL2W | D40: 0001 | E40: x
A41: Audio Conferencing (outbound, US) | B41: Audio Conferencing (outbound, US) | C41: CFQ7TTC0JL2S | D41: 0001 | E41: x
A42: Australia Calling Plan | B42: Australia Calling Plan | C42: CFQ7TTC0LHRW | D42: 0001 | E42: x
A43: Australia Calling Plan | B43: Australia Calling Plan - Extended Service Term | C43: CFQ7TTC0LHRW | D43: 0002 | E43: x
A44: Azure Active Directory Basic | B44: Azure Active Directory Basic | C44: CFQ7TTC0LH1X | D44: 000G | E44: x
A45: Azure Active Directory Basic | B45: Azure Active Directory Basic - Extended Service Term | C45: CFQ7TTC0LH1X | D45: 0014 | E45: x
A46: Azure Active Directory Basic | B46: Azure Active Directory Basic for faculty | C46: CFQ7TTC0LH1X | D46: 000D | E46: x
A47: Azure Active Directory Basic | B47: Azure Active Directory Basic for faculty - Extended Service Term | C47: CFQ7TTC0LH1X | D47: 0012 | E47: x
A48: Azure Active Directory Basic | B48: Azure Active Directory Basic for Government | C48: CFQ7TTC0LH1X | D48: 000P | E48: x
A49: Azure Active Directory Basic | B49: Azure Active Directory Basic for Government - Extended Service Term | C49: CFQ7TTC0LH1X | D49: 0017 | E49: x
A50: Azure Active Directory Basic | B50: Azure Active Directory Basic for students | C50: CFQ7TTC0LH1X | D50: 000F | E50: x
A51: Azure Active Directory Basic | B51: Azure Active Directory Basic for students - Extended Service Term | C51: CFQ7TTC0LH1X | D51: 0018 | E51: x
... A77: Azure Information Protection Premium P2 | B77: Azure Information Protection Premium P2 for student - Extended Service Term | C77: CFQ7TTC0LGTL | D77: 0026 | E77: x
A78: Chat session for Virtual Agent | B78: Chat session for Virtual Agent | C78: CFQ7TTC0LHT2 | D78: 0001 | E78: x | G78: x | I78: x
A79: Chat session for Virtual Agent | B79: Chat session for Virtual Agent - Extended Service Term | C79: CFQ7TTC0LHT2 | D79: 000L | E79: x | G79: x | I79: x
A80: Copilot | B80: Copilot | C80: CFQ7TTC0N8SX | D80: 0001 | E80: x | G80: x | I80: x
A81: Copilot | B81: Copilot | C81: CFQ7TTC0N8SX | D81: 0002 | E81: x | G81: x | I81: x
A82: Copilot | B82: Copilot - Extended Service Term | C82: CFQ7TTC0N8SX | D82: 0003 | E82: x | G82: x | I82: x
A83: Customer Lockbox | B83: Customer Lockbox | C83: CFQ7TTC0LHZF | D83: 0001 | E83: x
A84: Customer Lockbox | B84: Customer Lockbox - Extended Service Term | C84: CFQ7TTC0LHZF | D84: 0013 | E84: x
A85: Dynamics 365 Virtual Agent for Customer Service | B85: Dynamics 365 Virtual Agent for Customer Service | C85: CFQ7TTC0LHT1 | D85: 0001 | E85: x | G85: x | I85: x
A86: Dynamics 365 Virtual Agent for Customer Service | B86: Dynamics 365 Virtual Agent for Customer Service - Extended Service Term | C86: CFQ7TTC0LHT1 | D86: 000K | E86: x | G86: x | I86: x
A87: Dynamics 365 Virtual Agent for Customer Service User License | B87: Dynamics 365 Virtual Agent for Customer Service User License | C87: CFQ7TTC0LHS0 | D87: 0001 | E87: x | G87: x | I87: x
A88: Dynamics 365 Virtual Agent for Customer Service User License | B88: Dynamics 365 Virtual Agent for Customer Service User License - Extended Service Term | C88: CFQ7TTC0LHS0 | D88: 0009 | E88: x | G88: x | I88: x
A89: eCDN | B89: eCDN | C89: CFQ7TTC0JSQ1 | D89: 0002 | E89: x
A90: eCDN | B90: eCDN - Extended Service Term | C90: CFQ7TTC0JSQ1 | D90: 000C | E90: x
A91: eCDN | B91: eCDN GCC | C91: CFQ7TTC0JSQ1 | D91: 0005 | E91: x
A92: eCDN | B92: eCDN GCC - Extended Service Term | C92: CFQ7TTC0JSQ1 | D92: 000F | E92: x
A93: Enterprise Mobility + Security A3 | B93: Enterprise Mobility + Security A3 for Faculty | C93: CFQ7TTC0LSNC | D93: 0006 | E93: x
A94: Enterprise Mobility + Security A3 | B94: Enterprise Mobility + Security A3 for Faculty | C94: CFQ7TTC0LSNC | D94: 0002 | E94: x
A95: Enterprise Mobility + Security A3 | B95: Enterprise Mobility + Security A3 for Faculty - Extended Service Term | C95: CFQ7TTC0LSNC | D95: 000R | E95: x
A96: Enterprise Mobility + Security A3 | B96: Enterprise Mobility + Security A3 for Students | C96: CFQ7TTC0LSNC | D96: 0007 | E96: x
A97: Enterprise Mobility + Security A3 | B97: Enterprise Mobility + Security A3 for Students | C97: CFQ7TTC0LSNC | D97: 0003 | E97: x
A98: Enterprise Mobility + Security A3 | B98: Enterprise Mobility + Security A3 for Students - Extended Service Term | C98: CFQ7TTC0LSNC | D98: 000Q | E98: x
A99: Enterprise Mobility + Security A3 | B99: Enterprise Mobility + Security A3 for students use benefit | C99: CFQ7TTC0LSNC | D99: 0008 | E99: x
A100: Enterprise Mobility + Security A3 | B100: Enterprise Mobility + Security A3 for students use benefit | C100: CFQ7TTC0LSNC | D100: 0001 | E100: x
... A161: M365 F5 Insider Risk Management | B161: M365 F5 Insider Risk Management - Extended Service Term | C161: CFQ7TTC0QB3G | D161: 0009 | E161: x
A162: Microsoft 365 A1 | B162: Microsoft 365 A1 Legacy | C162: CFQ7TTC0J1HD | D162: 0004 | E162: x | F162: x | I162: x
A163: Microsoft 365 A1 | B163: Microsoft 365 A1 Legacy | C163: CFQ7TTC0J1HD | D163: 0001 | E163: x | F163: x | I163: x
A164: Microsoft 365 A1 | B164: Microsoft 365 A1 Legacy - Extended Service Term | C164: CFQ7TTC0J1HD | D164: 000G | E164: x | F164: x | I164: x
A165: Microsoft 365 A3 | B165: Microsoft 365 A3 - Unattended License for faculty | C165: CFQ7TTC0LHPL | D165: 0012 | E165: x | F165: x | I165: x
A166: Microsoft 365 A3 | B166: Microsoft 365 A3 - Unattended License for faculty - Extended Service Term | C166: CFQ7TTC0LHPL | D166: 002N | E166: x | F166: x | I166: x
A167: Microsoft 365 A3 | B167: Microsoft 365 A3 - Unattended License for students | C167: CFQ7TTC0LHPL | D167: 0013 | E167: x | F167: x | I167: x
A168: Microsoft 365 A3 | B168: Microsoft 365 A3 - Unattended License for students - Extended Service Term | C168: CFQ7TTC0LHPL | D168: 002L | E168: x | F168: x | I168: x
A169: Microsoft 365 A3 | B169: Microsoft 365 A3 for faculty | C169: CFQ7TTC0LHPL | D169: 000W | E169: x | F169: x | I169: x
A170: Microsoft 365 A3 | B170: Microsoft 365 A3 for faculty | C170: CFQ7TTC0LHPL | D170: 0001 | E170: x | F170: x | I170: x
A171: Microsoft 365 A3 | B171: Microsoft 365 A3 for faculty - Extended Service Term | C171: CFQ7TTC0LHPL | D171: 002G | E171: x | F171: x | I171: x
A172: Microsoft 365 A3 | B172: Microsoft 365 A3 for students | C172: CFQ7TTC0LHPL | D172: 000X | E172: x | F172: x | I172: x
A173: Microsoft 365 A3 | B173: Microsoft 365 A3 for students | C173: CFQ7TTC0LHPL | D173: 0002 | E173: x | F173: x | I173: x
... A177: Microsoft 365 A3 | B177: Microsoft 365 A3 student use benefits - Extended Service Term | C177: CFQ7TTC0LHPL | D177: 002C | E177: x | F177: x | I177: x
A178: Microsoft 365 A5 | B178: Microsoft 365 A5 for faculty | C178: CFQ7TTC0LHPJ | D178: 0015 | E178: x | G178: x | I178: x
A179: Microsoft 365 A5 | B179: Microsoft 365 A5 for faculty | C179: CFQ7TTC0LHPJ | D179: 0001 | E179: x | G179: x | I179: x
A180: Microsoft 365 A5 | B180: Microsoft 365 A5 for faculty - Extended Service Term | C180: CFQ7TTC0LHPJ | D180: 002Z | E180: x | G180: x | I180: x
A181: Microsoft 365 A5 | B181: Microsoft 365 A5 for students | C181: CFQ7TTC0LHPJ | D181: 0013 | E181: x | G181: x | I181: x
A182: Microsoft 365 A5 | B182: Microsoft 365 A5 for students - Extended Service Term | C182: CFQ7TTC0LHPJ | D182: 002W | E182: x | G182: x | I182: x
A183: Microsoft 365 A5 | B183: Microsoft 365 A5 with Calling Minutes for Faculty | C183: CFQ7TTC0LHPJ | D183: 0012 | E183: x | G183: x | I183: x
A184: Microsoft 365 A5 | B184: Microsoft 365 A5 with Calling Minutes for Faculty | C184: CFQ7TTC0LHPJ | D184: 001H | E184: x | G184: x | I184: x
A185: Microsoft 365 A5 | B185: Microsoft 365 A5 with Calling Minutes for Faculty - Extended Service Term | C185: CFQ7TTC0LHPJ | D185: 002V | E185: x | G185: x | I185: x
A186: Microsoft 365 A5 | B186: Microsoft 365 A5 with Calling Minutes for Students | C186: CFQ7TTC0LHPJ | D186: 0016 | E186: x | G186: x | I186: x
A187: Microsoft 365 A5 | B187: Microsoft 365 A5 with Calling Minutes for Students | C187: CFQ7TTC0LHPJ | D187: 001D | E187: x | G187: x | I187: x
A188: Microsoft 365 A5 | B188: Microsoft 365 A5 with Calling Minutes for Students - Extended Service Term | C188: CFQ7TTC0LHPJ | D188: 002R | E188: x | G188: x | I188: x
A189: Microsoft 365 A5 | B189: Microsoft 365 A5 without Audio Conferencing for faculty | C189: CFQ7TTC0LHPJ | D189: 0019 | E189: x | G189: x | I189: x
... A207: Microsoft 365 A5 student use benefits | B207: Microsoft 365 A5 student use benefits - Extended Service Term | C207: CFQ7TTC0LHP8 | D207: 0008 | E207: x | G207: x | I207: x
A208: Microsoft 365 Audio Conferencing | B208: Extended Dial-out Minutes to USA/CAN | C208: CFQ7TTC0LHSL | D208: 002B | E208: x | H208: x
A209: Microsoft 365 Audio Conferencing | B209: Extended Dial-out Minutes to USA/CAN | C209: CFQ7TTC0LHSL | D209: 0002 | E209: x | H209: x
...

Sheet Master Input Sheet
A1: Last Updated Date | B1: 46248
A2: Last Updated Time | B2: 0.80625
A3: Legend | B3: To be Filled
A7: ProductId | B7: SkuId | C7: SkuTitle | D7: TermDuration | E7: BillingPlan | F7: ERP Price | G7: UnitPrice/Catalogue Price
A8: CFQ7TTC0HL8Z | B8: 1 | C8: 10-Year Audit Log Retention Add On | D8: P1Y | E8: Monthly | F8: 2079 | G8: 1663.2
A9: CFQ7TTC0HL8Z | B9: 1 | C9: 10-Year Audit Log Retention Add On | D9: P1Y | E9: Annual | F9: 1980 | G9: 1584
A10: CFQ7TTC0HL8Z | B10: 5 | C10: 10-Year Audit Log Retention Add On for FLW | D10: P1Y | E10: Monthly | F10: 1386 | G10: 1108.8
A11: CFQ7TTC0HL8Z | B11: 4 | C11: 10-Year Audit Log Retention Add On (Education Pricing) | D11: P1Y | E11: Annual | F11: 1980 | G11: 1584
A12: CFQ7TTC0HL8Z | B12: 5 | C12: 10-Year Audit Log Retention Add On for FLW | D12: P1Y | E12: Annual | F12: 1320 | G12: 1056
A13: CFQ7TTC0HL8Z | B13: 1 | C13: 10-Year Audit Log Retention Add On | D13: P1M | E13: Monthly | F13: 198 | G13: 158.4
A14: CFQ7TTC0HL8Z | B14: 4 | C14: 10-Year Audit Log Retention Add On (Education Pricing) | D14: P1M | E14: Monthly | F14: 198 | G14: 158.4
A15: CFQ7TTC0HL8Z | B15: 5 | C15: 10-Year Audit Log Retention Add On for FLW | D15: P1M | E15: Monthly | F15: 132 | G15: 105.6
A16: CFQ7TTC0HL8Z | B16: 4 | C16: 10-Year Audit Log Retention Add On (Education Pricing) | D16: P1Y | E16: Monthly | F16: 2079 | G16: 1663.2
A17: CFQ7TTC0RN26 | B17: 1 | C17: Advanced Data Residency | D17: P1Y | E17: Monthly | F17: 2079 | G17: 1663.2
A18: CFQ7TTC0RN26 | B18: 1 | C18: Advanced Data Residency | D18: P3Y | E18: Triennial | F18: 5940 | G18: 4752
A19: CFQ7TTC0RN26 | B19: 1 | C19: Advanced Data Residency | D19: P1Y | E19: Annual | F19: 1980 | G19: 1584
A20: CFQ7TTC0RN26 | B20: 1 | C20: Advanced Data Residency | D20: P3Y | E20: Annual | F20: 5940 | G20: 4752
A21: CFQ7TTC0HDK0 | B21: 000B | C21: Advanced Communications (Non-Profit Pricing) | D21: P1Y | E21: Monthly | F21: 5040 | G21: 4536
A22: CFQ7TTC0HDK0 | B22: 000D | C22: Advanced Communications (Education Student Pricing) | D22: P1Y | E22: Monthly | F22: 1890 | G22: 1512
A23: CFQ7TTC0HDK0 | B23: 000C | C23: Advanced Communications (Education Faculty Pricing) | D23: P1Y | E23: Monthly | F23: 2520 | G23: 2016
A24: CFQ7TTC0HDK0 | B24: 000C | C24: Advanced Communications (Education Faculty Pricing) | D24: P1Y | E24: Annual | F24: 2400 | G24: 1920
A25: CFQ7TTC0HDK0 | B25: 000B | C25: Advanced Communications (Non-Profit Pricing) | D25: P1M | E25: Monthly | F25: 480 | G25: 432
A26: CFQ7TTC0HDK0 | B26: 000D | C26: Advanced Communications (Education Student Pricing) | D26: P1M | E26: Monthly | F26: 180 | G26: 144
A27: CFQ7TTC0HDK0 | B27: 1 | C27: Advanced Communications | D27: P1M | E27: Monthly | F27: 1200 | G27: 960
A28: CFQ7TTC0HDK0 | B28: 000B | C28: Advanced Communications (Non-Profit Pricing) | D28: P1Y | E28: Annual | F28: 4800 | G28: 4320
A29: CFQ7TTC0HDK0 | B29: 1 | C29: Advanced Communications | D29: P1Y | E29: Annual | F29: 12000 | G29: 9600
A30: CFQ7TTC0HDK0 | B30: 1 | C30: Advanced Communications | D30: P1Y | E30: Monthly | F30: 12600 | G30: 10080
A31: CFQ7TTC0HDK0 | B31: 000D | C31: Advanced Communications (Education Student Pricing) | D31: P1Y | E31: Annual | F31: 1800 | G31: 1440
A32: CFQ7TTC0HDK0 | B32: 000C | C32: Advanced Communications (Education Faculty Pricing) | D32: P1M | E32: Monthly | F32: 240 | G32: 192
A33: CFQ7TTC0LHQD | B33: 4 | C33: Advanced eDiscovery Storage (Education Faculty Pricing) | D33: P1M | E33: Monthly | F33: 1998 | G33: 1598.4
A34: CFQ7TTC0LHQD | B34: 4 | C34: Advanced eDiscovery Storage (Education Faculty Pricing) | D34: P1Y | E34: Monthly | F34: 20979 | G34: 16783.2
A35: CFQ7TTC0LHQD | B35: 4 | C35: Advanced eDiscovery Storage (Education Faculty Pricing) | D35: P1Y | E35: Annual | F35: 19980 | G35: 15984
A36: CFQ7TTC0LHQD | B36: 1 | C36: Advanced eDiscovery Storage | D36: P1Y | E36: Monthly | F36: 104832 | G36: 83865.6
A37: CFQ7TTC0LHQD | B37: 5 | C37: Advanced eDiscovery Storage (Non-Profit Pricing) | D37: P1Y | E37: Monthly | F37: 41958 | G37: 37762.2
A38: CFQ7TTC0LHQD | B38: 1 | C38: Advanced eDiscovery Storage | D38: P1Y | E38: Annual | F38: 99840 | G38: 79872
A39: CFQ7TTC0LHQD | B39: 5 | C39: Advanced eDiscovery Storage (Non-Profit Pricing) | D39: P1M | E39: Monthly | F39: 3996 | G39: 3596.4
A40: CFQ7TTC0LHQD | B40: 5 | C40: Advanced eDiscovery Storage (Non-Profit Pricing) | D40: P1Y | E40: Annual | F40: 39960 | G40: 35964
A41: CFQ7TTC0LHQD | B41: 1 | C41: Advanced eDiscovery Storage | D41: P1M | E41: Monthly | F41: 9984 | G41: 7987.2
A42: CFQ7TTC10RSN | B42: 3 | C42: Microsoft Defender and Purview Suites for Microsoft 365 Business Premium | D42: P1Y | E42: Monthly | F42: 15750 | G42: 12600
A43: CFQ7TTC10RSN | B43: 1 | C43: Microsoft Defender Suite for Microsoft 365 Business Premium | D43: P1Y | E43: Monthly | F43: 10458 | G43: 8366.4
A44: CFQ7TTC10RSN | B44: 7 | C44: Microsoft Purview Suite for Microsoft 365 Business Premium (Non-Profit Pricing) | D44: P1Y | E44: Monthly | F44: 4221 | G44: 3798.96
... A78: CFQ7TTC0LHRL | B78: 2 | C78: Dataverse Database Capacity add-on | D78: P1Y | E78: Annual | F78: 39960 | G78: 29970
A79: CFQ7TTC0LHRL | B79: 000H | C79: Dataverse Database Capacity add-on (Education Pricing) | D79: P1M | E79: Monthly | F79: 2796 | G79: 2097
A80: CFQ7TTC0LHRL | B80: 2 | C80: Dataverse Database Capacity add-on | D80: P1M | E80: Monthly | F80: 3996 | G80: 2997
A81: CFQ7TTC0LHRL | B81: 000J | C81: Dataverse Database Capacity add-on (Non-Profit Pricing) | D81: P1Y | E81: Monthly | F81: 29358 | G81: 26422.2
A82: CFQ7TTC0LHRL | B82: 2 | C82: Dataverse Database Capacity add-on | D82: P1Y | E82: Monthly | F82: 41958 | G82: 31468.56
A83: CFQ7TTC0LHRL | B83: 000H | C83: Dataverse Database Capacity add-on (Education Pricing) | D83: P1Y | E83: Monthly | F83: 29358 | G83: 22018.56
A84: CFQ7TTC0LHRL | B84: 000J | C84: Dataverse Database Capacity add-on (Non-Profit Pricing) | D84: P1M | E84: Monthly | F84: 2796 | G84: 2516.4
A85: CFQ7TTC0LHRL | B85: 000H | C85: Dataverse Database Capacity add-on (Education Pricing) | D85: P1Y | E85: Annual | F85: 27960 | G85: 20970
A86: CFQ7TTC0LHRL | B86: 000J | C86: Dataverse Database Capacity add-on (Non-Profit Pricing) | D86: P1Y | E86: Annual | F86: 27960 | G86: 25164
A87: CFQ7TTC0NCD7 | B87: 3 | C87: Dataverse Database Capacity add-on Tier 2 (Min 1000GB) | D87: P1M | E87: Monthly | F87: 2994 | G87: 2245.5
A88: CFQ7TTC0NCD7 | B88: 3 | C88: Dataverse Database Capacity add-on Tier 2 (Min 1000GB) | D88: P1Y | E88: Annual | F88: 29940 | G88: 22455
A89: CFQ7TTC0NCD7 | B89: 3 | C89: Dataverse Database Capacity add-on Tier 2 (Min 1000GB) | D89: P1Y | E89: Monthly | F89: 31437 | G89: 23577.72
A90: CFQ7TTC0NCD7 | B90: 2 | C90: Dataverse Database Capacity add-on Tier 2 (Min 1000GB) | D90: P1M | E90: None | F90: 0 | G90: 0
A91: CFQ7TTC0LHQ3 | B91: 1 | C91: Dataverse File Capacity add-on | D91: P1Y | E91: Monthly | F91: 2079 | G91: 1559.28
A92: CFQ7TTC0LHQ3 | B92: 000G | C92: Dataverse File Capacity add-on (Non-Profit Pricing) | D92: P1Y | E92: Monthly | F92: 1449 | G92: 1304.16
A93: CFQ7TTC0LHQ3 | B93: 1 | C93: Dataverse File Capacity add-on | D93: P1Y | E93: Annual | F93: 1980 | G93: 1485
A94: CFQ7TTC0LHQ3 | B94: 000G | C94: Dataverse File Capacity add-on (Non-Profit Pricing) | D94: P1Y | E94: Annual | F94: 1380 | G94: 1242
A95: CFQ7TTC0LHQ3 | B95: 000H | C95: Dataverse File Capacity add-on (Education Pricing) | D95: P1Y | E95: Annual | F95: 1380 | G95: 1035
A96: CFQ7TTC0LHQ3 | B96: 000H | C96: Dataverse File Capacity add-on (Education Pricing) | D96: P1Y | E96: Monthly | F96: 1449 | G96: 1086.72
A97: CFQ7TTC0LHQ3 | B97: 1 | C97: Dataverse File Capacity add-on | D97: P1M | E97: Monthly | F97: 198 | G97: 148.5
A98: CFQ7TTC0LHQ3 | B98: 000G | C98: Dataverse File Capacity add-on (Non-Profit Pricing) | D98: P1M | E98: Monthly | F98: 138 | G98: 124.2
A99: CFQ7TTC0LHQ3 | B99: 000H | C99: Dataverse File Capacity add-on (Education Pricing) | D99: P1M | E99: Monthly | F99: 138 | G99: 103.5
A100: CFQ7TTC0HBSL | B100: 000G | C100: Dataverse Log Capacity add-on (Non-Profit Pricing) | D100: P1Y | E100: Monthly | F100: 7308 | G100: 6577.2
A101: CFQ7TTC0HBSL | B101: 1 | C101: Dataverse Log Capacity add-on | D101: P1M | E101: Monthly | F101: 996 | G101: 747
A102: CFQ7TTC0HBSL | B102: 1 | C102: Dataverse Log Capacity add-on | D102: P1Y | E102: Monthly | F102: 10458 | G102: 7843.56
A103: CFQ7TTC0HBSL | B103: 1 | C103: Dataverse Log Capacity add-on | D103: P1Y | E103: Annual | F103: 9960 | G103: 7470
A104: CFQ7TTC0HBSL | B104: 000G | C104: Dataverse Log Capacity add-on (Non-Profit Pricing) | D104: P1Y | E104: Annual | F104: 6960 | G104: 6264
A105: CFQ7TTC0HBSL | B105: 000H | C105: Dataverse Log Capacity add-on (Education Pricing) | D105: P1Y | E105: Monthly | F105: 7308 | G105: 5481
A106: CFQ7TTC0HBSL | B106: 000H | C106: Dataverse Log Capacity add-on (Education Pricing) | D106: P1Y | E106: Annual | F106: 6960 | G106: 5220
A107: CFQ7TTC0HBSL | B107: 000G | C107: Dataverse Log Capacity add-on (Non-Profit Pricing) | D107: P1M | E107: Monthly | F107: 696 | G107: 626.4
A108: CFQ7TTC0HBSL | B108: 000H | C108: Dataverse Log Capacity add-on (Education Pricing) | D108: P1M | E108: Monthly | F108: 696 | G108: 522
A109: CFQ7TTC0LHXR | B109: 000B | C109: Dynamics 365 Operations-Order Lines (Education Pricing) | D109: P1M | E109: Monthly | F109: 34944 | G109: 24460.8
A110: CFQ7TTC0LHXR | B110: 1 | C110: Dynamics 365 Operations – Order Lines | D110: P1M | E110: Monthly | F110: 49914 | G110: 34939.8
A111: CFQ7TTC0LHXR | B111: 1 | C111: Dynamics 365 Operations – Order Lines | D111: P1Y | E111: Annual | F111: 499140 | G111: 349398
A112: CFQ7TTC0LHXR | B112: 1 | C112: Dynamics 365 Operations – Order Lines | D112: P1Y | E112: Monthly | F112: 524097 | G112: 366868
A113: CFQ7TTC0LHXR | B113: 000G | C113: Dynamics 365 Operations – Order Lines (Non-Profit Pricing) | D113: P1Y | E113: Monthly | F113: 131040 | G113: 117936
A114: CFQ7TTC0LHXR | B114: 000B | C114: Dynamics 365 Operations-Order Lines (Education Pricing) | D114: P1Y | E114: Monthly | F114: 366912 | G114: 256838.4
A115: CFQ7TTC0LHXR | B115: 000B | C115: Dynamics 365 Operations-Order Lines (Education Pricing) | D115: P1Y | E115: Annual | F115: 349440 | G115: 244608
A116: CFQ7TTC0LHXR | B116: 000G | C116: Dynamics 365 Operations – Order Lines (Non-Profit Pricing) | D116: P1M | E116: Monthly | F116: 12480 | G116: 11232
A117: CFQ7TTC0LHXR | B117: 000G | C117: Dynamics 365 Operations – Order Lines (Non-Profit Pricing) | D117: P1Y | E117: Annual | F117: 124800 | G117: 112320
A118: CFQ7TTC0LHWJ | B118: 1 | C118: Dynamics 365 Asset Management Addl Assets | D118: P1M | E118: Monthly | F118: 9984 | G118: 6988.8
A119: CFQ7TTC0LHWJ | B119: 1 | C119: Dynamics 365 Asset Management Addl Assets | D119: P3Y | E119: Monthly | F119: 314496 | G119: 220147.2
A120: CFQ7TTC0LHWJ | B120: 000C | C120: Dynamics 365 Asset Management Addl Assets (Education Faculty Pricing) | D120: P1Y | E120: Monthly | F120: 73395 | G120: 51376.56
A121: CFQ7TTC0LHWJ | B121: 1 | C121: Dynamics 365 Asset Management Addl Assets | D121: P1Y | E121: Annual | F121: 99840 | G121: 69888
A122: CFQ7TTC0LHWJ | B122: 000C | C122: Dynamics 365 Asset Management Addl Assets (Education Faculty Pricing) | D122: P1Y | E122: Annual | F122: 69900 | G122: 48930
A123: CFQ7TTC0LHWJ | B123: 000B | C123: Dynamics 365 Asset Management Addl Assets (Non-Profit Pricing) | D123: P1Y | E123: Annual | F123: 69900 | G123: 62910
A124: CFQ7TTC0LHWJ | B124: 000B | C124: Dynamics 365 Asset Management Addl Assets (Non-Profit Pricing) | D124: P1M | E124: Monthly | F124: 6990 | G124: 6291
A125: CFQ7TTC0LHWJ | B125: 000C | C125: Dynamics 365 Asset Management Addl Assets (Education Faculty Pricing) | D125: P1M | E125: Monthly | F125: 6990 | G125: 4893
A126: CFQ7TTC0LHWJ | B126: 1 | C126: Dynamics 365 Asset Management Addl Assets | D126: P3Y | E126: Triennial | F126: 299520 | G126: 209664
A127: CFQ7TTC0LHWJ | B127: 000B | C127: Dynamics 365 Asset Management Addl Assets (Non-Profit Pricing) | D127: P1Y | E127: Monthly | F127: 73395 | G127: 66055.56
A128: CFQ7TTC0LHWJ | B128: 1 | C128: Dynamics 365 Asset Management Addl Assets | D128: P3Y | E128: Annual | F128: 299520 | G128: 209664
A129: CFQ7TTC0LHWJ | B129: 1 | C129: Dynamics 365 Asset Management Addl Assets | D129: P1Y | E129: Monthly | F129: 104832 | G129: 73382.4
A130: CFQ7TTC0HD7P | B130: 3 | C130: Dynamics 365 Business Central Additional Environment Addon (Education Faculty Pricing) | D130: P1Y | E130: Annual | F130: 164700 | G130: 115290
A131: CFQ7TTC0HD7P | B131: 1 | C131: Dynamics 365 Business Central Additional Environment Addon | D131: P1M | E131: Monthly | F131: 29952 | G131: 20966.4
A132: CFQ7TTC0HD7P | B132: 4 | C132: Dynamics 365 Business Central Additional Environment Addon (Non-Profit Pricing) | D132: P1Y | E132: Annual | F132: 119820 | G132: 107838
A133: CFQ7TTC0HD7P | B133: 3 | C133: Dynamics 365 Business Central Additional Environment Addon (Education Faculty Pricing) | D133: P1M | E133: Monthly | F133: 16470 | G133: 11529
A134: CFQ7TTC0HD7P | B134: 1 | C134: Dynamics 365 Business Central Additional Environment Addon | D134: P1Y | E134: Monthly | F134: 314496 | G134: 220147.2
A135: CFQ7TTC0HD7P | B135: 4 | C135: Dynamics 365 Business Central Additional Environment Addon (Non-Profit Pricing) | D135: P1Y | E135: Monthly | F135: 125811 | G135: 113230
A136: CFQ7TTC0HD7P | B136: 1 | C136: Dynamics 365 Business Central Additional Environment Addon | D136: P1Y | E136: Annual | F136: 299520 | G136: 209664
...

Sheet Calculation Sheet
A2: ProductId | B2: SkuId | C2: SkuTitle | D2: TermDuration | E2: BillingPlan | F2: Segment | G2: ERP Price | H2: UnitPrice | I2: M365 CSP Core Rebate (Disti) | J2: Distributor Product Tier 1 | K2: Distributor Product Tier 2 | L2: Distributor Growth Accelerator | M2: Expected Disti Discounting to Skysecure | N2: Expected Disti Pricing to Skysecure
A3: CFQ7TTC0HL8Z | B3: 1 | C3: 10-Year Audit Log Retention Add On | D3: P1Y | E3: Monthly | F3: Commercial | G3: 2079 | H3: 1663.2 | I3: =IF(COUNTIFS(Addendum!C:C,A3,Addendum!D:D,IF(ISNUMBER(B3),TEXT(B3,"0000"),B3),Addendum!E:E,"X")>0,4%,0) -> 0.04 | J3: =IF(COUNTIFS(Addendum!C:C,A3,Addendum!D:D,IF(ISNUMBER(B3),TEXT(B3,"0000"),B3),Addendum!F:F,"X")>0,2.5%,0) -> 0 | K3: =IF(COUNTIFS(Addendum!C:C,A3,Addendum!D:D,IF(ISNUMBER(B3),TEXT(B3,"0000"),B3),Addendum!G:G,"X")>0,7%,0) -> 0 | L3: =IF(COUNTIFS(Addendum!C:C,A3,Addendum!D:D,IF(ISNUMBER(B3),TEXT(B3,"0000"),B3),Addendum!I:I,"X")>0,10%,0) -> 0 | M3: =IF(AND(I3=0%,J3=0%,K3=0%,L3=0%),0%, IF(OR(TRIM(E3)="OneTime",TRIM(D3)=""),0%, IF( OR( TRIM(D3)="P1M", AND(TRIM(D3)="P1Y",TRIM(E3)="Monthly"), AND(TRIM(D3)="P3Y",TRIM(E3)="Monthly") ), IF(AND(I3=4%,J3=0%,K3=0%,L3=0%),1%, IF(AND(I3=4%,J3=2.5%,K3=0%,L3=10%),2%, IF(AND(I3=4%,J3=0%,K3=7%,L3=10%),3%,0%))), IF( OR( AND(TRIM(D3)="P1Y",TRIM(E3)="Annual"), AND(TRIM(D3)="P3Y",TRIM(E3)="Annual"), AND(TRIM(D3)="P3Y",TRIM(E3)="Triennial") ), IF(AND(I3=4%,J3=0%,K3=0%,L3=0%),3%, IF(AND(I3=4%,J3=2.5%,K3=0%,L3=10%),10%, IF(AND(I3=4%,J3=0%,K3=7%,L3=10%),14%,0%))), 0% )))) -> 0.01 | N3: =H3-(H3*M3) -> 1646.568
A4: CFQ7TTC0HL8Z | B4: 1 | C4: 10-Year Audit Log Retention Add On | D4: P1Y | E4: Annual | F4: Commercial | G4: 1980 | H4: 1584 | I4: =IF(COUNTIFS(Addendum!C:C,A4,Addendum!D:D,IF(ISNUMBER(B4),TEXT(B4,"0000"),B4),Addendum!E:E,"X")>0,4%,0) -> 0.04 | J4: =IF(COUNTIFS(Addendum!C:C,A4,Addendum!D:D,IF(ISNUMBER(B4),TEXT(B4,"0000"),B4),Addendum!F:F,"X")>0,2.5%,0) -> 0 | K4: =IF(COUNTIFS(Addendum!C:C,A4,Addendum!D:D,IF(ISNUMBER(B4),TEXT(B4,"0000"),B4),Addendum!G:G,"X")>0,7%,0) -> 0 | L4: =IF(COUNTIFS(Addendum!C:C,A4,Addendum!D:D,IF(ISNUMBER(B4),TEXT(B4,"0000"),B4),Addendum!I:I,"X")>0,10%,0) -> 0 | M4: =IF(AND(I4=0%,J4=0%,K4=0%,L4=0%),0%, IF(OR(TRIM(E4)="OneTime",TRIM(D4)=""),0%, IF( OR( TRIM(D4)="P1M", AND(TRIM(D4)="P1Y",TRIM(E4)="Monthly"), AND(TRIM(D4)="P3Y",TRIM(E4)="Monthly") ), IF(AND(I4=4%,J4=0%,K4=0%,L4=0%),1%, IF(AND(I4=4%,J4=2.5%,K4=0%,L4=10%),2%, IF(AND(I4=4%,J4=0%,K4=7%,L4=10%),3%,0%))), IF( OR( AND(TRIM(D4)="P1Y",TRIM(E4)="Annual"), AND(TRIM(D4)="P3Y",TRIM(E4)="Annual"), AND(TRIM(D4)="P3Y",TRIM(E4)="Triennial") ), IF(AND(I4=4%,J4=0%,K4=0%,L4=0%),3%, IF(AND(I4=4%,J4=2.5%,K4=0%,L4=10%),10%, IF(AND(I4=4%,J4=0%,K4=7%,L4=10%),14%,0%))), 0% )))) -> 0.03 | N4: =H4-(H4*M4) -> 1536.48
A5: CFQ7TTC0HL8Z | B5: 5 | C5: 10-Year Audit Log Retention Add On for FLW | D5: P1Y | E5: Monthly | F5: Commercial | G5: 1386 | H5: 1108.8 | I5: =IF(COUNTIFS(Addendum!C:C,A5,Addendum!D:D,IF(ISNUMBER(B5),TEXT(B5,"0000"),B5),Addendum!E:E,"X")>0,4%,0) -> 0.04 | J5: =IF(COUNTIFS(Addendum!C:C,A5,Addendum!D:D,IF(ISNUMBER(B5),TEXT(B5,"0000"),B5),Addendum!F:F,"X")>0,2.5%,0) -> 0 | K5: =IF(COUNTIFS(Addendum!C:C,A5,Addendum!D:D,IF(ISNUMBER(B5),TEXT(B5,"0000"),B5),Addendum!G:G,"X")>0,7%,0) -> 0 | L5: =IF(COUNTIFS(Addendum!C:C,A5,Addendum!D:D,IF(ISNUMBER(B5),TEXT(B5,"0000"),B5),Addendum!I:I,"X")>0,10%,0) -> 0 | M5: =IF(AND(I5=0%,J5=0%,K5=0%,L5=0%),0%, IF(OR(TRIM(E5)="OneTime",TRIM(D5)=""),0%, IF( OR( TRIM(D5)="P1M", AND(TRIM(D5)="P1Y",TRIM(E5)="Monthly"), AND(TRIM(D5)="P3Y",TRIM(E5)="Monthly") ), IF(AND(I5=4%,J5=0%,K5=0%,L5=0%),1%, IF(AND(I5=4%,J5=2.5%,K5=0%,L5=10%),2%, IF(AND(I5=4%,J5=0%,K5=7%,L5=10%),3%,0%))), IF( OR( AND(TRIM(D5)="P1Y",TRIM(E5)="Annual"), AND(TRIM(D5)="P3Y",TRIM(E5)="Annual"), AND(TRIM(D5)="P3Y",TRIM(E5)="Triennial") ), IF(AND(I5=4%,J5=0%,K5=0%,L5=0%),3%, IF(AND(I5=4%,J5=2.5%,K5=0%,L5=10%),10%, IF(AND(I5=4%,J5=0%,K5=7%,L5=10%),14%,0%))), 0% )))) -> 0.01 | N5: =H5-(H5*M5) -> 1097.712
A6: CFQ7TTC0HL8Z | B6: 4 | C6: 10-Year Audit Log Retention Add On (Education Pricing) | D6: P1Y | E6: Annual | F6: Education | G6: 1980 | H6: 1584 | I6: =IF(COUNTIFS(Addendum!C:C,A6,Addendum!D:D,IF(ISNUMBER(B6),TEXT(B6,"0000"),B6),Addendum!E:E,"X")>0,4%,0) -> 0.04 | J6: =IF(COUNTIFS(Addendum!C:C,A6,Addendum!D:D,IF(ISNUMBER(B6),TEXT(B6,"0000"),B6),Addendum!F:F,"X")>0,2.5%,0) -> 0 | K6: =IF(COUNTIFS(Addendum!C:C,A6,Addendum!D:D,IF(ISNUMBER(B6),TEXT(B6,"0000"),B6),Addendum!G:G,"X")>0,7%,0) -> 0 | L6: =IF(COUNTIFS(Addendum!C:C,A6,Addendum!D:D,IF(ISNUMBER(B6),TEXT(B6,"0000"),B6),Addendum!I:I,"X")>0,10%,0) -> 0 | M6: =IF(AND(I6=0%,J6=0%,K6=0%,L6=0%),0%, IF(OR(TRIM(E6)="OneTime",TRIM(D6)=""),0%, IF( OR( TRIM(D6)="P1M", AND(TRIM(D6)="P1Y",TRIM(E6)="Monthly"), AND(TRIM(D6)="P3Y",TRIM(E6)="Monthly") ), IF(AND(I6=4%,J6=0%,K6=0%,L6=0%),1%, IF(AND(I6=4%,J6=2.5%,K6=0%,L6=10%),2%, IF(AND(I6=4%,J6=0%,K6=7%,L6=10%),3%,0%))), IF( OR( AND(TRIM(D6)="P1Y",TRIM(E6)="Annual"), AND(TRIM(D6)="P3Y",TRIM(E6)="Annual"), AND(TRIM(D6)="P3Y",TRIM(E6)="Triennial") ), IF(AND(I6=4%,J6=0%,K6=0%,L6=0%),3%, IF(AND(I6=4%,J6=2.5%,K6=0%,L6=10%),10%, IF(AND(I6=4%,J6=0%,K6=7%,L6=10%),14%,0%))), 0% )))) -> 0.03 | N6: =H6-(H6*M6) -> 1536.48
A7: CFQ7TTC0HL8Z | B7: 5 | C7: 10-Year Audit Log Retention Add On for FLW | D7: P1Y | E7: Annual | F7: Commercial | G7: 1320 | H7: 1056 | I7: =IF(COUNTIFS(Addendum!C:C,A7,Addendum!D:D,IF(ISNUMBER(B7),TEXT(B7,"0000"),B7),Addendum!E:E,"X")>0,4%,0) -> 0.04 | J7: =IF(COUNTIFS(Addendum!C:C,A7,Addendum!D:D,IF(ISNUMBER(B7),TEXT(B7,"0000"),B7),Addendum!F:F,"X")>0,2.5%,0) -> 0 | K7: =IF(COUNTIFS(Addendum!C:C,A7,Addendum!D:D,IF(ISNUMBER(B7),TEXT(B7,"0000"),B7),Addendum!G:G,"X")>0,7%,0) -> 0 | L7: =IF(COUNTIFS(Addendum!C:C,A7,Addendum!D:D,IF(ISNUMBER(B7),TEXT(B7,"0000"),B7),Addendum!I:I,"X")>0,10%,0) -> 0 | M7: =IF(AND(I7=0%,J7=0%,K7=0%,L7=0%),0%, IF(OR(TRIM(E7)="OneTime",TRIM(D7)=""),0%, IF( OR( TRIM(D7)="P1M", AND(TRIM(D7)="P1Y",TRIM(E7)="Monthly"), AND(TRIM(D7)="P3Y",TRIM(E7)="Monthly") ), IF(AND(I7=4%,J7=0%,K7=0%,L7=0%),1%, IF(AND(I7=4%,J7=2.5%,K7=0%,L7=10%),2%, IF(AND(I7=4%,J7=0%,K7=7%,L7=10%),3%,0%))), IF( OR( AND(TRIM(D7)="P1Y",TRIM(E7)="Annual"), AND(TRIM(D7)="P3Y",TRIM(E7)="Annual"), AND(TRIM(D7)="P3Y",TRIM(E7)="Triennial") ), IF(AND(I7=4%,J7=0%,K7=0%,L7=0%),3%, IF(AND(I7=4%,J7=2.5%,K7=0%,L7=10%),10%, IF(AND(I7=4%,J7=0%,K7=7%,L7=10%),14%,0%))), 0% )))) -> 0.03 | N7: =H7-(H7*M7) -> 1024.32
A8: CFQ7TTC0HL8Z | B8: 1 | C8: 10-Year Audit Log Retention Add On | D8: P1M | E8: Monthly | F8: Commercial | G8: 198 | H8: 158.4 | I8: =IF(COUNTIFS(Addendum!C:C,A8,Addendum!D:D,IF(ISNUMBER(B8),TEXT(B8,"0000"),B8),Addendum!E:E,"X")>0,4%,0) -> 0.04 | J8: =IF(COUNTIFS(Addendum!C:C,A8,Addendum!D:D,IF(ISNUMBER(B8),TEXT(B8,"0000"),B8),Addendum!F:F,"X")>0,2.5%,0) -> 0 | K8: =IF(COUNTIFS(Addendum!C:C,A8,Addendum!D:D,IF(ISNUMBER(B8),TEXT(B8,"0000"),B8),Addendum!G:G,"X")>0,7%,0) -> 0 | L8: =IF(COUNTIFS(Addendum!C:C,A8,Addendum!D:D,IF(ISNUMBER(B8),TEXT(B8,"0000"),B8),Addendum!I:I,"X")>0,10%,0) -> 0 | M8: =IF(AND(I8=0%,J8=0%,K8=0%,L8=0%),0%, IF(OR(TRIM(E8)="OneTime",TRIM(D8)=""),0%, IF( OR( TRIM(D8)="P1M", AND(TRIM(D8)="P1Y",TRIM(E8)="Monthly"), AND(TRIM(D8)="P3Y",TRIM(E8)="Monthly") ), IF(AND(I8=4%,J8=0%,K8=0%,L8=0%),1%, IF(AND(I8=4%,J8=2.5%,K8=0%,L8=10%),2%, IF(AND(I8=4%,J8=0%,K8=7%,L8=10%),3%,0%))), IF( OR( AND(TRIM(D8)="P1Y",TRIM(E8)="Annual"), AND(TRIM(D8)="P3Y",TRIM(E8)="Annual"), AND(TRIM(D8)="P3Y",TRIM(E8)="Triennial") ), IF(AND(I8=4%,J8=0%,K8=0%,L8=0%),3%, IF(AND(I8=4%,J8=2.5%,K8=0%,L8=10%),10%, IF(AND(I8=4%,J8=0%,K8=7%,L8=10%),14%,0%))), 0% )))) -> 0.01 | N8: =H8-(H8*M8) -> 156.816
A9: CFQ7TTC0HL8Z | B9: 4 | C9: 10-Year Audit Log Retention Add On (Education Pricing) | D9: P1M | E9: Monthly | F9: Education | G9: 198 | H9: 158.4 | I9: =IF(COUNTIFS(Addendum!C:C,A9,Addendum!D:D,IF(ISNUMBER(B9),TEXT(B9,"0000"),B9),Addendum!E:E,"X")>0,4%,0) -> 0.04 | J9: =IF(COUNTIFS(Addendum!C:C,A9,Addendum!D:D,IF(ISNUMBER(B9),TEXT(B9,"0000"),B9),Addendum!F:F,"X")>0,2.5%,0) -> 0 | K9: =IF(COUNTIFS(Addendum!C:C,A9,Addendum!D:D,IF(ISNUMBER(B9),TEXT(B9,"0000"),B9),Addendum!G:G,"X")>0,7%,0) -> 0 | L9: =IF(COUNTIFS(Addendum!C:C,A9,Addendum!D:D,IF(ISNUMBER(B9),TEXT(B9,"0000"),B9),Addendum!I:I,"X")>0,10%,0) -> 0 | M9: =IF(AND(I9=0%,J9=0%,K9=0%,L9=0%),0%, IF(OR(TRIM(E9)="OneTime",TRIM(D9)=""),0%, IF( OR( TRIM(D9)="P1M", AND(TRIM(D9)="P1Y",TRIM(E9)="Monthly"), AND(TRIM(D9)="P3Y",TRIM(E9)="Monthly") ), IF(AND(I9=4%,J9=0%,K9=0%,L9=0%),1%, IF(AND(I9=4%,J9=2.5%,K9=0%,L9=10%),2%, IF(AND(I9=4%,J9=0%,K9=7%,L9=10%),3%,0%))), IF( OR( AND(TRIM(D9)="P1Y",TRIM(E9)="Annual"), AND(TRIM(D9)="P3Y",TRIM(E9)="Annual"), AND(TRIM(D9)="P3Y",TRIM(E9)="Triennial") ), IF(AND(I9=4%,J9=0%,K9=0%,L9=0%),3%, IF(AND(I9=4%,J9=2.5%,K9=0%,L9=10%),10%, IF(AND(I9=4%,J9=0%,K9=7%,L9=10%),14%,0%))), 0% )))) -> 0.01 | N9: =H9-(H9*M9) -> 156.816
A10: CFQ7TTC0HL8Z | B10: 5 | C10: 10-Year Audit Log Retention Add On for FLW | D10: P1M | E10: Monthly | F10: Commercial | G10: 132 | H10: 105.6 | I10: =IF(COUNTIFS(Addendum!C:C,A10,Addendum!D:D,IF(ISNUMBER(B10),TEXT(B10,"0000"),B10),Addendum!E:E,"X")>0,4%,0) -> 0.04 | J10: =IF(COUNTIFS(Addendum!C:C,A10,Addendum!D:D,IF(ISNUMBER(B10),TEXT(B10,"0000"),B10),Addendum!F:F,"X")>0,2.5%,0) -> 0 | K10: =IF(COUNTIFS(Addendum!C:C,A10,Addendum!D:D,IF(ISNUMBER(B10),TEXT(B10,"0000"),B10),Addendum!G:G,"X")>0,7%,0) -> 0 | L10: =IF(COUNTIFS(Addendum!C:C,A10,Addendum!D:D,IF(ISNUMBER(B10),TEXT(B10,"0000"),B10),Addendum!I:I,"X")>0,10%,0) -> 0 | M10: =IF(AND(I10=0%,J10=0%,K10=0%,L10=0%),0%, IF(OR(TRIM(E10)="OneTime",TRIM(D10)=""),0%, IF( OR( TRIM(D10)="P1M", AND(TRIM(D10)="P1Y",TRIM(E10)="Monthly"), AND(TRIM(D10)="P3Y",TRIM(E10)="Monthly") ), IF(AND(I10=4%,J10=0%,K10=0%,L10=0%),1%, IF(AND(I10=4%,J10=2.5%,K10=0%,L10=10%),2%, IF(AND(I10=4%,J10=0%,K10=7%,L10=10%),3%,0%))), IF( OR( AND(TRIM(D10)="P1Y",TRIM(E10)="Annual"), AND(TRIM(D10)="P3Y",TRIM(E10)="Annual"), AND(TRIM(D10)="P3Y",TRIM(E10)="Triennial") ), IF(AND(I10=4%,J10=0%,K10=0%,L10=0%),3%, IF(AND(I10=4%,J10=2.5%,K10=0%,L10=10%),10%, IF(AND(I10=4%,J10=0%,K10=7%,L10=10%),14%,0%))), 0% )))) -> 0.01 | N10: =H10-(H10*M10) -> 104.544
A11: CFQ7TTC0HL8Z | B11: 4 | C11: 10-Year Audit Log Retention Add On (Education Pricing) | D11: P1Y | E11: Monthly | F11: Education | G11: 2079 | H11: 1663.2 | I11: =IF(COUNTIFS(Addendum!C:C,A11,Addendum!D:D,IF(ISNUMBER(B11),TEXT(B11,"0000"),B11),Addendum!E:E,"X")>0,4%,0) -> 0.04 | J11: =IF(COUNTIFS(Addendum!C:C,A11,Addendum!D:D,IF(ISNUMBER(B11),TEXT(B11,"0000"),B11),Addendum!F:F,"X")>0,2.5%,0) -> 0 | K11: =IF(COUNTIFS(Addendum!C:C,A11,Addendum!D:D,IF(ISNUMBER(B11),TEXT(B11,"0000"),B11),Addendum!G:G,"X")>0,7%,0) -> 0 | L11: =IF(COUNTIFS(Addendum!C:C,A11,Addendum!D:D,IF(ISNUMBER(B11),TEXT(B11,"0000"),B11),Addendum!I:I,"X")>0,10%,0) -> 0 | M11: =IF(AND(I11=0%,J11=0%,K11=0%,L11=0%),0%, IF(OR(TRIM(E11)="OneTime",TRIM(D11)=""),0%, IF( OR( TRIM(D11)="P1M", AND(TRIM(D11)="P1Y",TRIM(E11)="Monthly"), AND(TRIM(D11)="P3Y",TRIM(E11)="Monthly") ), IF(AND(I11=4%,J11=0%,K11=0%,L11=0%),1%, IF(AND(I11=4%,J11=2.5%,K11=0%,L11=10%),2%, IF(AND(I11=4%,J11=0%,K11=7%,L11=10%),3%,0%))), IF( OR( AND(TRIM(D11)="P1Y",TRIM(E11)="Annual"), AND(TRIM(D11)="P3Y",TRIM(E11)="Annual"), AND(TRIM(D11)="P3Y",TRIM(E11)="Triennial") ), IF(AND(I11=4%,J11=0%,K11=0%,L11=0%),3%, IF(AND(I11=4%,J11=2.5%,K11=0%,L11=10%),10%, IF(AND(I11=4%,J11=0%,K11=7%,L11=10%),14%,0%))), 0% )))) -> 0.01 | N11: =H11-(H11*M11) -> 1646.568
A12: CFQ7TTC0RN26 | B12: 1 | C12: Advanced Data Residency | D12: P1Y | E12: Monthly | F12: Commercial | G12: 2079 | H12: 1663.2 | I12: =IF(COUNTIFS(Addendum!C:C,A12,Addendum!D:D,IF(ISNUMBER(B12),TEXT(B12,"0000"),B12),Addendum!E:E,"X")>0,4%,0) -> 0 | J12: =IF(COUNTIFS(Addendum!C:C,A12,Addendum!D:D,IF(ISNUMBER(B12),TEXT(B12,"0000"),B12),Addendum!F:F,"X")>0,2.5%,0) -> 0 | K12: =IF(COUNTIFS(Addendum!C:C,A12,Addendum!D:D,IF(ISNUMBER(B12),TEXT(B12,"0000"),B12),Addendum!G:G,"X")>0,7%,0) -> 0 | L12: =IF(COUNTIFS(Addendum!C:C,A12,Addendum!D:D,IF(ISNUMBER(B12),TEXT(B12,"0000"),B12),Addendum!I:I,"X")>0,10%,0) -> 0 | M12: =IF(AND(I12=0%,J12=0%,K12=0%,L12=0%),0%, IF(OR(TRIM(E12)="OneTime",TRIM(D12)=""),0%, IF( OR( TRIM(D12)="P1M", AND(TRIM(D12)="P1Y",TRIM(E12)="Monthly"), AND(TRIM(D12)="P3Y",TRIM(E12)="Monthly") ), IF(AND(I12=4%,J12=0%,K12=0%,L12=0%),1%, IF(AND(I12=4%,J12=2.5%,K12=0%,L12=10%),2%, IF(AND(I12=4%,J12=0%,K12=7%,L12=10%),3%,0%))), IF( OR( AND(TRIM(D12)="P1Y",TRIM(E12)="Annual"), AND(TRIM(D12)="P3Y",TRIM(E12)="Annual"), AND(TRIM(D12)="P3Y",TRIM(E12)="Triennial") ), IF(AND(I12=4%,J12=0%,K12=0%,L12=0%),3%, IF(AND(I12=4%,J12=2.5%,K12=0%,L12=10%),10%, IF(AND(I12=4%,J12=0%,K12=7%,L12=10%),14%,0%))), 0% )))) -> 0 | N12: =H12-(H12*M12) -> 1663.2
A13: CFQ7TTC0RN26 | B13: 1 | C13: Advanced Data Residency | D13: P3Y | E13: Triennial | F13: Commercial | G13: 5940 | H13: 4752 | I13: =IF(COUNTIFS(Addendum!C:C,A13,Addendum!D:D,IF(ISNUMBER(B13),TEXT(B13,"0000"),B13),Addendum!E:E,"X")>0,4%,0) -> 0 | J13: =IF(COUNTIFS(Addendum!C:C,A13,Addendum!D:D,IF(ISNUMBER(B13),TEXT(B13,"0000"),B13),Addendum!F:F,"X")>0,2.5%,0) -> 0 | K13: =IF(COUNTIFS(Addendum!C:C,A13,Addendum!D:D,IF(ISNUMBER(B13),TEXT(B13,"0000"),B13),Addendum!G:G,"X")>0,7%,0) -> 0 | L13: =IF(COUNTIFS(Addendum!C:C,A13,Addendum!D:D,IF(ISNUMBER(B13),TEXT(B13,"0000"),B13),Addendum!I:I,"X")>0,10%,0) -> 0 | M13: =IF(AND(I13=0%,J13=0%,K13=0%,L13=0%),0%, IF(OR(TRIM(E13)="OneTime",TRIM(D13)=""),0%, IF( OR( TRIM(D13)="P1M", AND(TRIM(D13)="P1Y",TRIM(E13)="Monthly"), AND(TRIM(D13)="P3Y",TRIM(E13)="Monthly") ), IF(AND(I13=4%,J13=0%,K13=0%,L13=0%),1%, IF(AND(I13=4%,J13=2.5%,K13=0%,L13=10%),2%, IF(AND(I13=4%,J13=0%,K13=7%,L13=10%),3%,0%))), IF( OR( AND(TRIM(D13)="P1Y",TRIM(E13)="Annual"), AND(TRIM(D13)="P3Y",TRIM(E13)="Annual"), AND(TRIM(D13)="P3Y",TRIM(E13)="Triennial") ), IF(AND(I13=4%,J13=0%,K13=0%,L13=0%),3%, IF(AND(I13=4%,J13=2.5%,K13=0%,L13=10%),10%, IF(AND(I13=4%,J13=0%,K13=7%,L13=10%),14%,0%))), 0% )))) -> 0 | N13: =H13-(H13*M13) -> 4752
A14: CFQ7TTC0RN26 | B14: 1 | C14: Advanced Data Residency | D14: P1Y | E14: Annual | F14: Commercial | G14: 1980 | H14: 1584 | I14: =IF(COUNTIFS(Addendum!C:C,A14,Addendum!D:D,IF(ISNUMBER(B14),TEXT(B14,"0000"),B14),Addendum!E:E,"X")>0,4%,0) -> 0 | J14: =IF(COUNTIFS(Addendum!C:C,A14,Addendum!D:D,IF(ISNUMBER(B14),TEXT(B14,"0000"),B14),Addendum!F:F,"X")>0,2.5%,0) -> 0 | K14: =IF(COUNTIFS(Addendum!C:C,A14,Addendum!D:D,IF(ISNUMBER(B14),TEXT(B14,"0000"),B14),Addendum!G:G,"X")>0,7%,0) -> 0 | L14: =IF(COUNTIFS(Addendum!C:C,A14,Addendum!D:D,IF(ISNUMBER(B14),TEXT(B14,"0000"),B14),Addendum!I:I,"X")>0,10%,0) -> 0 | M14: =IF(AND(I14=0%,J14=0%,K14=0%,L14=0%),0%, IF(OR(TRIM(E14)="OneTime",TRIM(D14)=""),0%, IF( OR( TRIM(D14)="P1M", AND(TRIM(D14)="P1Y",TRIM(E14)="Monthly"), AND(TRIM(D14)="P3Y",TRIM(E14)="Monthly") ), IF(AND(I14=4%,J14=0%,K14=0%,L14=0%),1%, IF(AND(I14=4%,J14=2.5%,K14=0%,L14=10%),2%, IF(AND(I14=4%,J14=0%,K14=7%,L14=10%),3%,0%))), IF( OR( AND(TRIM(D14)="P1Y",TRIM(E14)="Annual"), AND(TRIM(D14)="P3Y",TRIM(E14)="Annual"), AND(TRIM(D14)="P3Y",TRIM(E14)="Triennial") ), IF(AND(I14=4%,J14=0%,K14=0%,L14=0%),3%, IF(AND(I14=4%,J14=2.5%,K14=0%,L14=10%),10%, IF(AND(I14=4%,J14=0%,K14=7%,L14=10%),14%,0%))), 0% )))) -> 0 | N14: =H14-(H14*M14) -> 1584
A15: CFQ7TTC0RN26 | B15: 1 | C15: Advanced Data Residency | D15: P3Y | E15: Annual | F15: Commercial | G15: 5940 | H15: 4752 | I15: =IF(COUNTIFS(Addendum!C:C,A15,Addendum!D:D,IF(ISNUMBER(B15),TEXT(B15,"0000"),B15),Addendum!E:E,"X")>0,4%,0) -> 0 | J15: =IF(COUNTIFS(Addendum!C:C,A15,Addendum!D:D,IF(ISNUMBER(B15),TEXT(B15,"0000"),B15),Addendum!F:F,"X")>0,2.5%,0) -> 0 | K15: =IF(COUNTIFS(Addendum!C:C,A15,Addendum!D:D,IF(ISNUMBER(B15),TEXT(B15,"0000"),B15),Addendum!G:G,"X")>0,7%,0) -> 0 | L15: =IF(COUNTIFS(Addendum!C:C,A15,Addendum!D:D,IF(ISNUMBER(B15),TEXT(B15,"0000"),B15),Addendum!I:I,"X")>0,10%,0) -> 0 | M15: =IF(AND(I15=0%,J15=0%,K15=0%,L15=0%),0%, IF(OR(TRIM(E15)="OneTime",TRIM(D15)=""),0%, IF( OR( TRIM(D15)="P1M", AND(TRIM(D15)="P1Y",TRIM(E15)="Monthly"), AND(TRIM(D15)="P3Y",TRIM(E15)="Monthly") ), IF(AND(I15=4%,J15=0%,K15=0%,L15=0%),1%, IF(AND(I15=4%,J15=2.5%,K15=0%,L15=10%),2%, IF(AND(I15=4%,J15=0%,K15=7%,L15=10%),3%,0%))), IF( OR( AND(TRIM(D15)="P1Y",TRIM(E15)="Annual"), AND(TRIM(D15)="P3Y",TRIM(E15)="Annual"), AND(TRIM(D15)="P3Y",TRIM(E15)="Triennial") ), IF(AND(I15=4%,J15=0%,K15=0%,L15=0%),3%, IF(AND(I15=4%,J15=2.5%,K15=0%,L15=10%),10%, IF(AND(I15=4%,J15=0%,K15=7%,L15=10%),14%,0%))), 0% )))) -> 0 | N15: =H15-(H15*M15) -> 4752
A16: CFQ7TTC0HDK0 | B16: 000B | C16: Advanced Communications (Non-Profit Pricing) | D16: P1Y | E16: Monthly | F16: Charity | G16: 5040 | H16: 4536 | I16: =IF(COUNTIFS(Addendum!C:C,A16,Addendum!D:D,IF(ISNUMBER(B16),TEXT(B16,"0000"),B16),Addendum!E:E,"X")>0,4%,0) -> 0.04 | J16: =IF(COUNTIFS(Addendum!C:C,A16,Addendum!D:D,IF(ISNUMBER(B16),TEXT(B16,"0000"),B16),Addendum!F:F,"X")>0,2.5%,0) -> 0 | K16: =IF(COUNTIFS(Addendum!C:C,A16,Addendum!D:D,IF(ISNUMBER(B16),TEXT(B16,"0000"),B16),Addendum!G:G,"X")>0,7%,0) -> 0 | L16: =IF(COUNTIFS(Addendum!C:C,A16,Addendum!D:D,IF(ISNUMBER(B16),TEXT(B16,"0000"),B16),Addendum!I:I,"X")>0,10%,0) -> 0 | M16: =IF(AND(I16=0%,J16=0%,K16=0%,L16=0%),0%, IF(OR(TRIM(E16)="OneTime",TRIM(D16)=""),0%, IF( OR( TRIM(D16)="P1M", AND(TRIM(D16)="P1Y",TRIM(E16)="Monthly"), AND(TRIM(D16)="P3Y",TRIM(E16)="Monthly") ), IF(AND(I16=4%,J16=0%,K16=0%,L16=0%),1%, IF(AND(I16=4%,J16=2.5%,K16=0%,L16=10%),2%, IF(AND(I16=4%,J16=0%,K16=7%,L16=10%),3%,0%))), IF( OR( AND(TRIM(D16)="P1Y",TRIM(E16)="Annual"), AND(TRIM(D16)="P3Y",TRIM(E16)="Annual"), AND(TRIM(D16)="P3Y",TRIM(E16)="Triennial") ), IF(AND(I16=4%,J16=0%,K16=0%,L16=0%),3%, IF(AND(I16=4%,J16=2.5%,K16=0%,L16=10%),10%, IF(AND(I16=4%,J16=0%,K16=7%,L16=10%),14%,0%))), 0% )))) -> 0.01 | N16: =H16-(H16*M16) -> 4490.64
A17: CFQ7TTC0HDK0 | B17: 000D | C17: Advanced Communications (Education Student Pricing) | D17: P1Y | E17: Monthly | F17: Education | G17: 1890 | H17: 1512 | I17: =IF(COUNTIFS(Addendum!C:C,A17,Addendum!D:D,IF(ISNUMBER(B17),TEXT(B17,"0000"),B17),Addendum!E:E,"X")>0,4%,0) -> 0.04 | J17: =IF(COUNTIFS(Addendum!C:C,A17,Addendum!D:D,IF(ISNUMBER(B17),TEXT(B17,"0000"),B17),Addendum!F:F,"X")>0,2.5%,0) -> 0 | K17: =IF(COUNTIFS(Addendum!C:C,A17,Addendum!D:D,IF(ISNUMBER(B17),TEXT(B17,"0000"),B17),Addendum!G:G,"X")>0,7%,0) -> 0 | L17: =IF(COUNTIFS(Addendum!C:C,A17,Addendum!D:D,IF(ISNUMBER(B17),TEXT(B17,"0000"),B17),Addendum!I:I,"X")>0,10%,0) -> 0 | M17: =IF(AND(I17=0%,J17=0%,K17=0%,L17=0%),0%, IF(OR(TRIM(E17)="OneTime",TRIM(D17)=""),0%, IF( OR( TRIM(D17)="P1M", AND(TRIM(D17)="P1Y",TRIM(E17)="Monthly"), AND(TRIM(D17)="P3Y",TRIM(E17)="Monthly") ), IF(AND(I17=4%,J17=0%,K17=0%,L17=0%),1%, IF(AND(I17=4%,J17=2.5%,K17=0%,L17=10%),2%, IF(AND(I17=4%,J17=0%,K17=7%,L17=10%),3%,0%))), IF( OR( AND(TRIM(D17)="P1Y",TRIM(E17)="Annual"), AND(TRIM(D17)="P3Y",TRIM(E17)="Annual"), AND(TRIM(D17)="P3Y",TRIM(E17)="Triennial") ), IF(AND(I17=4%,J17=0%,K17=0%,L17=0%),3%, IF(AND(I17=4%,J17=2.5%,K17=0%,L17=10%),10%, IF(AND(I17=4%,J17=0%,K17=7%,L17=10%),14%,0%))), 0% )))) -> 0.01 | N17: =H17-(H17*M17) -> 1496.88
A18: CFQ7TTC0HDK0 | B18: 000C | C18: Advanced Communications (Education Faculty Pricing) | D18: P1Y | E18: Monthly | F18: Education | G18: 2520 | H18: 2016 | I18: =IF(COUNTIFS(Addendum!C:C,A18,Addendum!D:D,IF(ISNUMBER(B18),TEXT(B18,"0000"),B18),Addendum!E:E,"X")>0,4%,0) -> 0.04 | J18: =IF(COUNTIFS(Addendum!C:C,A18,Addendum!D:D,IF(ISNUMBER(B18),TEXT(B18,"0000"),B18),Addendum!F:F,"X")>0,2.5%,0) -> 0 | K18: =IF(COUNTIFS(Addendum!C:C,A18,Addendum!D:D,IF(ISNUMBER(B18),TEXT(B18,"0000"),B18),Addendum!G:G,"X")>0,7%,0) -> 0 | L18: =IF(COUNTIFS(Addendum!C:C,A18,Addendum!D:D,IF(ISNUMBER(B18),TEXT(B18,"0000"),B18),Addendum!I:I,"X")>0,10%,0) -> 0 | M18: =IF(AND(I18=0%,J18=0%,K18=0%,L18=0%),0%, IF(OR(TRIM(E18)="OneTime",TRIM(D18)=""),0%, IF( OR( TRIM(D18)="P1M", AND(TRIM(D18)="P1Y",TRIM(E18)="Monthly"), AND(TRIM(D18)="P3Y",TRIM(E18)="Monthly") ), IF(AND(I18=4%,J18=0%,K18=0%,L18=0%),1%, IF(AND(I18=4%,J18=2.5%,K18=0%,L18=10%),2%, IF(AND(I18=4%,J18=0%,K18=7%,L18=10%),3%,0%))), IF( OR( AND(TRIM(D18)="P1Y",TRIM(E18)="Annual"), AND(TRIM(D18)="P3Y",TRIM(E18)="Annual"), AND(TRIM(D18)="P3Y",TRIM(E18)="Triennial") ), IF(AND(I18=4%,J18=0%,K18=0%,L18=0%),3%, IF(AND(I18=4%,J18=2.5%,K18=0%,L18=10%),10%, IF(AND(I18=4%,J18=0%,K18=7%,L18=10%),14%,0%))), 0% )))) -> 0.01 | N18: =H18-(H18*M18) -> 1995.84
A19: CFQ7TTC0HDK0 | B19: 000C | C19: Advanced Communications (Education Faculty Pricing) | D19: P1Y | E19: Annual | F19: Education | G19: 2400 | H19: 1920 | I19: =IF(COUNTIFS(Addendum!C:C,A19,Addendum!D:D,IF(ISNUMBER(B19),TEXT(B19,"0000"),B19),Addendum!E:E,"X")>0,4%,0) -> 0.04 | J19: =IF(COUNTIFS(Addendum!C:C,A19,Addendum!D:D,IF(ISNUMBER(B19),TEXT(B19,"0000"),B19),Addendum!F:F,"X")>0,2.5%,0) -> 0 | K19: =IF(COUNTIFS(Addendum!C:C,A19,Addendum!D:D,IF(ISNUMBER(B19),TEXT(B19,"0000"),B19),Addendum!G:G,"X")>0,7%,0) -> 0 | L19: =IF(COUNTIFS(Addendum!C:C,A19,Addendum!D:D,IF(ISNUMBER(B19),TEXT(B19,"0000"),B19),Addendum!I:I,"X")>0,10%,0) -> 0 | M19: =IF(AND(I19=0%,J19=0%,K19=0%,L19=0%),0%, IF(OR(TRIM(E19)="OneTime",TRIM(D19)=""),0%, IF( OR( TRIM(D19)="P1M", AND(TRIM(D19)="P1Y",TRIM(E19)="Monthly"), AND(TRIM(D19)="P3Y",TRIM(E19)="Monthly") ), IF(AND(I19=4%,J19=0%,K19=0%,L19=0%),1%, IF(AND(I19=4%,J19=2.5%,K19=0%,L19=10%),2%, IF(AND(I19=4%,J19=0%,K19=7%,L19=10%),3%,0%))), IF( OR( AND(TRIM(D19)="P1Y",TRIM(E19)="Annual"), AND(TRIM(D19)="P3Y",TRIM(E19)="Annual"), AND(TRIM(D19)="P3Y",TRIM(E19)="Triennial") ), IF(AND(I19=4%,J19=0%,K19=0%,L19=0%),3%, IF(AND(I19=4%,J19=2.5%,K19=0%,L19=10%),10%, IF(AND(I19=4%,J19=0%,K19=7%,L19=10%),14%,0%))), 0% )))) -> 0.03 | N19: =H19-(H19*M19) -> 1862.4
A20: CFQ7TTC0HDK0 | B20: 000B | C20: Advanced Communications (Non-Profit Pricing) | D20: P1M | E20: Monthly | F20: Charity | G20: 480 | H20: 432 | I20: =IF(COUNTIFS(Addendum!C:C,A20,Addendum!D:D,IF(ISNUMBER(B20),TEXT(B20,"0000"),B20),Addendum!E:E,"X")>0,4%,0) -> 0.04 | J20: =IF(COUNTIFS(Addendum!C:C,A20,Addendum!D:D,IF(ISNUMBER(B20),TEXT(B20,"0000"),B20),Addendum!F:F,"X")>0,2.5%,0) -> 0 | K20: =IF(COUNTIFS(Addendum!C:C,A20,Addendum!D:D,IF(ISNUMBER(B20),TEXT(B20,"0000"),B20),Addendum!G:G,"X")>0,7%,0) -> 0 | L20: =IF(COUNTIFS(Addendum!C:C,A20,Addendum!D:D,IF(ISNUMBER(B20),TEXT(B20,"0000"),B20),Addendum!I:I,"X")>0,10%,0) -> 0 | M20: =IF(AND(I20=0%,J20=0%,K20=0%,L20=0%),0%, IF(OR(TRIM(E20)="OneTime",TRIM(D20)=""),0%, IF( OR( TRIM(D20)="P1M", AND(TRIM(D20)="P1Y",TRIM(E20)="Monthly"), AND(TRIM(D20)="P3Y",TRIM(E20)="Monthly") ), IF(AND(I20=4%,J20=0%,K20=0%,L20=0%),1%, IF(AND(I20=4%,J20=2.5%,K20=0%,L20=10%),2%, IF(AND(I20=4%,J20=0%,K20=7%,L20=10%),3%,0%))), IF( OR( AND(TRIM(D20)="P1Y",TRIM(E20)="Annual"), AND(TRIM(D20)="P3Y",TRIM(E20)="Annual"), AND(TRIM(D20)="P3Y",TRIM(E20)="Triennial") ), IF(AND(I20=4%,J20=0%,K20=0%,L20=0%),3%, IF(AND(I20=4%,J20=2.5%,K20=0%,L20=10%),10%, IF(AND(I20=4%,J20=0%,K20=7%,L20=10%),14%,0%))), 0% )))) -> 0.01 | N20: =H20-(H20*M20) -> 427.68
A21: CFQ7TTC0HDK0 | B21: 000D | C21: Advanced Communications (Education Student Pricing) | D21: P1M | E21: Monthly | F21: Education | G21: 180 | H21: 144 | I21: =IF(COUNTIFS(Addendum!C:C,A21,Addendum!D:D,IF(ISNUMBER(B21),TEXT(B21,"0000"),B21),Addendum!E:E,"X")>0,4%,0) -> 0.04 | J21: =IF(COUNTIFS(Addendum!C:C,A21,Addendum!D:D,IF(ISNUMBER(B21),TEXT(B21,"0000"),B21),Addendum!F:F,"X")>0,2.5%,0) -> 0 | K21: =IF(COUNTIFS(Addendum!C:C,A21,Addendum!D:D,IF(ISNUMBER(B21),TEXT(B21,"0000"),B21),Addendum!G:G,"X")>0,7%,0) -> 0 | L21: =IF(COUNTIFS(Addendum!C:C,A21,Addendum!D:D,IF(ISNUMBER(B21),TEXT(B21,"0000"),B21),Addendum!I:I,"X")>0,10%,0) -> 0 | M21: =IF(AND(I21=0%,J21=0%,K21=0%,L21=0%),0%, IF(OR(TRIM(E21)="OneTime",TRIM(D21)=""),0%, IF( OR( TRIM(D21)="P1M", AND(TRIM(D21)="P1Y",TRIM(E21)="Monthly"), AND(TRIM(D21)="P3Y",TRIM(E21)="Monthly") ), IF(AND(I21=4%,J21=0%,K21=0%,L21=0%),1%, IF(AND(I21=4%,J21=2.5%,K21=0%,L21=10%),2%, IF(AND(I21=4%,J21=0%,K21=7%,L21=10%),3%,0%))), IF( OR( AND(TRIM(D21)="P1Y",TRIM(E21)="Annual"), AND(TRIM(D21)="P3Y",TRIM(E21)="Annual"), AND(TRIM(D21)="P3Y",TRIM(E21)="Triennial") ), IF(AND(I21=4%,J21=0%,K21=0%,L21=0%),3%, IF(AND(I21=4%,J21=2.5%,K21=0%,L21=10%),10%, IF(AND(I21=4%,J21=0%,K21=7%,L21=10%),14%,0%))), 0% )))) -> 0.01 | N21: =H21-(H21*M21) -> 142.56
A22: CFQ7TTC0HDK0 | B22: 1 | C22: Advanced Communications | D22: P1M | E22: Monthly | F22: Commercial | G22: 1200 | H22: 960 | I22: =IF(COUNTIFS(Addendum!C:C,A22,Addendum!D:D,IF(ISNUMBER(B22),TEXT(B22,"0000"),B22),Addendum!E:E,"X")>0,4%,0) -> 0.04 | J22: =IF(COUNTIFS(Addendum!C:C,A22,Addendum!D:D,IF(ISNUMBER(B22),TEXT(B22,"0000"),B22),Addendum!F:F,"X")>0,2.5%,0) -> 0 | K22: =IF(COUNTIFS(Addendum!C:C,A22,Addendum!D:D,IF(ISNUMBER(B22),TEXT(B22,"0000"),B22),Addendum!G:G,"X")>0,7%,0) -> 0 | L22: =IF(COUNTIFS(Addendum!C:C,A22,Addendum!D:D,IF(ISNUMBER(B22),TEXT(B22,"0000"),B22),Addendum!I:I,"X")>0,10%,0) -> 0 | M22: =IF(AND(I22=0%,J22=0%,K22=0%,L22=0%),0%, IF(OR(TRIM(E22)="OneTime",TRIM(D22)=""),0%, IF( OR( TRIM(D22)="P1M", AND(TRIM(D22)="P1Y",TRIM(E22)="Monthly"), AND(TRIM(D22)="P3Y",TRIM(E22)="Monthly") ), IF(AND(I22=4%,J22=0%,K22=0%,L22=0%),1%, IF(AND(I22=4%,J22=2.5%,K22=0%,L22=10%),2%, IF(AND(I22=4%,J22=0%,K22=7%,L22=10%),3%,0%))), IF( OR( AND(TRIM(D22)="P1Y",TRIM(E22)="Annual"), AND(TRIM(D22)="P3Y",TRIM(E22)="Annual"), AND(TRIM(D22)="P3Y",TRIM(E22)="Triennial") ), IF(AND(I22=4%,J22=0%,K22=0%,L22=0%),3%, IF(AND(I22=4%,J22=2.5%,K22=0%,L22=10%),10%, IF(AND(I22=4%,J22=0%,K22=7%,L22=10%),14%,0%))), 0% )))) -> 0.01 | N22: =H22-(H22*M22) -> 950.4
A23: CFQ7TTC0HDK0 | B23: 000B | C23: Advanced Communications (Non-Profit Pricing) | D23: P1Y | E23: Annual | F23: Charity | G23: 4800 | H23: 4320 | I23: =IF(COUNTIFS(Addendum!C:C,A23,Addendum!D:D,IF(ISNUMBER(B23),TEXT(B23,"0000"),B23),Addendum!E:E,"X")>0,4%,0) -> 0.04 | J23: =IF(COUNTIFS(Addendum!C:C,A23,Addendum!D:D,IF(ISNUMBER(B23),TEXT(B23,"0000"),B23),Addendum!F:F,"X")>0,2.5%,0) -> 0 | K23: =IF(COUNTIFS(Addendum!C:C,A23,Addendum!D:D,IF(ISNUMBER(B23),TEXT(B23,"0000"),B23),Addendum!G:G,"X")>0,7%,0) -> 0 | L23: =IF(COUNTIFS(Addendum!C:C,A23,Addendum!D:D,IF(ISNUMBER(B23),TEXT(B23,"0000"),B23),Addendum!I:I,"X")>0,10%,0) -> 0 | M23: =IF(AND(I23=0%,J23=0%,K23=0%,L23=0%),0%, IF(OR(TRIM(E23)="OneTime",TRIM(D23)=""),0%, IF( OR( TRIM(D23)="P1M", AND(TRIM(D23)="P1Y",TRIM(E23)="Monthly"), AND(TRIM(D23)="P3Y",TRIM(E23)="Monthly") ), IF(AND(I23=4%,J23=0%,K23=0%,L23=0%),1%, IF(AND(I23=4%,J23=2.5%,K23=0%,L23=10%),2%, IF(AND(I23=4%,J23=0%,K23=7%,L23=10%),3%,0%))), IF( OR( AND(TRIM(D23)="P1Y",TRIM(E23)="Annual"), AND(TRIM(D23)="P3Y",TRIM(E23)="Annual"), AND(TRIM(D23)="P3Y",TRIM(E23)="Triennial") ), IF(AND(I23=4%,J23=0%,K23=0%,L23=0%),3%, IF(AND(I23=4%,J23=2.5%,K23=0%,L23=10%),10%, IF(AND(I23=4%,J23=0%,K23=7%,L23=10%),14%,0%))), 0% )))) -> 0.03 | N23: =H23-(H23*M23) -> 4190.4
A24: CFQ7TTC0HDK0 | B24: 1 | C24: Advanced Communications | D24: P1Y | E24: Annual | F24: Commercial | G24: 12000 | H24: 9600 | I24: =IF(COUNTIFS(Addendum!C:C,A24,Addendum!D:D,IF(ISNUMBER(B24),TEXT(B24,"0000"),B24),Addendum!E:E,"X")>0,4%,0) -> 0.04 | J24: =IF(COUNTIFS(Addendum!C:C,A24,Addendum!D:D,IF(ISNUMBER(B24),TEXT(B24,"0000"),B24),Addendum!F:F,"X")>0,2.5%,0) -> 0 | K24: =IF(COUNTIFS(Addendum!C:C,A24,Addendum!D:D,IF(ISNUMBER(B24),TEXT(B24,"0000"),B24),Addendum!G:G,"X")>0,7%,0) -> 0 | L24: =IF(COUNTIFS(Addendum!C:C,A24,Addendum!D:D,IF(ISNUMBER(B24),TEXT(B24,"0000"),B24),Addendum!I:I,"X")>0,10%,0) -> 0 | M24: =IF(AND(I24=0%,J24=0%,K24=0%,L24=0%),0%, IF(OR(TRIM(E24)="OneTime",TRIM(D24)=""),0%, IF( OR( TRIM(D24)="P1M", AND(TRIM(D24)="P1Y",TRIM(E24)="Monthly"), AND(TRIM(D24)="P3Y",TRIM(E24)="Monthly") ), IF(AND(I24=4%,J24=0%,K24=0%,L24=0%),1%, IF(AND(I24=4%,J24=2.5%,K24=0%,L24=10%),2%, IF(AND(I24=4%,J24=0%,K24=7%,L24=10%),3%,0%))), IF( OR( AND(TRIM(D24)="P1Y",TRIM(E24)="Annual"), AND(TRIM(D24)="P3Y",TRIM(E24)="Annual"), AND(TRIM(D24)="P3Y",TRIM(E24)="Triennial") ), IF(AND(I24=4%,J24=0%,K24=0%,L24=0%),3%, IF(AND(I24=4%,J24=2.5%,K24=0%,L24=10%),10%, IF(AND(I24=4%,J24=0%,K24=7%,L24=10%),14%,0%))), 0% )))) -> 0.03 | N24: =H24-(H24*M24) -> 9312
A25: CFQ7TTC0HDK0 | B25: 1 | C25: Advanced Communications | D25: P1Y | E25: Monthly | F25: Commercial | G25: 12600 | H25: 10080 | I25: =IF(COUNTIFS(Addendum!C:C,A25,Addendum!D:D,IF(ISNUMBER(B25),TEXT(B25,"0000"),B25),Addendum!E:E,"X")>0,4%,0) -> 0.04 | J25: =IF(COUNTIFS(Addendum!C:C,A25,Addendum!D:D,IF(ISNUMBER(B25),TEXT(B25,"0000"),B25),Addendum!F:F,"X")>0,2.5%,0) -> 0 | K25: =IF(COUNTIFS(Addendum!C:C,A25,Addendum!D:D,IF(ISNUMBER(B25),TEXT(B25,"0000"),B25),Addendum!G:G,"X")>0,7%,0) -> 0 | L25: =IF(COUNTIFS(Addendum!C:C,A25,Addendum!D:D,IF(ISNUMBER(B25),TEXT(B25,"0000"),B25),Addendum!I:I,"X")>0,10%,0) -> 0 | M25: =IF(AND(I25=0%,J25=0%,K25=0%,L25=0%),0%, IF(OR(TRIM(E25)="OneTime",TRIM(D25)=""),0%, IF( OR( TRIM(D25)="P1M", AND(TRIM(D25)="P1Y",TRIM(E25)="Monthly"), AND(TRIM(D25)="P3Y",TRIM(E25)="Monthly") ), IF(AND(I25=4%,J25=0%,K25=0%,L25=0%),1%, IF(AND(I25=4%,J25=2.5%,K25=0%,L25=10%),2%, IF(AND(I25=4%,J25=0%,K25=7%,L25=10%),3%,0%))), IF( OR( AND(TRIM(D25)="P1Y",TRIM(E25)="Annual"), AND(TRIM(D25)="P3Y",TRIM(E25)="Annual"), AND(TRIM(D25)="P3Y",TRIM(E25)="Triennial") ), IF(AND(I25=4%,J25=0%,K25=0%,L25=0%),3%, IF(AND(I25=4%,J25=2.5%,K25=0%,L25=10%),10%, IF(AND(I25=4%,J25=0%,K25=7%,L25=10%),14%,0%))), 0% )))) -> 0.01 | N25: =H25-(H25*M25) -> 9979.2
A26: CFQ7TTC0HDK0 | B26: 000D | C26: Advanced Communications (Education Student Pricing) | D26: P1Y | E26: Annual | F26: Education | G26: 1800 | H26: 1440 | I26: =IF(COUNTIFS(Addendum!C:C,A26,Addendum!D:D,IF(ISNUMBER(B26),TEXT(B26,"0000"),B26),Addendum!E:E,"X")>0,4%,0) -> 0.04 | J26: =IF(COUNTIFS(Addendum!C:C,A26,Addendum!D:D,IF(ISNUMBER(B26),TEXT(B26,"0000"),B26),Addendum!F:F,"X")>0,2.5%,0) -> 0 | K26: =IF(COUNTIFS(Addendum!C:C,A26,Addendum!D:D,IF(ISNUMBER(B26),TEXT(B26,"0000"),B26),Addendum!G:G,"X")>0,7%,0) -> 0 | L26: =IF(COUNTIFS(Addendum!C:C,A26,Addendum!D:D,IF(ISNUMBER(B26),TEXT(B26,"0000"),B26),Addendum!I:I,"X")>0,10%,0) -> 0 | M26: =IF(AND(I26=0%,J26=0%,K26=0%,L26=0%),0%, IF(OR(TRIM(E26)="OneTime",TRIM(D26)=""),0%, IF( OR( TRIM(D26)="P1M", AND(TRIM(D26)="P1Y",TRIM(E26)="Monthly"), AND(TRIM(D26)="P3Y",TRIM(E26)="Monthly") ), IF(AND(I26=4%,J26=0%,K26=0%,L26=0%),1%, IF(AND(I26=4%,J26=2.5%,K26=0%,L26=10%),2%, IF(AND(I26=4%,J26=0%,K26=7%,L26=10%),3%,0%))), IF( OR( AND(TRIM(D26)="P1Y",TRIM(E26)="Annual"), AND(TRIM(D26)="P3Y",TRIM(E26)="Annual"), AND(TRIM(D26)="P3Y",TRIM(E26)="Triennial") ), IF(AND(I26=4%,J26=0%,K26=0%,L26=0%),3%, IF(AND(I26=4%,J26=2.5%,K26=0%,L26=10%),10%, IF(AND(I26=4%,J26=0%,K26=7%,L26=10%),14%,0%))), 0% )))) -> 0.03 | N26: =H26-(H26*M26) -> 1396.8
A27: CFQ7TTC0HDK0 | B27: 000C | C27: Advanced Communications (Education Faculty Pricing) | D27: P1M | E27: Monthly | F27: Education | G27: 240 | H27: 192 | I27: =IF(COUNTIFS(Addendum!C:C,A27,Addendum!D:D,IF(ISNUMBER(B27),TEXT(B27,"0000"),B27),Addendum!E:E,"X")>0,4%,0) -> 0.04 | J27: =IF(COUNTIFS(Addendum!C:C,A27,Addendum!D:D,IF(ISNUMBER(B27),TEXT(B27,"0000"),B27),Addendum!F:F,"X")>0,2.5%,0) -> 0 | K27: =IF(COUNTIFS(Addendum!C:C,A27,Addendum!D:D,IF(ISNUMBER(B27),TEXT(B27,"0000"),B27),Addendum!G:G,"X")>0,7%,0) -> 0 | L27: =IF(COUNTIFS(Addendum!C:C,A27,Addendum!D:D,IF(ISNUMBER(B27),TEXT(B27,"0000"),B27),Addendum!I:I,"X")>0,10%,0) -> 0 | M27: =IF(AND(I27=0%,J27=0%,K27=0%,L27=0%),0%, IF(OR(TRIM(E27)="OneTime",TRIM(D27)=""),0%, IF( OR( TRIM(D27)="P1M", AND(TRIM(D27)="P1Y",TRIM(E27)="Monthly"), AND(TRIM(D27)="P3Y",TRIM(E27)="Monthly") ), IF(AND(I27=4%,J27=0%,K27=0%,L27=0%),1%, IF(AND(I27=4%,J27=2.5%,K27=0%,L27=10%),2%, IF(AND(I27=4%,J27=0%,K27=7%,L27=10%),3%,0%))), IF( OR( AND(TRIM(D27)="P1Y",TRIM(E27)="Annual"), AND(TRIM(D27)="P3Y",TRIM(E27)="Annual"), AND(TRIM(D27)="P3Y",TRIM(E27)="Triennial") ), IF(AND(I27=4%,J27=0%,K27=0%,L27=0%),3%, IF(AND(I27=4%,J27=2.5%,K27=0%,L27=10%),10%, IF(AND(I27=4%,J27=0%,K27=7%,L27=10%),14%,0%))), 0% )))) -> 0.01 | N27: =H27-(H27*M27) -> 190.08
A28: CFQ7TTC0LHQD | B28: 4 | C28: Advanced eDiscovery Storage (Education Faculty Pricing) | D28: P1M | E28: Monthly | F28: Education | G28: 1998 | H28: 1598.4 | I28: =IF(COUNTIFS(Addendum!C:C,A28,Addendum!D:D,IF(ISNUMBER(B28),TEXT(B28,"0000"),B28),Addendum!E:E,"X")>0,4%,0) -> 0 | J28: =IF(COUNTIFS(Addendum!C:C,A28,Addendum!D:D,IF(ISNUMBER(B28),TEXT(B28,"0000"),B28),Addendum!F:F,"X")>0,2.5%,0) -> 0 | K28: =IF(COUNTIFS(Addendum!C:C,A28,Addendum!D:D,IF(ISNUMBER(B28),TEXT(B28,"0000"),B28),Addendum!G:G,"X")>0,7%,0) -> 0 | L28: =IF(COUNTIFS(Addendum!C:C,A28,Addendum!D:D,IF(ISNUMBER(B28),TEXT(B28,"0000"),B28),Addendum!I:I,"X")>0,10%,0) -> 0 | M28: =IF(AND(I28=0%,J28=0%,K28=0%,L28=0%),0%, IF(OR(TRIM(E28)="OneTime",TRIM(D28)=""),0%, IF( OR( TRIM(D28)="P1M", AND(TRIM(D28)="P1Y",TRIM(E28)="Monthly"), AND(TRIM(D28)="P3Y",TRIM(E28)="Monthly") ), IF(AND(I28=4%,J28=0%,K28=0%,L28=0%),1%, IF(AND(I28=4%,J28=2.5%,K28=0%,L28=10%),2%, IF(AND(I28=4%,J28=0%,K28=7%,L28=10%),3%,0%))), IF( OR( AND(TRIM(D28)="P1Y",TRIM(E28)="Annual"), AND(TRIM(D28)="P3Y",TRIM(E28)="Annual"), AND(TRIM(D28)="P3Y",TRIM(E28)="Triennial") ), IF(AND(I28=4%,J28=0%,K28=0%,L28=0%),3%, IF(AND(I28=4%,J28=2.5%,K28=0%,L28=10%),10%, IF(AND(I28=4%,J28=0%,K28=7%,L28=10%),14%,0%))), 0% )))) -> 0 | N28: =H28-(H28*M28) -> 1598.4
A29: CFQ7TTC0LHQD | B29: 4 | C29: Advanced eDiscovery Storage (Education Faculty Pricing) | D29: P1Y | E29: Monthly | F29: Education | G29: 20979 | H29: 16783.2 | I29: =IF(COUNTIFS(Addendum!C:C,A29,Addendum!D:D,IF(ISNUMBER(B29),TEXT(B29,"0000"),B29),Addendum!E:E,"X")>0,4%,0) -> 0 | J29: =IF(COUNTIFS(Addendum!C:C,A29,Addendum!D:D,IF(ISNUMBER(B29),TEXT(B29,"0000"),B29),Addendum!F:F,"X")>0,2.5%,0) -> 0 | K29: =IF(COUNTIFS(Addendum!C:C,A29,Addendum!D:D,IF(ISNUMBER(B29),TEXT(B29,"0000"),B29),Addendum!G:G,"X")>0,7%,0) -> 0 | L29: =IF(COUNTIFS(Addendum!C:C,A29,Addendum!D:D,IF(ISNUMBER(B29),TEXT(B29,"0000"),B29),Addendum!I:I,"X")>0,10%,0) -> 0 | M29: =IF(AND(I29=0%,J29=0%,K29=0%,L29=0%),0%, IF(OR(TRIM(E29)="OneTime",TRIM(D29)=""),0%, IF( OR( TRIM(D29)="P1M", AND(TRIM(D29)="P1Y",TRIM(E29)="Monthly"), AND(TRIM(D29)="P3Y",TRIM(E29)="Monthly") ), IF(AND(I29=4%,J29=0%,K29=0%,L29=0%),1%, IF(AND(I29=4%,J29=2.5%,K29=0%,L29=10%),2%, IF(AND(I29=4%,J29=0%,K29=7%,L29=10%),3%,0%))), IF( OR( AND(TRIM(D29)="P1Y",TRIM(E29)="Annual"), AND(TRIM(D29)="P3Y",TRIM(E29)="Annual"), AND(TRIM(D29)="P3Y",TRIM(E29)="Triennial") ), IF(AND(I29=4%,J29=0%,K29=0%,L29=0%),3%, IF(AND(I29=4%,J29=2.5%,K29=0%,L29=10%),10%, IF(AND(I29=4%,J29=0%,K29=7%,L29=10%),14%,0%))), 0% )))) -> 0 | N29: =H29-(H29*M29) -> 16783.2
A30: CFQ7TTC0LHQD | B30: 4 | C30: Advanced eDiscovery Storage (Education Faculty Pricing) | D30: P1Y | E30: Annual | F30: Education | G30: 19980 | H30: 15984 | I30: =IF(COUNTIFS(Addendum!C:C,A30,Addendum!D:D,IF(ISNUMBER(B30),TEXT(B30,"0000"),B30),Addendum!E:E,"X")>0,4%,0) -> 0 | J30: =IF(COUNTIFS(Addendum!C:C,A30,Addendum!D:D,IF(ISNUMBER(B30),TEXT(B30,"0000"),B30),Addendum!F:F,"X")>0,2.5%,0) -> 0 | K30: =IF(COUNTIFS(Addendum!C:C,A30,Addendum!D:D,IF(ISNUMBER(B30),TEXT(B30,"0000"),B30),Addendum!G:G,"X")>0,7%,0) -> 0 | L30: =IF(COUNTIFS(Addendum!C:C,A30,Addendum!D:D,IF(ISNUMBER(B30),TEXT(B30,"0000"),B30),Addendum!I:I,"X")>0,10%,0) -> 0 | M30: =IF(AND(I30=0%,J30=0%,K30=0%,L30=0%),0%, IF(OR(TRIM(E30)="OneTime",TRIM(D30)=""),0%, IF( OR( TRIM(D30)="P1M", AND(TRIM(D30)="P1Y",TRIM(E30)="Monthly"), AND(TRIM(D30)="P3Y",TRIM(E30)="Monthly") ), IF(AND(I30=4%,J30=0%,K30=0%,L30=0%),1%, IF(AND(I30=4%,J30=2.5%,K30=0%,L30=10%),2%, IF(AND(I30=4%,J30=0%,K30=7%,L30=10%),3%,0%))), IF( OR( AND(TRIM(D30)="P1Y",TRIM(E30)="Annual"), AND(TRIM(D30)="P3Y",TRIM(E30)="Annual"), AND(TRIM(D30)="P3Y",TRIM(E30)="Triennial") ), IF(AND(I30=4%,J30=0%,K30=0%,L30=0%),3%, IF(AND(I30=4%,J30=2.5%,K30=0%,L30=10%),10%, IF(AND(I30=4%,J30=0%,K30=7%,L30=10%),14%,0%))), 0% )))) -> 0 | N30: =H30-(H30*M30) -> 15984
A31: CFQ7TTC0LHQD | B31: 1 | C31: Advanced eDiscovery Storage | D31: P1Y | E31: Monthly | F31: Commercial | G31: 104832 | H31: 83865.6 | I31: =IF(COUNTIFS(Addendum!C:C,A31,Addendum!D:D,IF(ISNUMBER(B31),TEXT(B31,"0000"),B31),Addendum!E:E,"X")>0,4%,0) -> 0 | J31: =IF(COUNTIFS(Addendum!C:C,A31,Addendum!D:D,IF(ISNUMBER(B31),TEXT(B31,"0000"),B31),Addendum!F:F,"X")>0,2.5%,0) -> 0 | K31: =IF(COUNTIFS(Addendum!C:C,A31,Addendum!D:D,IF(ISNUMBER(B31),TEXT(B31,"0000"),B31),Addendum!G:G,"X")>0,7%,0) -> 0 | L31: =IF(COUNTIFS(Addendum!C:C,A31,Addendum!D:D,IF(ISNUMBER(B31),TEXT(B31,"0000"),B31),Addendum!I:I,"X")>0,10%,0) -> 0 | M31: =IF(AND(I31=0%,J31=0%,K31=0%,L31=0%),0%, IF(OR(TRIM(E31)="OneTime",TRIM(D31)=""),0%, IF( OR( TRIM(D31)="P1M", AND(TRIM(D31)="P1Y",TRIM(E31)="Monthly"), AND(TRIM(D31)="P3Y",TRIM(E31)="Monthly") ), IF(AND(I31=4%,J31=0%,K31=0%,L31=0%),1%, IF(AND(I31=4%,J31=2.5%,K31=0%,L31=10%),2%, IF(AND(I31=4%,J31=0%,K31=7%,L31=10%),3%,0%))), IF( OR( AND(TRIM(D31)="P1Y",TRIM(E31)="Annual"), AND(TRIM(D31)="P3Y",TRIM(E31)="Annual"), AND(TRIM(D31)="P3Y",TRIM(E31)="Triennial") ), IF(AND(I31=4%,J31=0%,K31=0%,L31=0%),3%, IF(AND(I31=4%,J31=2.5%,K31=0%,L31=10%),10%, IF(AND(I31=4%,J31=0%,K31=7%,L31=10%),14%,0%))), 0% )))) -> 0 | N31: =H31-(H31*M31) -> 83865.6
A32: CFQ7TTC0LHQD | B32: 5 | C32: Advanced eDiscovery Storage (Non-Profit Pricing) | D32: P1Y | E32: Monthly | F32: Charity | G32: 41958 | H32: 37762.2 | I32: =IF(COUNTIFS(Addendum!C:C,A32,Addendum!D:D,IF(ISNUMBER(B32),TEXT(B32,"0000"),B32),Addendum!E:E,"X")>0,4%,0) -> 0 | J32: =IF(COUNTIFS(Addendum!C:C,A32,Addendum!D:D,IF(ISNUMBER(B32),TEXT(B32,"0000"),B32),Addendum!F:F,"X")>0,2.5%,0) -> 0 | K32: =IF(COUNTIFS(Addendum!C:C,A32,Addendum!D:D,IF(ISNUMBER(B32),TEXT(B32,"0000"),B32),Addendum!G:G,"X")>0,7%,0) -> 0 | L32: =IF(COUNTIFS(Addendum!C:C,A32,Addendum!D:D,IF(ISNUMBER(B32),TEXT(B32,"0000"),B32),Addendum!I:I,"X")>0,10%,0) -> 0 | M32: =IF(AND(I32=0%,J32=0%,K32=0%,L32=0%),0%, IF(OR(TRIM(E32)="OneTime",TRIM(D32)=""),0%, IF( OR( TRIM(D32)="P1M", AND(TRIM(D32)="P1Y",TRIM(E32)="Monthly"), AND(TRIM(D32)="P3Y",TRIM(E32)="Monthly") ), IF(AND(I32=4%,J32=0%,K32=0%,L32=0%),1%, IF(AND(I32=4%,J32=2.5%,K32=0%,L32=10%),2%, IF(AND(I32=4%,J32=0%,K32=7%,L32=10%),3%,0%))), IF( OR( AND(TRIM(D32)="P1Y",TRIM(E32)="Annual"), AND(TRIM(D32)="P3Y",TRIM(E32)="Annual"), AND(TRIM(D32)="P3Y",TRIM(E32)="Triennial") ), IF(AND(I32=4%,J32=0%,K32=0%,L32=0%),3%, IF(AND(I32=4%,J32=2.5%,K32=0%,L32=10%),10%, IF(AND(I32=4%,J32=0%,K32=7%,L32=10%),14%,0%))), 0% )))) -> 0 | N32: =H32-(H32*M32) -> 37762.2
A33: CFQ7TTC0LHQD | B33: 1 | C33: Advanced eDiscovery Storage | D33: P1Y | E33: Annual | F33: Commercial | G33: 99840 | H33: 79872 | I33: =IF(COUNTIFS(Addendum!C:C,A33,Addendum!D:D,IF(ISNUMBER(B33),TEXT(B33,"0000"),B33),Addendum!E:E,"X")>0,4%,0) -> 0 | J33: =IF(COUNTIFS(Addendum!C:C,A33,Addendum!D:D,IF(ISNUMBER(B33),TEXT(B33,"0000"),B33),Addendum!F:F,"X")>0,2.5%,0) -> 0 | K33: =IF(COUNTIFS(Addendum!C:C,A33,Addendum!D:D,IF(ISNUMBER(B33),TEXT(B33,"0000"),B33),Addendum!G:G,"X")>0,7%,0) -> 0 | L33: =IF(COUNTIFS(Addendum!C:C,A33,Addendum!D:D,IF(ISNUMBER(B33),TEXT(B33,"0000"),B33),Addendum!I:I,"X")>0,10%,0) -> 0 | M33: =IF(AND(I33=0%,J33=0%,K33=0%,L33=0%),0%, IF(OR(TRIM(E33)="OneTime",TRIM(D33)=""),0%, IF( OR( TRIM(D33)="P1M", AND(TRIM(D33)="P1Y",TRIM(E33)="Monthly"), AND(TRIM(D33)="P3Y",TRIM(E33)="Monthly") ), IF(AND(I33=4%,J33=0%,K33=0%,L33=0%),1%, IF(AND(I33=4%,J33=2.5%,K33=0%,L33=10%),2%, IF(AND(I33=4%,J33=0%,K33=7%,L33=10%),3%,0%))), IF( OR( AND(TRIM(D33)="P1Y",TRIM(E33)="Annual"), AND(TRIM(D33)="P3Y",TRIM(E33)="Annual"), AND(TRIM(D33)="P3Y",TRIM(E33)="Triennial") ), IF(AND(I33=4%,J33=0%,K33=0%,L33=0%),3%, IF(AND(I33=4%,J33=2.5%,K33=0%,L33=10%),10%, IF(AND(I33=4%,J33=0%,K33=7%,L33=10%),14%,0%))), 0% )))) -> 0 | N33: =H33-(H33*M33) -> 79872
A34: CFQ7TTC0LHQD | B34: 5 | C34: Advanced eDiscovery Storage (Non-Profit Pricing) | D34: P1M | E34: Monthly | F34: Charity | G34: 3996 | H34: 3596.4 | I34: =IF(COUNTIFS(Addendum!C:C,A34,Addendum!D:D,IF(ISNUMBER(B34),TEXT(B34,"0000"),B34),Addendum!E:E,"X")>0,4%,0) -> 0 | J34: =IF(COUNTIFS(Addendum!C:C,A34,Addendum!D:D,IF(ISNUMBER(B34),TEXT(B34,"0000"),B34),Addendum!F:F,"X")>0,2.5%,0) -> 0 | K34: =IF(COUNTIFS(Addendum!C:C,A34,Addendum!D:D,IF(ISNUMBER(B34),TEXT(B34,"0000"),B34),Addendum!G:G,"X")>0,7%,0) -> 0 | L34: =IF(COUNTIFS(Addendum!C:C,A34,Addendum!D:D,IF(ISNUMBER(B34),TEXT(B34,"0000"),B34),Addendum!I:I,"X")>0,10%,0) -> 0 | M34: =IF(AND(I34=0%,J34=0%,K34=0%,L34=0%),0%, IF(OR(TRIM(E34)="OneTime",TRIM(D34)=""),0%, IF( OR( TRIM(D34)="P1M", AND(TRIM(D34)="P1Y",TRIM(E34)="Monthly"), AND(TRIM(D34)="P3Y",TRIM(E34)="Monthly") ), IF(AND(I34=4%,J34=0%,K34=0%,L34=0%),1%, IF(AND(I34=4%,J34=2.5%,K34=0%,L34=10%),2%, IF(AND(I34=4%,J34=0%,K34=7%,L34=10%),3%,0%))), IF( OR( AND(TRIM(D34)="P1Y",TRIM(E34)="Annual"), AND(TRIM(D34)="P3Y",TRIM(E34)="Annual"), AND(TRIM(D34)="P3Y",TRIM(E34)="Triennial") ), IF(AND(I34=4%,J34=0%,K34=0%,L34=0%),3%, IF(AND(I34=4%,J34=2.5%,K34=0%,L34=10%),10%, IF(AND(I34=4%,J34=0%,K34=7%,L34=10%),14%,0%))), 0% )))) -> 0 | N34: =H34-(H34*M34) -> 3596.4
A35: CFQ7TTC0LHQD | B35: 5 | C35: Advanced eDiscovery Storage (Non-Profit Pricing) | D35: P1Y | E35: Annual | F35: Charity | G35: 39960 | H35: 35964 | I35: =IF(COUNTIFS(Addendum!C:C,A35,Addendum!D:D,IF(ISNUMBER(B35),TEXT(B35,"0000"),B35),Addendum!E:E,"X")>0,4%,0) -> 0 | J35: =IF(COUNTIFS(Addendum!C:C,A35,Addendum!D:D,IF(ISNUMBER(B35),TEXT(B35,"0000"),B35),Addendum!F:F,"X")>0,2.5%,0) -> 0 | K35: =IF(COUNTIFS(Addendum!C:C,A35,Addendum!D:D,IF(ISNUMBER(B35),TEXT(B35,"0000"),B35),Addendum!G:G,"X")>0,7%,0) -> 0 | L35: =IF(COUNTIFS(Addendum!C:C,A35,Addendum!D:D,IF(ISNUMBER(B35),TEXT(B35,"0000"),B35),Addendum!I:I,"X")>0,10%,0) -> 0 | M35: =IF(AND(I35=0%,J35=0%,K35=0%,L35=0%),0%, IF(OR(TRIM(E35)="OneTime",TRIM(D35)=""),0%, IF( OR( TRIM(D35)="P1M", AND(TRIM(D35)="P1Y",TRIM(E35)="Monthly"), AND(TRIM(D35)="P3Y",TRIM(E35)="Monthly") ), IF(AND(I35=4%,J35=0%,K35=0%,L35=0%),1%, IF(AND(I35=4%,J35=2.5%,K35=0%,L35=10%),2%, IF(AND(I35=4%,J35=0%,K35=7%,L35=10%),3%,0%))), IF( OR( AND(TRIM(D35)="P1Y",TRIM(E35)="Annual"), AND(TRIM(D35)="P3Y",TRIM(E35)="Annual"), AND(TRIM(D35)="P3Y",TRIM(E35)="Triennial") ), IF(AND(I35=4%,J35=0%,K35=0%,L35=0%),3%, IF(AND(I35=4%,J35=2.5%,K35=0%,L35=10%),10%, IF(AND(I35=4%,J35=0%,K35=7%,L35=10%),14%,0%))), 0% )))) -> 0 | N35: =H35-(H35*M35) -> 35964
A36: CFQ7TTC0LHQD | B36: 1 | C36: Advanced eDiscovery Storage | D36: P1M | E36: Monthly | F36: Commercial | G36: 9984 | H36: 7987.2 | I36: =IF(COUNTIFS(Addendum!C:C,A36,Addendum!D:D,IF(ISNUMBER(B36),TEXT(B36,"0000"),B36),Addendum!E:E,"X")>0,4%,0) -> 0 | J36: =IF(COUNTIFS(Addendum!C:C,A36,Addendum!D:D,IF(ISNUMBER(B36),TEXT(B36,"0000"),B36),Addendum!F:F,"X")>0,2.5%,0) -> 0 | K36: =IF(COUNTIFS(Addendum!C:C,A36,Addendum!D:D,IF(ISNUMBER(B36),TEXT(B36,"0000"),B36),Addendum!G:G,"X")>0,7%,0) -> 0 | L36: =IF(COUNTIFS(Addendum!C:C,A36,Addendum!D:D,IF(ISNUMBER(B36),TEXT(B36,"0000"),B36),Addendum!I:I,"X")>0,10%,0) -> 0 | M36: =IF(AND(I36=0%,J36=0%,K36=0%,L36=0%),0%, IF(OR(TRIM(E36)="OneTime",TRIM(D36)=""),0%, IF( OR( TRIM(D36)="P1M", AND(TRIM(D36)="P1Y",TRIM(E36)="Monthly"), AND(TRIM(D36)="P3Y",TRIM(E36)="Monthly") ), IF(AND(I36=4%,J36=0%,K36=0%,L36=0%),1%, IF(AND(I36=4%,J36=2.5%,K36=0%,L36=10%),2%, IF(AND(I36=4%,J36=0%,K36=7%,L36=10%),3%,0%))), IF( OR( AND(TRIM(D36)="P1Y",TRIM(E36)="Annual"), AND(TRIM(D36)="P3Y",TRIM(E36)="Annual"), AND(TRIM(D36)="P3Y",TRIM(E36)="Triennial") ), IF(AND(I36=4%,J36=0%,K36=0%,L36=0%),3%, IF(AND(I36=4%,J36=2.5%,K36=0%,L36=10%),10%, IF(AND(I36=4%,J36=0%,K36=7%,L36=10%),14%,0%))), 0% )))) -> 0 | N36: =H36-(H36*M36) -> 7987.2
A37: CFQ7TTC10RSN | B37: 3 | C37: Microsoft Defender and Purview Suites for Microsoft 365 Business Premium | D37: P1Y | E37: Monthly | F37: Commercial | G37: 15750 | H37: 12600 | I37: =IF(COUNTIFS(Addendum!C:C,A37,Addendum!D:D,IF(ISNUMBER(B37),TEXT(B37,"0000"),B37),Addendum!E:E,"X")>0,4%,0) -> 0.04 | J37: =IF(COUNTIFS(Addendum!C:C,A37,Addendum!D:D,IF(ISNUMBER(B37),TEXT(B37,"0000"),B37),Addendum!F:F,"X")>0,2.5%,0) -> 0.025 | K37: =IF(COUNTIFS(Addendum!C:C,A37,Addendum!D:D,IF(ISNUMBER(B37),TEXT(B37,"0000"),B37),Addendum!G:G,"X")>0,7%,0) -> 0 | L37: =IF(COUNTIFS(Addendum!C:C,A37,Addendum!D:D,IF(ISNUMBER(B37),TEXT(B37,"0000"),B37),Addendum!I:I,"X")>0,10%,0) -> 0.1 | M37: =IF(AND(I37=0%,J37=0%,K37=0%,L37=0%),0%, IF(OR(TRIM(E37)="OneTime",TRIM(D37)=""),0%, IF( OR( TRIM(D37)="P1M", AND(TRIM(D37)="P1Y",TRIM(E37)="Monthly"), AND(TRIM(D37)="P3Y",TRIM(E37)="Monthly") ), IF(AND(I37=4%,J37=0%,K37=0%,L37=0%),1%, IF(AND(I37=4%,J37=2.5%,K37=0%,L37=10%),2%, IF(AND(I37=4%,J37=0%,K37=7%,L37=10%),3%,0%))), IF( OR( AND(TRIM(D37)="P1Y",TRIM(E37)="Annual"), AND(TRIM(D37)="P3Y",TRIM(E37)="Annual"), AND(TRIM(D37)="P3Y",TRIM(E37)="Triennial") ), IF(AND(I37=4%,J37=0%,K37=0%,L37=0%),3%, IF(AND(I37=4%,J37=2.5%,K37=0%,L37=10%),10%, IF(AND(I37=4%,J37=0%,K37=7%,L37=10%),14%,0%))), 0% )))) -> 0.02 | N37: =H37-(H37*M37) -> 12348
A38: CFQ7TTC10RSN | B38: 1 | C38: Microsoft Defender Suite for Microsoft 365 Business Premium | D38: P1Y | E38: Monthly | F38: Commercial | G38: 10458 | H38: 8366.4 | I38: =IF(COUNTIFS(Addendum!C:C,A38,Addendum!D:D,IF(ISNUMBER(B38),TEXT(B38,"0000"),B38),Addendum!E:E,"X")>0,4%,0) -> 0.04 | J38: =IF(COUNTIFS(Addendum!C:C,A38,Addendum!D:D,IF(ISNUMBER(B38),TEXT(B38,"0000"),B38),Addendum!F:F,"X")>0,2.5%,0) -> 0.025 | K38: =IF(COUNTIFS(Addendum!C:C,A38,Addendum!D:D,IF(ISNUMBER(B38),TEXT(B38,"0000"),B38),Addendum!G:G,"X")>0,7%,0) -> 0 | L38: =IF(COUNTIFS(Addendum!C:C,A38,Addendum!D:D,IF(ISNUMBER(B38),TEXT(B38,"0000"),B38),Addendum!I:I,"X")>0,10%,0) -> 0.1 | M38: =IF(AND(I38=0%,J38=0%,K38=0%,L38=0%),0%, IF(OR(TRIM(E38)="OneTime",TRIM(D38)=""),0%, IF( OR( TRIM(D38)="P1M", AND(TRIM(D38)="P1Y",TRIM(E38)="Monthly"), AND(TRIM(D38)="P3Y",TRIM(E38)="Monthly") ), IF(AND(I38=4%,J38=0%,K38=0%,L38=0%),1%, IF(AND(I38=4%,J38=2.5%,K38=0%,L38=10%),2%, IF(AND(I38=4%,J38=0%,K38=7%,L38=10%),3%,0%))), IF( OR( AND(TRIM(D38)="P1Y",TRIM(E38)="Annual"), AND(TRIM(D38)="P3Y",TRIM(E38)="Annual"), AND(TRIM(D38)="P3Y",TRIM(E38)="Triennial") ), IF(AND(I38=4%,J38=0%,K38=0%,L38=0%),3%, IF(AND(I38=4%,J38=2.5%,K38=0%,L38=10%),10%, IF(AND(I38=4%,J38=0%,K38=7%,L38=10%),14%,0%))), 0% )))) -> 0.02 | N38: =H38-(H38*M38) -> 8199.072
A39: CFQ7TTC10RSN | B39: 7 | C39: Microsoft Purview Suite for Microsoft 365 Business Premium (Non-Profit Pricing) | D39: P1Y | E39: Monthly | F39: Charity | G39: 4221 | H39: 3798.96 | I39: =IF(COUNTIFS(Addendum!C:C,A39,Addendum!D:D,IF(ISNUMBER(B39),TEXT(B39,"0000"),B39),Addendum!E:E,"X")>0,4%,0) -> 0.04 | J39: =IF(COUNTIFS(Addendum!C:C,A39,Addendum!D:D,IF(ISNUMBER(B39),TEXT(B39,"0000"),B39),Addendum!F:F,"X")>0,2.5%,0) -> 0.025 | K39: =IF(COUNTIFS(Addendum!C:C,A39,Addendum!D:D,IF(ISNUMBER(B39),TEXT(B39,"0000"),B39),Addendum!G:G,"X")>0,7%,0) -> 0 | L39: =IF(COUNTIFS(Addendum!C:C,A39,Addendum!D:D,IF(ISNUMBER(B39),TEXT(B39,"0000"),B39),Addendum!I:I,"X")>0,10%,0) -> 0.1 | M39: =IF(AND(I39=0%,J39=0%,K39=0%,L39=0%),0%, IF(OR(TRIM(E39)="OneTime",TRIM(D39)=""),0%, IF( OR( TRIM(D39)="P1M", AND(TRIM(D39)="P1Y",TRIM(E39)="Monthly"), AND(TRIM(D39)="P3Y",TRIM(E39)="Monthly") ), IF(AND(I39=4%,J39=0%,K39=0%,L39=0%),1%, IF(AND(I39=4%,J39=2.5%,K39=0%,L39=10%),2%, IF(AND(I39=4%,J39=0%,K39=7%,L39=10%),3%,0%))), IF( OR( AND(TRIM(D39)="P1Y",TRIM(E39)="Annual"), AND(TRIM(D39)="P3Y",TRIM(E39)="Annual"), AND(TRIM(D39)="P3Y",TRIM(E39)="Triennial") ), IF(AND(I39=4%,J39=0%,K39=0%,L39=0%),3%, IF(AND(I39=4%,J39=2.5%,K39=0%,L39=10%),10%, IF(AND(I39=4%,J39=0%,K39=7%,L39=10%),14%,0%))), 0% )))) -> 0.02 | N39: =H39-(H39*M39) -> 3722.9808
... A73: CFQ7TTC0LHRL | B73: 2 | C73: Dataverse Database Capacity add-on | D73: P1Y | E73: Annual | F73: Commercial | G73: 39960 | H73: 29970 | I73: =IF(COUNTIFS(Addendum!C:C,A73,Addendum!D:D,IF(ISNUMBER(B73),TEXT(B73,"0000"),B73),Addendum!E:E,"X")>0,4%,0) -> 0 | J73: =IF(COUNTIFS(Addendum!C:C,A73,Addendum!D:D,IF(ISNUMBER(B73),TEXT(B73,"0000"),B73),Addendum!F:F,"X")>0,2.5%,0) -> 0 | K73: =IF(COUNTIFS(Addendum!C:C,A73,Addendum!D:D,IF(ISNUMBER(B73),TEXT(B73,"0000"),B73),Addendum!G:G,"X")>0,7%,0) -> 0 | L73: =IF(COUNTIFS(Addendum!C:C,A73,Addendum!D:D,IF(ISNUMBER(B73),TEXT(B73,"0000"),B73),Addendum!I:I,"X")>0,10%,0) -> 0 | M73: =IF(AND(I73=0%,J73=0%,K73=0%,L73=0%),0%, IF(OR(TRIM(E73)="OneTime",TRIM(D73)=""),0%, IF( OR( TRIM(D73)="P1M", AND(TRIM(D73)="P1Y",TRIM(E73)="Monthly"), AND(TRIM(D73)="P3Y",TRIM(E73)="Monthly") ), IF(AND(I73=4%,J73=0%,K73=0%,L73=0%),1%, IF(AND(I73=4%,J73=2.5%,K73=0%,L73=10%),2%, IF(AND(I73=4%,J73=0%,K73=7%,L73=10%),3%,0%))), IF( OR( AND(TRIM(D73)="P1Y",TRIM(E73)="Annual"), AND(TRIM(D73)="P3Y",TRIM(E73)="Annual"), AND(TRIM(D73)="P3Y",TRIM(E73)="Triennial") ), IF(AND(I73=4%,J73=0%,K73=0%,L73=0%),3%, IF(AND(I73=4%,J73=2.5%,K73=0%,L73=10%),10%, IF(AND(I73=4%,J73=0%,K73=7%,L73=10%),14%,0%))), 0% )))) -> 0 | N73: =H73-(H73*M73) -> 29970
A74: CFQ7TTC0LHRL | B74: 000H | C74: Dataverse Database Capacity add-on (Education Pricing) | D74: P1M | E74: Monthly | F74: Education | G74: 2796 | H74: 2097 | I74: =IF(COUNTIFS(Addendum!C:C,A74,Addendum!D:D,IF(ISNUMBER(B74),TEXT(B74,"0000"),B74),Addendum!E:E,"X")>0,4%,0) -> 0 | J74: =IF(COUNTIFS(Addendum!C:C,A74,Addendum!D:D,IF(ISNUMBER(B74),TEXT(B74,"0000"),B74),Addendum!F:F,"X")>0,2.5%,0) -> 0 | K74: =IF(COUNTIFS(Addendum!C:C,A74,Addendum!D:D,IF(ISNUMBER(B74),TEXT(B74,"0000"),B74),Addendum!G:G,"X")>0,7%,0) -> 0 | L74: =IF(COUNTIFS(Addendum!C:C,A74,Addendum!D:D,IF(ISNUMBER(B74),TEXT(B74,"0000"),B74),Addendum!I:I,"X")>0,10%,0) -> 0 | M74: =IF(AND(I74=0%,J74=0%,K74=0%,L74=0%),0%, IF(OR(TRIM(E74)="OneTime",TRIM(D74)=""),0%, IF( OR( TRIM(D74)="P1M", AND(TRIM(D74)="P1Y",TRIM(E74)="Monthly"), AND(TRIM(D74)="P3Y",TRIM(E74)="Monthly") ), IF(AND(I74=4%,J74=0%,K74=0%,L74=0%),1%, IF(AND(I74=4%,J74=2.5%,K74=0%,L74=10%),2%, IF(AND(I74=4%,J74=0%,K74=7%,L74=10%),3%,0%))), IF( OR( AND(TRIM(D74)="P1Y",TRIM(E74)="Annual"), AND(TRIM(D74)="P3Y",TRIM(E74)="Annual"), AND(TRIM(D74)="P3Y",TRIM(E74)="Triennial") ), IF(AND(I74=4%,J74=0%,K74=0%,L74=0%),3%, IF(AND(I74=4%,J74=2.5%,K74=0%,L74=10%),10%, IF(AND(I74=4%,J74=0%,K74=7%,L74=10%),14%,0%))), 0% )))) -> 0 | N74: =H74-(H74*M74) -> 2097
A75: CFQ7TTC0LHRL | B75: 2 | C75: Dataverse Database Capacity add-on | D75: P1M | E75: Monthly | F75: Commercial | G75: 3996 | H75: 2997 | I75: =IF(COUNTIFS(Addendum!C:C,A75,Addendum!D:D,IF(ISNUMBER(B75),TEXT(B75,"0000"),B75),Addendum!E:E,"X")>0,4%,0) -> 0 | J75: =IF(COUNTIFS(Addendum!C:C,A75,Addendum!D:D,IF(ISNUMBER(B75),TEXT(B75,"0000"),B75),Addendum!F:F,"X")>0,2.5%,0) -> 0 | K75: =IF(COUNTIFS(Addendum!C:C,A75,Addendum!D:D,IF(ISNUMBER(B75),TEXT(B75,"0000"),B75),Addendum!G:G,"X")>0,7%,0) -> 0 | L75: =IF(COUNTIFS(Addendum!C:C,A75,Addendum!D:D,IF(ISNUMBER(B75),TEXT(B75,"0000"),B75),Addendum!I:I,"X")>0,10%,0) -> 0 | M75: =IF(AND(I75=0%,J75=0%,K75=0%,L75=0%),0%, IF(OR(TRIM(E75)="OneTime",TRIM(D75)=""),0%, IF( OR( TRIM(D75)="P1M", AND(TRIM(D75)="P1Y",TRIM(E75)="Monthly"), AND(TRIM(D75)="P3Y",TRIM(E75)="Monthly") ), IF(AND(I75=4%,J75=0%,K75=0%,L75=0%),1%, IF(AND(I75=4%,J75=2.5%,K75=0%,L75=10%),2%, IF(AND(I75=4%,J75=0%,K75=7%,L75=10%),3%,0%))), IF( OR( AND(TRIM(D75)="P1Y",TRIM(E75)="Annual"), AND(TRIM(D75)="P3Y",TRIM(E75)="Annual"), AND(TRIM(D75)="P3Y",TRIM(E75)="Triennial") ), IF(AND(I75=4%,J75=0%,K75=0%,L75=0%),3%, IF(AND(I75=4%,J75=2.5%,K75=0%,L75=10%),10%, IF(AND(I75=4%,J75=0%,K75=7%,L75=10%),14%,0%))), 0% )))) -> 0 | N75: =H75-(H75*M75) -> 2997
A76: CFQ7TTC0LHRL | B76: 000J | C76: Dataverse Database Capacity add-on (Non-Profit Pricing) | D76: P1Y | E76: Monthly | F76: Charity | G76: 29358 | H76: 26422.2 | I76: =IF(COUNTIFS(Addendum!C:C,A76,Addendum!D:D,IF(ISNUMBER(B76),TEXT(B76,"0000"),B76),Addendum!E:E,"X")>0,4%,0) -> 0 | J76: =IF(COUNTIFS(Addendum!C:C,A76,Addendum!D:D,IF(ISNUMBER(B76),TEXT(B76,"0000"),B76),Addendum!F:F,"X")>0,2.5%,0) -> 0 | K76: =IF(COUNTIFS(Addendum!C:C,A76,Addendum!D:D,IF(ISNUMBER(B76),TEXT(B76,"0000"),B76),Addendum!G:G,"X")>0,7%,0) -> 0 | L76: =IF(COUNTIFS(Addendum!C:C,A76,Addendum!D:D,IF(ISNUMBER(B76),TEXT(B76,"0000"),B76),Addendum!I:I,"X")>0,10%,0) -> 0 | M76: =IF(AND(I76=0%,J76=0%,K76=0%,L76=0%),0%, IF(OR(TRIM(E76)="OneTime",TRIM(D76)=""),0%, IF( OR( TRIM(D76)="P1M", AND(TRIM(D76)="P1Y",TRIM(E76)="Monthly"), AND(TRIM(D76)="P3Y",TRIM(E76)="Monthly") ), IF(AND(I76=4%,J76=0%,K76=0%,L76=0%),1%, IF(AND(I76=4%,J76=2.5%,K76=0%,L76=10%),2%, IF(AND(I76=4%,J76=0%,K76=7%,L76=10%),3%,0%))), IF( OR( AND(TRIM(D76)="P1Y",TRIM(E76)="Annual"), AND(TRIM(D76)="P3Y",TRIM(E76)="Annual"), AND(TRIM(D76)="P3Y",TRIM(E76)="Triennial") ), IF(AND(I76=4%,J76=0%,K76=0%,L76=0%),3%, IF(AND(I76=4%,J76=2.5%,K76=0%,L76=10%),10%, IF(AND(I76=4%,J76=0%,K76=7%,L76=10%),14%,0%))), 0% )))) -> 0 | N76: =H76-(H76*M76) -> 26422.2
A77: CFQ7TTC0LHRL | B77: 2 | C77: Dataverse Database Capacity add-on | D77: P1Y | E77: Monthly | F77: Commercial | G77: 41958 | H77: 31468.56 | I77: =IF(COUNTIFS(Addendum!C:C,A77,Addendum!D:D,IF(ISNUMBER(B77),TEXT(B77,"0000"),B77),Addendum!E:E,"X")>0,4%,0) -> 0 | J77: =IF(COUNTIFS(Addendum!C:C,A77,Addendum!D:D,IF(ISNUMBER(B77),TEXT(B77,"0000"),B77),Addendum!F:F,"X")>0,2.5%,0) -> 0 | K77: =IF(COUNTIFS(Addendum!C:C,A77,Addendum!D:D,IF(ISNUMBER(B77),TEXT(B77,"0000"),B77),Addendum!G:G,"X")>0,7%,0) -> 0 | L77: =IF(COUNTIFS(Addendum!C:C,A77,Addendum!D:D,IF(ISNUMBER(B77),TEXT(B77,"0000"),B77),Addendum!I:I,"X")>0,10%,0) -> 0 | M77: =IF(AND(I77=0%,J77=0%,K77=0%,L77=0%),0%, IF(OR(TRIM(E77)="OneTime",TRIM(D77)=""),0%, IF( OR( TRIM(D77)="P1M", AND(TRIM(D77)="P1Y",TRIM(E77)="Monthly"), AND(TRIM(D77)="P3Y",TRIM(E77)="Monthly") ), IF(AND(I77=4%,J77=0%,K77=0%,L77=0%),1%, IF(AND(I77=4%,J77=2.5%,K77=0%,L77=10%),2%, IF(AND(I77=4%,J77=0%,K77=7%,L77=10%),3%,0%))), IF( OR( AND(TRIM(D77)="P1Y",TRIM(E77)="Annual"), AND(TRIM(D77)="P3Y",TRIM(E77)="Annual"), AND(TRIM(D77)="P3Y",TRIM(E77)="Triennial") ), IF(AND(I77=4%,J77=0%,K77=0%,L77=0%),3%, IF(AND(I77=4%,J77=2.5%,K77=0%,L77=10%),10%, IF(AND(I77=4%,J77=0%,K77=7%,L77=10%),14%,0%))), 0% )))) -> 0 | N77: =H77-(H77*M77) -> 31468.56
A78: CFQ7TTC0LHRL | B78: 000H | C78: Dataverse Database Capacity add-on (Education Pricing) | D78: P1Y | E78: Monthly | F78: Education | G78: 29358 | H78: 22018.56 | I78: =IF(COUNTIFS(Addendum!C:C,A78,Addendum!D:D,IF(ISNUMBER(B78),TEXT(B78,"0000"),B78),Addendum!E:E,"X")>0,4%,0) -> 0 | J78: =IF(COUNTIFS(Addendum!C:C,A78,Addendum!D:D,IF(ISNUMBER(B78),TEXT(B78,"0000"),B78),Addendum!F:F,"X")>0,2.5%,0) -> 0 | K78: =IF(COUNTIFS(Addendum!C:C,A78,Addendum!D:D,IF(ISNUMBER(B78),TEXT(B78,"0000"),B78),Addendum!G:G,"X")>0,7%,0) -> 0 | L78: =IF(COUNTIFS(Addendum!C:C,A78,Addendum!D:D,IF(ISNUMBER(B78),TEXT(B78,"0000"),B78),Addendum!I:I,"X")>0,10%,0) -> 0 | M78: =IF(AND(I78=0%,J78=0%,K78=0%,L78=0%),0%, IF(OR(TRIM(E78)="OneTime",TRIM(D78)=""),0%, IF( OR( TRIM(D78)="P1M", AND(TRIM(D78)="P1Y",TRIM(E78)="Monthly"), AND(TRIM(D78)="P3Y",TRIM(E78)="Monthly") ), IF(AND(I78=4%,J78=0%,K78=0%,L78=0%),1%, IF(AND(I78=4%,J78=2.5%,K78=0%,L78=10%),2%, IF(AND(I78=4%,J78=0%,K78=7%,L78=10%),3%,0%))), IF( OR( AND(TRIM(D78)="P1Y",TRIM(E78)="Annual"), AND(TRIM(D78)="P3Y",TRIM(E78)="Annual"), AND(TRIM(D78)="P3Y",TRIM(E78)="Triennial") ), IF(AND(I78=4%,J78=0%,K78=0%,L78=0%),3%, IF(AND(I78=4%,J78=2.5%,K78=0%,L78=10%),10%, IF(AND(I78=4%,J78=0%,K78=7%,L78=10%),14%,0%))), 0% )))) -> 0 | N78: =H78-(H78*M78) -> 22018.56
A79: CFQ7TTC0LHRL | B79: 000J | C79: Dataverse Database Capacity add-on (Non-Profit Pricing) | D79: P1M | E79: Monthly | F79: Charity | G79: 2796 | H79: 2516.4 | I79: =IF(COUNTIFS(Addendum!C:C,A79,Addendum!D:D,IF(ISNUMBER(B79),TEXT(B79,"0000"),B79),Addendum!E:E,"X")>0,4%,0) -> 0 | J79: =IF(COUNTIFS(Addendum!C:C,A79,Addendum!D:D,IF(ISNUMBER(B79),TEXT(B79,"0000"),B79),Addendum!F:F,"X")>0,2.5%,0) -> 0 | K79: =IF(COUNTIFS(Addendum!C:C,A79,Addendum!D:D,IF(ISNUMBER(B79),TEXT(B79,"0000"),B79),Addendum!G:G,"X")>0,7%,0) -> 0 | L79: =IF(COUNTIFS(Addendum!C:C,A79,Addendum!D:D,IF(ISNUMBER(B79),TEXT(B79,"0000"),B79),Addendum!I:I,"X")>0,10%,0) -> 0 | M79: =IF(AND(I79=0%,J79=0%,K79=0%,L79=0%),0%, IF(OR(TRIM(E79)="OneTime",TRIM(D79)=""),0%, IF( OR( TRIM(D79)="P1M", AND(TRIM(D79)="P1Y",TRIM(E79)="Monthly"), AND(TRIM(D79)="P3Y",TRIM(E79)="Monthly") ), IF(AND(I79=4%,J79=0%,K79=0%,L79=0%),1%, IF(AND(I79=4%,J79=2.5%,K79=0%,L79=10%),2%, IF(AND(I79=4%,J79=0%,K79=7%,L79=10%),3%,0%))), IF( OR( AND(TRIM(D79)="P1Y",TRIM(E79)="Annual"), AND(TRIM(D79)="P3Y",TRIM(E79)="Annual"), AND(TRIM(D79)="P3Y",TRIM(E79)="Triennial") ), IF(AND(I79=4%,J79=0%,K79=0%,L79=0%),3%, IF(AND(I79=4%,J79=2.5%,K79=0%,L79=10%),10%, IF(AND(I79=4%,J79=0%,K79=7%,L79=10%),14%,0%))), 0% )))) -> 0 | N79: =H79-(H79*M79) -> 2516.4
A80: CFQ7TTC0LHRL | B80: 000H | C80: Dataverse Database Capacity add-on (Education Pricing) | D80: P1Y | E80: Annual | F80: Education | G80: 27960 | H80: 20970 | I80: =IF(COUNTIFS(Addendum!C:C,A80,Addendum!D:D,IF(ISNUMBER(B80),TEXT(B80,"0000"),B80),Addendum!E:E,"X")>0,4%,0) -> 0 | J80: =IF(COUNTIFS(Addendum!C:C,A80,Addendum!D:D,IF(ISNUMBER(B80),TEXT(B80,"0000"),B80),Addendum!F:F,"X")>0,2.5%,0) -> 0 | K80: =IF(COUNTIFS(Addendum!C:C,A80,Addendum!D:D,IF(ISNUMBER(B80),TEXT(B80,"0000"),B80),Addendum!G:G,"X")>0,7%,0) -> 0 | L80: =IF(COUNTIFS(Addendum!C:C,A80,Addendum!D:D,IF(ISNUMBER(B80),TEXT(B80,"0000"),B80),Addendum!I:I,"X")>0,10%,0) -> 0 | M80: =IF(AND(I80=0%,J80=0%,K80=0%,L80=0%),0%, IF(OR(TRIM(E80)="OneTime",TRIM(D80)=""),0%, IF( OR( TRIM(D80)="P1M", AND(TRIM(D80)="P1Y",TRIM(E80)="Monthly"), AND(TRIM(D80)="P3Y",TRIM(E80)="Monthly") ), IF(AND(I80=4%,J80=0%,K80=0%,L80=0%),1%, IF(AND(I80=4%,J80=2.5%,K80=0%,L80=10%),2%, IF(AND(I80=4%,J80=0%,K80=7%,L80=10%),3%,0%))), IF( OR( AND(TRIM(D80)="P1Y",TRIM(E80)="Annual"), AND(TRIM(D80)="P3Y",TRIM(E80)="Annual"), AND(TRIM(D80)="P3Y",TRIM(E80)="Triennial") ), IF(AND(I80=4%,J80=0%,K80=0%,L80=0%),3%, IF(AND(I80=4%,J80=2.5%,K80=0%,L80=10%),10%, IF(AND(I80=4%,J80=0%,K80=7%,L80=10%),14%,0%))), 0% )))) -> 0 | N80: =H80-(H80*M80) -> 20970
A81: CFQ7TTC0LHRL | B81: 000J | C81: Dataverse Database Capacity add-on (Non-Profit Pricing) | D81: P1Y | E81: Annual | F81: Charity | G81: 27960 | H81: 25164 | I81: =IF(COUNTIFS(Addendum!C:C,A81,Addendum!D:D,IF(ISNUMBER(B81),TEXT(B81,"0000"),B81),Addendum!E:E,"X")>0,4%,0) -> 0 | J81: =IF(COUNTIFS(Addendum!C:C,A81,Addendum!D:D,IF(ISNUMBER(B81),TEXT(B81,"0000"),B81),Addendum!F:F,"X")>0,2.5%,0) -> 0 | K81: =IF(COUNTIFS(Addendum!C:C,A81,Addendum!D:D,IF(ISNUMBER(B81),TEXT(B81,"0000"),B81),Addendum!G:G,"X")>0,7%,0) -> 0 | L81: =IF(COUNTIFS(Addendum!C:C,A81,Addendum!D:D,IF(ISNUMBER(B81),TEXT(B81,"0000"),B81),Addendum!I:I,"X")>0,10%,0) -> 0 | M81: =IF(AND(I81=0%,J81=0%,K81=0%,L81=0%),0%, IF(OR(TRIM(E81)="OneTime",TRIM(D81)=""),0%, IF( OR( TRIM(D81)="P1M", AND(TRIM(D81)="P1Y",TRIM(E81)="Monthly"), AND(TRIM(D81)="P3Y",TRIM(E81)="Monthly") ), IF(AND(I81=4%,J81=0%,K81=0%,L81=0%),1%, IF(AND(I81=4%,J81=2.5%,K81=0%,L81=10%),2%, IF(AND(I81=4%,J81=0%,K81=7%,L81=10%),3%,0%))), IF( OR( AND(TRIM(D81)="P1Y",TRIM(E81)="Annual"), AND(TRIM(D81)="P3Y",TRIM(E81)="Annual"), AND(TRIM(D81)="P3Y",TRIM(E81)="Triennial") ), IF(AND(I81=4%,J81=0%,K81=0%,L81=0%),3%, IF(AND(I81=4%,J81=2.5%,K81=0%,L81=10%),10%, IF(AND(I81=4%,J81=0%,K81=7%,L81=10%),14%,0%))), 0% )))) -> 0 | N81: =H81-(H81*M81) -> 25164
A82: CFQ7TTC0NCD7 | B82: 3 | C82: Dataverse Database Capacity add-on Tier 2 (Min 1000GB) | D82: P1M | E82: Monthly | F82: Commercial | G82: 2994 | H82: 2245.5 | I82: =IF(COUNTIFS(Addendum!C:C,A82,Addendum!D:D,IF(ISNUMBER(B82),TEXT(B82,"0000"),B82),Addendum!E:E,"X")>0,4%,0) -> 0 | J82: =IF(COUNTIFS(Addendum!C:C,A82,Addendum!D:D,IF(ISNUMBER(B82),TEXT(B82,"0000"),B82),Addendum!F:F,"X")>0,2.5%,0) -> 0 | K82: =IF(COUNTIFS(Addendum!C:C,A82,Addendum!D:D,IF(ISNUMBER(B82),TEXT(B82,"0000"),B82),Addendum!G:G,"X")>0,7%,0) -> 0 | L82: =IF(COUNTIFS(Addendum!C:C,A82,Addendum!D:D,IF(ISNUMBER(B82),TEXT(B82,"0000"),B82),Addendum!I:I,"X")>0,10%,0) -> 0 | M82: =IF(AND(I82=0%,J82=0%,K82=0%,L82=0%),0%, IF(OR(TRIM(E82)="OneTime",TRIM(D82)=""),0%, IF( OR( TRIM(D82)="P1M", AND(TRIM(D82)="P1Y",TRIM(E82)="Monthly"), AND(TRIM(D82)="P3Y",TRIM(E82)="Monthly") ), IF(AND(I82=4%,J82=0%,K82=0%,L82=0%),1%, IF(AND(I82=4%,J82=2.5%,K82=0%,L82=10%),2%, IF(AND(I82=4%,J82=0%,K82=7%,L82=10%),3%,0%))), IF( OR( AND(TRIM(D82)="P1Y",TRIM(E82)="Annual"), AND(TRIM(D82)="P3Y",TRIM(E82)="Annual"), AND(TRIM(D82)="P3Y",TRIM(E82)="Triennial") ), IF(AND(I82=4%,J82=0%,K82=0%,L82=0%),3%, IF(AND(I82=4%,J82=2.5%,K82=0%,L82=10%),10%, IF(AND(I82=4%,J82=0%,K82=7%,L82=10%),14%,0%))), 0% )))) -> 0 | N82: =H82-(H82*M82) -> 2245.5
A83: CFQ7TTC0NCD7 | B83: 3 | C83: Dataverse Database Capacity add-on Tier 2 (Min 1000GB) | D83: P1Y | E83: Annual | F83: Commercial | G83: 29940 | H83: 22455 | I83: =IF(COUNTIFS(Addendum!C:C,A83,Addendum!D:D,IF(ISNUMBER(B83),TEXT(B83,"0000"),B83),Addendum!E:E,"X")>0,4%,0) -> 0 | J83: =IF(COUNTIFS(Addendum!C:C,A83,Addendum!D:D,IF(ISNUMBER(B83),TEXT(B83,"0000"),B83),Addendum!F:F,"X")>0,2.5%,0) -> 0 | K83: =IF(COUNTIFS(Addendum!C:C,A83,Addendum!D:D,IF(ISNUMBER(B83),TEXT(B83,"0000"),B83),Addendum!G:G,"X")>0,7%,0) -> 0 | L83: =IF(COUNTIFS(Addendum!C:C,A83,Addendum!D:D,IF(ISNUMBER(B83),TEXT(B83,"0000"),B83),Addendum!I:I,"X")>0,10%,0) -> 0 | M83: =IF(AND(I83=0%,J83=0%,K83=0%,L83=0%),0%, IF(OR(TRIM(E83)="OneTime",TRIM(D83)=""),0%, IF( OR( TRIM(D83)="P1M", AND(TRIM(D83)="P1Y",TRIM(E83)="Monthly"), AND(TRIM(D83)="P3Y",TRIM(E83)="Monthly") ), IF(AND(I83=4%,J83=0%,K83=0%,L83=0%),1%, IF(AND(I83=4%,J83=2.5%,K83=0%,L83=10%),2%, IF(AND(I83=4%,J83=0%,K83=7%,L83=10%),3%,0%))), IF( OR( AND(TRIM(D83)="P1Y",TRIM(E83)="Annual"), AND(TRIM(D83)="P3Y",TRIM(E83)="Annual"), AND(TRIM(D83)="P3Y",TRIM(E83)="Triennial") ), IF(AND(I83=4%,J83=0%,K83=0%,L83=0%),3%, IF(AND(I83=4%,J83=2.5%,K83=0%,L83=10%),10%, IF(AND(I83=4%,J83=0%,K83=7%,L83=10%),14%,0%))), 0% )))) -> 0 | N83: =H83-(H83*M83) -> 22455
A84: CFQ7TTC0NCD7 | B84: 3 | C84: Dataverse Database Capacity add-on Tier 2 (Min 1000GB) | D84: P1Y | E84: Monthly | F84: Commercial | G84: 31437 | H84: 23577.72 | I84: =IF(COUNTIFS(Addendum!C:C,A84,Addendum!D:D,IF(ISNUMBER(B84),TEXT(B84,"0000"),B84),Addendum!E:E,"X")>0,4%,0) -> 0 | J84: =IF(COUNTIFS(Addendum!C:C,A84,Addendum!D:D,IF(ISNUMBER(B84),TEXT(B84,"0000"),B84),Addendum!F:F,"X")>0,2.5%,0) -> 0 | K84: =IF(COUNTIFS(Addendum!C:C,A84,Addendum!D:D,IF(ISNUMBER(B84),TEXT(B84,"0000"),B84),Addendum!G:G,"X")>0,7%,0) -> 0 | L84: =IF(COUNTIFS(Addendum!C:C,A84,Addendum!D:D,IF(ISNUMBER(B84),TEXT(B84,"0000"),B84),Addendum!I:I,"X")>0,10%,0) -> 0 | M84: =IF(AND(I84=0%,J84=0%,K84=0%,L84=0%),0%, IF(OR(TRIM(E84)="OneTime",TRIM(D84)=""),0%, IF( OR( TRIM(D84)="P1M", AND(TRIM(D84)="P1Y",TRIM(E84)="Monthly"), AND(TRIM(D84)="P3Y",TRIM(E84)="Monthly") ), IF(AND(I84=4%,J84=0%,K84=0%,L84=0%),1%, IF(AND(I84=4%,J84=2.5%,K84=0%,L84=10%),2%, IF(AND(I84=4%,J84=0%,K84=7%,L84=10%),3%,0%))), IF( OR( AND(TRIM(D84)="P1Y",TRIM(E84)="Annual"), AND(TRIM(D84)="P3Y",TRIM(E84)="Annual"), AND(TRIM(D84)="P3Y",TRIM(E84)="Triennial") ), IF(AND(I84=4%,J84=0%,K84=0%,L84=0%),3%, IF(AND(I84=4%,J84=2.5%,K84=0%,L84=10%),10%, IF(AND(I84=4%,J84=0%,K84=7%,L84=10%),14%,0%))), 0% )))) -> 0 | N84: =H84-(H84*M84) -> 23577.72
A85: CFQ7TTC0NCD7 | B85: 2 | C85: Dataverse Database Capacity add-on Tier 2 (Min 1000GB) | D85: P1M | E85: None | F85: Commercial | G85: 0 | H85: 0 | I85: =IF(COUNTIFS(Addendum!C:C,A85,Addendum!D:D,IF(ISNUMBER(B85),TEXT(B85,"0000"),B85),Addendum!E:E,"X")>0,4%,0) -> 0 | J85: =IF(COUNTIFS(Addendum!C:C,A85,Addendum!D:D,IF(ISNUMBER(B85),TEXT(B85,"0000"),B85),Addendum!F:F,"X")>0,2.5%,0) -> 0 | K85: =IF(COUNTIFS(Addendum!C:C,A85,Addendum!D:D,IF(ISNUMBER(B85),TEXT(B85,"0000"),B85),Addendum!G:G,"X")>0,7%,0) -> 0 | L85: =IF(COUNTIFS(Addendum!C:C,A85,Addendum!D:D,IF(ISNUMBER(B85),TEXT(B85,"0000"),B85),Addendum!I:I,"X")>0,10%,0) -> 0 | M85: =IF(AND(I85=0%,J85=0%,K85=0%,L85=0%),0%, IF(OR(TRIM(E85)="OneTime",TRIM(D85)=""),0%, IF( OR( TRIM(D85)="P1M", AND(TRIM(D85)="P1Y",TRIM(E85)="Monthly"), AND(TRIM(D85)="P3Y",TRIM(E85)="Monthly") ), IF(AND(I85=4%,J85=0%,K85=0%,L85=0%),1%, IF(AND(I85=4%,J85=2.5%,K85=0%,L85=10%),2%, IF(AND(I85=4%,J85=0%,K85=7%,L85=10%),3%,0%))), IF( OR( AND(TRIM(D85)="P1Y",TRIM(E85)="Annual"), AND(TRIM(D85)="P3Y",TRIM(E85)="Annual"), AND(TRIM(D85)="P3Y",TRIM(E85)="Triennial") ), IF(AND(I85=4%,J85=0%,K85=0%,L85=0%),3%, IF(AND(I85=4%,J85=2.5%,K85=0%,L85=10%),10%, IF(AND(I85=4%,J85=0%,K85=7%,L85=10%),14%,0%))), 0% )))) -> 0 | N85: =H85-(H85*M85) -> 0
A86: CFQ7TTC0LHQ3 | B86: 1 | C86: Dataverse File Capacity add-on | D86: P1Y | E86: Monthly | F86: Commercial | G86: 2079 | H86: 1559.28 | I86: =IF(COUNTIFS(Addendum!C:C,A86,Addendum!D:D,IF(ISNUMBER(B86),TEXT(B86,"0000"),B86),Addendum!E:E,"X")>0,4%,0) -> 0 | J86: =IF(COUNTIFS(Addendum!C:C,A86,Addendum!D:D,IF(ISNUMBER(B86),TEXT(B86,"0000"),B86),Addendum!F:F,"X")>0,2.5%,0) -> 0 | K86: =IF(COUNTIFS(Addendum!C:C,A86,Addendum!D:D,IF(ISNUMBER(B86),TEXT(B86,"0000"),B86),Addendum!G:G,"X")>0,7%,0) -> 0 | L86: =IF(COUNTIFS(Addendum!C:C,A86,Addendum!D:D,IF(ISNUMBER(B86),TEXT(B86,"0000"),B86),Addendum!I:I,"X")>0,10%,0) -> 0 | M86: =IF(AND(I86=0%,J86=0%,K86=0%,L86=0%),0%, IF(OR(TRIM(E86)="OneTime",TRIM(D86)=""),0%, IF( OR( TRIM(D86)="P1M", AND(TRIM(D86)="P1Y",TRIM(E86)="Monthly"), AND(TRIM(D86)="P3Y",TRIM(E86)="Monthly") ), IF(AND(I86=4%,J86=0%,K86=0%,L86=0%),1%, IF(AND(I86=4%,J86=2.5%,K86=0%,L86=10%),2%, IF(AND(I86=4%,J86=0%,K86=7%,L86=10%),3%,0%))), IF( OR( AND(TRIM(D86)="P1Y",TRIM(E86)="Annual"), AND(TRIM(D86)="P3Y",TRIM(E86)="Annual"), AND(TRIM(D86)="P3Y",TRIM(E86)="Triennial") ), IF(AND(I86=4%,J86=0%,K86=0%,L86=0%),3%, IF(AND(I86=4%,J86=2.5%,K86=0%,L86=10%),10%, IF(AND(I86=4%,J86=0%,K86=7%,L86=10%),14%,0%))), 0% )))) -> 0 | N86: =H86-(H86*M86) -> 1559.28
A87: CFQ7TTC0LHQ3 | B87: 000G | C87: Dataverse File Capacity add-on (Non-Profit Pricing) | D87: P1Y | E87: Monthly | F87: Charity | G87: 1449 | H87: 1304.16 | I87: =IF(COUNTIFS(Addendum!C:C,A87,Addendum!D:D,IF(ISNUMBER(B87),TEXT(B87,"0000"),B87),Addendum!E:E,"X")>0,4%,0) -> 0 | J87: =IF(COUNTIFS(Addendum!C:C,A87,Addendum!D:D,IF(ISNUMBER(B87),TEXT(B87,"0000"),B87),Addendum!F:F,"X")>0,2.5%,0) -> 0 | K87: =IF(COUNTIFS(Addendum!C:C,A87,Addendum!D:D,IF(ISNUMBER(B87),TEXT(B87,"0000"),B87),Addendum!G:G,"X")>0,7%,0) -> 0 | L87: =IF(COUNTIFS(Addendum!C:C,A87,Addendum!D:D,IF(ISNUMBER(B87),TEXT(B87,"0000"),B87),Addendum!I:I,"X")>0,10%,0) -> 0 | M87: =IF(AND(I87=0%,J87=0%,K87=0%,L87=0%),0%, IF(OR(TRIM(E87)="OneTime",TRIM(D87)=""),0%, IF( OR( TRIM(D87)="P1M", AND(TRIM(D87)="P1Y",TRIM(E87)="Monthly"), AND(TRIM(D87)="P3Y",TRIM(E87)="Monthly") ), IF(AND(I87=4%,J87=0%,K87=0%,L87=0%),1%, IF(AND(I87=4%,J87=2.5%,K87=0%,L87=10%),2%, IF(AND(I87=4%,J87=0%,K87=7%,L87=10%),3%,0%))), IF( OR( AND(TRIM(D87)="P1Y",TRIM(E87)="Annual"), AND(TRIM(D87)="P3Y",TRIM(E87)="Annual"), AND(TRIM(D87)="P3Y",TRIM(E87)="Triennial") ), IF(AND(I87=4%,J87=0%,K87=0%,L87=0%),3%, IF(AND(I87=4%,J87=2.5%,K87=0%,L87=10%),10%, IF(AND(I87=4%,J87=0%,K87=7%,L87=10%),14%,0%))), 0% )))) -> 0 | N87: =H87-(H87*M87) -> 1304.16
A88: CFQ7TTC0LHQ3 | B88: 1 | C88: Dataverse File Capacity add-on | D88: P1Y | E88: Annual | F88: Commercial | G88: 1980 | H88: 1485 | I88: =IF(COUNTIFS(Addendum!C:C,A88,Addendum!D:D,IF(ISNUMBER(B88),TEXT(B88,"0000"),B88),Addendum!E:E,"X")>0,4%,0) -> 0 | J88: =IF(COUNTIFS(Addendum!C:C,A88,Addendum!D:D,IF(ISNUMBER(B88),TEXT(B88,"0000"),B88),Addendum!F:F,"X")>0,2.5%,0) -> 0 | K88: =IF(COUNTIFS(Addendum!C:C,A88,Addendum!D:D,IF(ISNUMBER(B88),TEXT(B88,"0000"),B88),Addendum!G:G,"X")>0,7%,0) -> 0 | L88: =IF(COUNTIFS(Addendum!C:C,A88,Addendum!D:D,IF(ISNUMBER(B88),TEXT(B88,"0000"),B88),Addendum!I:I,"X")>0,10%,0) -> 0 | M88: =IF(AND(I88=0%,J88=0%,K88=0%,L88=0%),0%, IF(OR(TRIM(E88)="OneTime",TRIM(D88)=""),0%, IF( OR( TRIM(D88)="P1M", AND(TRIM(D88)="P1Y",TRIM(E88)="Monthly"), AND(TRIM(D88)="P3Y",TRIM(E88)="Monthly") ), IF(AND(I88=4%,J88=0%,K88=0%,L88=0%),1%, IF(AND(I88=4%,J88=2.5%,K88=0%,L88=10%),2%, IF(AND(I88=4%,J88=0%,K88=7%,L88=10%),3%,0%))), IF( OR( AND(TRIM(D88)="P1Y",TRIM(E88)="Annual"), AND(TRIM(D88)="P3Y",TRIM(E88)="Annual"), AND(TRIM(D88)="P3Y",TRIM(E88)="Triennial") ), IF(AND(I88=4%,J88=0%,K88=0%,L88=0%),3%, IF(AND(I88=4%,J88=2.5%,K88=0%,L88=10%),10%, IF(AND(I88=4%,J88=0%,K88=7%,L88=10%),14%,0%))), 0% )))) -> 0 | N88: =H88-(H88*M88) -> 1485
A89: CFQ7TTC0LHQ3 | B89: 000G | C89: Dataverse File Capacity add-on (Non-Profit Pricing) | D89: P1Y | E89: Annual | F89: Charity | G89: 1380 | H89: 1242 | I89: =IF(COUNTIFS(Addendum!C:C,A89,Addendum!D:D,IF(ISNUMBER(B89),TEXT(B89,"0000"),B89),Addendum!E:E,"X")>0,4%,0) -> 0 | J89: =IF(COUNTIFS(Addendum!C:C,A89,Addendum!D:D,IF(ISNUMBER(B89),TEXT(B89,"0000"),B89),Addendum!F:F,"X")>0,2.5%,0) -> 0 | K89: =IF(COUNTIFS(Addendum!C:C,A89,Addendum!D:D,IF(ISNUMBER(B89),TEXT(B89,"0000"),B89),Addendum!G:G,"X")>0,7%,0) -> 0 | L89: =IF(COUNTIFS(Addendum!C:C,A89,Addendum!D:D,IF(ISNUMBER(B89),TEXT(B89,"0000"),B89),Addendum!I:I,"X")>0,10%,0) -> 0 | M89: =IF(AND(I89=0%,J89=0%,K89=0%,L89=0%),0%, IF(OR(TRIM(E89)="OneTime",TRIM(D89)=""),0%, IF( OR( TRIM(D89)="P1M", AND(TRIM(D89)="P1Y",TRIM(E89)="Monthly"), AND(TRIM(D89)="P3Y",TRIM(E89)="Monthly") ), IF(AND(I89=4%,J89=0%,K89=0%,L89=0%),1%, IF(AND(I89=4%,J89=2.5%,K89=0%,L89=10%),2%, IF(AND(I89=4%,J89=0%,K89=7%,L89=10%),3%,0%))), IF( OR( AND(TRIM(D89)="P1Y",TRIM(E89)="Annual"), AND(TRIM(D89)="P3Y",TRIM(E89)="Annual"), AND(TRIM(D89)="P3Y",TRIM(E89)="Triennial") ), IF(AND(I89=4%,J89=0%,K89=0%,L89=0%),3%, IF(AND(I89=4%,J89=2.5%,K89=0%,L89=10%),10%, IF(AND(I89=4%,J89=0%,K89=7%,L89=10%),14%,0%))), 0% )))) -> 0 | N89: =H89-(H89*M89) -> 1242
A90: CFQ7TTC0LHQ3 | B90: 000H | C90: Dataverse File Capacity add-on (Education Pricing) | D90: P1Y | E90: Annual | F90: Education | G90: 1380 | H90: 1035 | I90: =IF(COUNTIFS(Addendum!C:C,A90,Addendum!D:D,IF(ISNUMBER(B90),TEXT(B90,"0000"),B90),Addendum!E:E,"X")>0,4%,0) -> 0 | J90: =IF(COUNTIFS(Addendum!C:C,A90,Addendum!D:D,IF(ISNUMBER(B90),TEXT(B90,"0000"),B90),Addendum!F:F,"X")>0,2.5%,0) -> 0 | K90: =IF(COUNTIFS(Addendum!C:C,A90,Addendum!D:D,IF(ISNUMBER(B90),TEXT(B90,"0000"),B90),Addendum!G:G,"X")>0,7%,0) -> 0 | L90: =IF(COUNTIFS(Addendum!C:C,A90,Addendum!D:D,IF(ISNUMBER(B90),TEXT(B90,"0000"),B90),Addendum!I:I,"X")>0,10%,0) -> 0 | M90: =IF(AND(I90=0%,J90=0%,K90=0%,L90=0%),0%, IF(OR(TRIM(E90)="OneTime",TRIM(D90)=""),0%, IF( OR( TRIM(D90)="P1M", AND(TRIM(D90)="P1Y",TRIM(E90)="Monthly"), AND(TRIM(D90)="P3Y",TRIM(E90)="Monthly") ), IF(AND(I90=4%,J90=0%,K90=0%,L90=0%),1%, IF(AND(I90=4%,J90=2.5%,K90=0%,L90=10%),2%, IF(AND(I90=4%,J90=0%,K90=7%,L90=10%),3%,0%))), IF( OR( AND(TRIM(D90)="P1Y",TRIM(E90)="Annual"), AND(TRIM(D90)="P3Y",TRIM(E90)="Annual"), AND(TRIM(D90)="P3Y",TRIM(E90)="Triennial") ), IF(AND(I90=4%,J90=0%,K90=0%,L90=0%),3%, IF(AND(I90=4%,J90=2.5%,K90=0%,L90=10%),10%, IF(AND(I90=4%,J90=0%,K90=7%,L90=10%),14%,0%))), 0% )))) -> 0 | N90: =H90-(H90*M90) -> 1035
A91: CFQ7TTC0LHQ3 | B91: 000H | C91: Dataverse File Capacity add-on (Education Pricing) | D91: P1Y | E91: Monthly | F91: Education | G91: 1449 | H91: 1086.72 | I91: =IF(COUNTIFS(Addendum!C:C,A91,Addendum!D:D,IF(ISNUMBER(B91),TEXT(B91,"0000"),B91),Addendum!E:E,"X")>0,4%,0) -> 0 | J91: =IF(COUNTIFS(Addendum!C:C,A91,Addendum!D:D,IF(ISNUMBER(B91),TEXT(B91,"0000"),B91),Addendum!F:F,"X")>0,2.5%,0) -> 0 | K91: =IF(COUNTIFS(Addendum!C:C,A91,Addendum!D:D,IF(ISNUMBER(B91),TEXT(B91,"0000"),B91),Addendum!G:G,"X")>0,7%,0) -> 0 | L91: =IF(COUNTIFS(Addendum!C:C,A91,Addendum!D:D,IF(ISNUMBER(B91),TEXT(B91,"0000"),B91),Addendum!I:I,"X")>0,10%,0) -> 0 | M91: =IF(AND(I91=0%,J91=0%,K91=0%,L91=0%),0%, IF(OR(TRIM(E91)="OneTime",TRIM(D91)=""),0%, IF( OR( TRIM(D91)="P1M", AND(TRIM(D91)="P1Y",TRIM(E91)="Monthly"), AND(TRIM(D91)="P3Y",TRIM(E91)="Monthly") ), IF(AND(I91=4%,J91=0%,K91=0%,L91=0%),1%, IF(AND(I91=4%,J91=2.5%,K91=0%,L91=10%),2%, IF(AND(I91=4%,J91=0%,K91=7%,L91=10%),3%,0%))), IF( OR( AND(TRIM(D91)="P1Y",TRIM(E91)="Annual"), AND(TRIM(D91)="P3Y",TRIM(E91)="Annual"), AND(TRIM(D91)="P3Y",TRIM(E91)="Triennial") ), IF(AND(I91=4%,J91=0%,K91=0%,L91=0%),3%, IF(AND(I91=4%,J91=2.5%,K91=0%,L91=10%),10%, IF(AND(I91=4%,J91=0%,K91=7%,L91=10%),14%,0%))), 0% )))) -> 0 | N91: =H91-(H91*M91) -> 1086.72
A92: CFQ7TTC0LHQ3 | B92: 1 | C92: Dataverse File Capacity add-on | D92: P1M | E92: Monthly | F92: Commercial | G92: 198 | H92: 148.5 | I92: =IF(COUNTIFS(Addendum!C:C,A92,Addendum!D:D,IF(ISNUMBER(B92),TEXT(B92,"0000"),B92),Addendum!E:E,"X")>0,4%,0) -> 0 | J92: =IF(COUNTIFS(Addendum!C:C,A92,Addendum!D:D,IF(ISNUMBER(B92),TEXT(B92,"0000"),B92),Addendum!F:F,"X")>0,2.5%,0) -> 0 | K92: =IF(COUNTIFS(Addendum!C:C,A92,Addendum!D:D,IF(ISNUMBER(B92),TEXT(B92,"0000"),B92),Addendum!G:G,"X")>0,7%,0) -> 0 | L92: =IF(COUNTIFS(Addendum!C:C,A92,Addendum!D:D,IF(ISNUMBER(B92),TEXT(B92,"0000"),B92),Addendum!I:I,"X")>0,10%,0) -> 0 | M92: =IF(AND(I92=0%,J92=0%,K92=0%,L92=0%),0%, IF(OR(TRIM(E92)="OneTime",TRIM(D92)=""),0%, IF( OR( TRIM(D92)="P1M", AND(TRIM(D92)="P1Y",TRIM(E92)="Monthly"), AND(TRIM(D92)="P3Y",TRIM(E92)="Monthly") ), IF(AND(I92=4%,J92=0%,K92=0%,L92=0%),1%, IF(AND(I92=4%,J92=2.5%,K92=0%,L92=10%),2%, IF(AND(I92=4%,J92=0%,K92=7%,L92=10%),3%,0%))), IF( OR( AND(TRIM(D92)="P1Y",TRIM(E92)="Annual"), AND(TRIM(D92)="P3Y",TRIM(E92)="Annual"), AND(TRIM(D92)="P3Y",TRIM(E92)="Triennial") ), IF(AND(I92=4%,J92=0%,K92=0%,L92=0%),3%, IF(AND(I92=4%,J92=2.5%,K92=0%,L92=10%),10%, IF(AND(I92=4%,J92=0%,K92=7%,L92=10%),14%,0%))), 0% )))) -> 0 | N92: =H92-(H92*M92) -> 148.5
A93: CFQ7TTC0LHQ3 | B93: 000G | C93: Dataverse File Capacity add-on (Non-Profit Pricing) | D93: P1M | E93: Monthly | F93: Charity | G93: 138 | H93: 124.2 | I93: =IF(COUNTIFS(Addendum!C:C,A93,Addendum!D:D,IF(ISNUMBER(B93),TEXT(B93,"0000"),B93),Addendum!E:E,"X")>0,4%,0) -> 0 | J93: =IF(COUNTIFS(Addendum!C:C,A93,Addendum!D:D,IF(ISNUMBER(B93),TEXT(B93,"0000"),B93),Addendum!F:F,"X")>0,2.5%,0) -> 0 | K93: =IF(COUNTIFS(Addendum!C:C,A93,Addendum!D:D,IF(ISNUMBER(B93),TEXT(B93,"0000"),B93),Addendum!G:G,"X")>0,7%,0) -> 0 | L93: =IF(COUNTIFS(Addendum!C:C,A93,Addendum!D:D,IF(ISNUMBER(B93),TEXT(B93,"0000"),B93),Addendum!I:I,"X")>0,10%,0) -> 0 | M93: =IF(AND(I93=0%,J93=0%,K93=0%,L93=0%),0%, IF(OR(TRIM(E93)="OneTime",TRIM(D93)=""),0%, IF( OR( TRIM(D93)="P1M", AND(TRIM(D93)="P1Y",TRIM(E93)="Monthly"), AND(TRIM(D93)="P3Y",TRIM(E93)="Monthly") ), IF(AND(I93=4%,J93=0%,K93=0%,L93=0%),1%, IF(AND(I93=4%,J93=2.5%,K93=0%,L93=10%),2%, IF(AND(I93=4%,J93=0%,K93=7%,L93=10%),3%,0%))), IF( OR( AND(TRIM(D93)="P1Y",TRIM(E93)="Annual"), AND(TRIM(D93)="P3Y",TRIM(E93)="Annual"), AND(TRIM(D93)="P3Y",TRIM(E93)="Triennial") ), IF(AND(I93=4%,J93=0%,K93=0%,L93=0%),3%, IF(AND(I93=4%,J93=2.5%,K93=0%,L93=10%),10%, IF(AND(I93=4%,J93=0%,K93=7%,L93=10%),14%,0%))), 0% )))) -> 0 | N93: =H93-(H93*M93) -> 124.2
A94: CFQ7TTC0LHQ3 | B94: 000H | C94: Dataverse File Capacity add-on (Education Pricing) | D94: P1M | E94: Monthly | F94: Education | G94: 138 | H94: 103.5 | I94: =IF(COUNTIFS(Addendum!C:C,A94,Addendum!D:D,IF(ISNUMBER(B94),TEXT(B94,"0000"),B94),Addendum!E:E,"X")>0,4%,0) -> 0 | J94: =IF(COUNTIFS(Addendum!C:C,A94,Addendum!D:D,IF(ISNUMBER(B94),TEXT(B94,"0000"),B94),Addendum!F:F,"X")>0,2.5%,0) -> 0 | K94: =IF(COUNTIFS(Addendum!C:C,A94,Addendum!D:D,IF(ISNUMBER(B94),TEXT(B94,"0000"),B94),Addendum!G:G,"X")>0,7%,0) -> 0 | L94: =IF(COUNTIFS(Addendum!C:C,A94,Addendum!D:D,IF(ISNUMBER(B94),TEXT(B94,"0000"),B94),Addendum!I:I,"X")>0,10%,0) -> 0 | M94: =IF(AND(I94=0%,J94=0%,K94=0%,L94=0%),0%, IF(OR(TRIM(E94)="OneTime",TRIM(D94)=""),0%, IF( OR( TRIM(D94)="P1M", AND(TRIM(D94)="P1Y",TRIM(E94)="Monthly"), AND(TRIM(D94)="P3Y",TRIM(E94)="Monthly") ), IF(AND(I94=4%,J94=0%,K94=0%,L94=0%),1%, IF(AND(I94=4%,J94=2.5%,K94=0%,L94=10%),2%, IF(AND(I94=4%,J94=0%,K94=7%,L94=10%),3%,0%))), IF( OR( AND(TRIM(D94)="P1Y",TRIM(E94)="Annual"), AND(TRIM(D94)="P3Y",TRIM(E94)="Annual"), AND(TRIM(D94)="P3Y",TRIM(E94)="Triennial") ), IF(AND(I94=4%,J94=0%,K94=0%,L94=0%),3%, IF(AND(I94=4%,J94=2.5%,K94=0%,L94=10%),10%, IF(AND(I94=4%,J94=0%,K94=7%,L94=10%),14%,0%))), 0% )))) -> 0 | N94: =H94-(H94*M94) -> 103.5
A95: CFQ7TTC0HBSL | B95: 000G | C95: Dataverse Log Capacity add-on (Non-Profit Pricing) | D95: P1Y | E95: Monthly | F95: Charity | G95: 7308 | H95: 6577.2 | I95: =IF(COUNTIFS(Addendum!C:C,A95,Addendum!D:D,IF(ISNUMBER(B95),TEXT(B95,"0000"),B95),Addendum!E:E,"X")>0,4%,0) -> 0 | J95: =IF(COUNTIFS(Addendum!C:C,A95,Addendum!D:D,IF(ISNUMBER(B95),TEXT(B95,"0000"),B95),Addendum!F:F,"X")>0,2.5%,0) -> 0 | K95: =IF(COUNTIFS(Addendum!C:C,A95,Addendum!D:D,IF(ISNUMBER(B95),TEXT(B95,"0000"),B95),Addendum!G:G,"X")>0,7%,0) -> 0 | L95: =IF(COUNTIFS(Addendum!C:C,A95,Addendum!D:D,IF(ISNUMBER(B95),TEXT(B95,"0000"),B95),Addendum!I:I,"X")>0,10%,0) -> 0 | M95: =IF(AND(I95=0%,J95=0%,K95=0%,L95=0%),0%, IF(OR(TRIM(E95)="OneTime",TRIM(D95)=""),0%, IF( OR( TRIM(D95)="P1M", AND(TRIM(D95)="P1Y",TRIM(E95)="Monthly"), AND(TRIM(D95)="P3Y",TRIM(E95)="Monthly") ), IF(AND(I95=4%,J95=0%,K95=0%,L95=0%),1%, IF(AND(I95=4%,J95=2.5%,K95=0%,L95=10%),2%, IF(AND(I95=4%,J95=0%,K95=7%,L95=10%),3%,0%))), IF( OR( AND(TRIM(D95)="P1Y",TRIM(E95)="Annual"), AND(TRIM(D95)="P3Y",TRIM(E95)="Annual"), AND(TRIM(D95)="P3Y",TRIM(E95)="Triennial") ), IF(AND(I95=4%,J95=0%,K95=0%,L95=0%),3%, IF(AND(I95=4%,J95=2.5%,K95=0%,L95=10%),10%, IF(AND(I95=4%,J95=0%,K95=7%,L95=10%),14%,0%))), 0% )))) -> 0 | N95: =H95-(H95*M95) -> 6577.2
A96: CFQ7TTC0HBSL | B96: 1 | C96: Dataverse Log Capacity add-on | D96: P1M | E96: Monthly | F96: Commercial | G96: 996 | H96: 747 | I96: =IF(COUNTIFS(Addendum!C:C,A96,Addendum!D:D,IF(ISNUMBER(B96),TEXT(B96,"0000"),B96),Addendum!E:E,"X")>0,4%,0) -> 0 | J96: =IF(COUNTIFS(Addendum!C:C,A96,Addendum!D:D,IF(ISNUMBER(B96),TEXT(B96,"0000"),B96),Addendum!F:F,"X")>0,2.5%,0) -> 0 | K96: =IF(COUNTIFS(Addendum!C:C,A96,Addendum!D:D,IF(ISNUMBER(B96),TEXT(B96,"0000"),B96),Addendum!G:G,"X")>0,7%,0) -> 0 | L96: =IF(COUNTIFS(Addendum!C:C,A96,Addendum!D:D,IF(ISNUMBER(B96),TEXT(B96,"0000"),B96),Addendum!I:I,"X")>0,10%,0) -> 0 | M96: =IF(AND(I96=0%,J96=0%,K96=0%,L96=0%),0%, IF(OR(TRIM(E96)="OneTime",TRIM(D96)=""),0%, IF( OR( TRIM(D96)="P1M", AND(TRIM(D96)="P1Y",TRIM(E96)="Monthly"), AND(TRIM(D96)="P3Y",TRIM(E96)="Monthly") ), IF(AND(I96=4%,J96=0%,K96=0%,L96=0%),1%, IF(AND(I96=4%,J96=2.5%,K96=0%,L96=10%),2%, IF(AND(I96=4%,J96=0%,K96=7%,L96=10%),3%,0%))), IF( OR( AND(TRIM(D96)="P1Y",TRIM(E96)="Annual"), AND(TRIM(D96)="P3Y",TRIM(E96)="Annual"), AND(TRIM(D96)="P3Y",TRIM(E96)="Triennial") ), IF(AND(I96=4%,J96=0%,K96=0%,L96=0%),3%, IF(AND(I96=4%,J96=2.5%,K96=0%,L96=10%),10%, IF(AND(I96=4%,J96=0%,K96=7%,L96=10%),14%,0%))), 0% )))) -> 0 | N96: =H96-(H96*M96) -> 747
A97: CFQ7TTC0HBSL | B97: 1 | C97: Dataverse Log Capacity add-on | D97: P1Y | E97: Monthly | F97: Commercial | G97: 10458 | H97: 7843.56 | I97: =IF(COUNTIFS(Addendum!C:C,A97,Addendum!D:D,IF(ISNUMBER(B97),TEXT(B97,"0000"),B97),Addendum!E:E,"X")>0,4%,0) -> 0 | J97: =IF(COUNTIFS(Addendum!C:C,A97,Addendum!D:D,IF(ISNUMBER(B97),TEXT(B97,"0000"),B97),Addendum!F:F,"X")>0,2.5%,0) -> 0 | K97: =IF(COUNTIFS(Addendum!C:C,A97,Addendum!D:D,IF(ISNUMBER(B97),TEXT(B97,"0000"),B97),Addendum!G:G,"X")>0,7%,0) -> 0 | L97: =IF(COUNTIFS(Addendum!C:C,A97,Addendum!D:D,IF(ISNUMBER(B97),TEXT(B97,"0000"),B97),Addendum!I:I,"X")>0,10%,0) -> 0 | M97: =IF(AND(I97=0%,J97=0%,K97=0%,L97=0%),0%, IF(OR(TRIM(E97)="OneTime",TRIM(D97)=""),0%, IF( OR( TRIM(D97)="P1M", AND(TRIM(D97)="P1Y",TRIM(E97)="Monthly"), AND(TRIM(D97)="P3Y",TRIM(E97)="Monthly") ), IF(AND(I97=4%,J97=0%,K97=0%,L97=0%),1%, IF(AND(I97=4%,J97=2.5%,K97=0%,L97=10%),2%, IF(AND(I97=4%,J97=0%,K97=7%,L97=10%),3%,0%))), IF( OR( AND(TRIM(D97)="P1Y",TRIM(E97)="Annual"), AND(TRIM(D97)="P3Y",TRIM(E97)="Annual"), AND(TRIM(D97)="P3Y",TRIM(E97)="Triennial") ), IF(AND(I97=4%,J97=0%,K97=0%,L97=0%),3%, IF(AND(I97=4%,J97=2.5%,K97=0%,L97=10%),10%, IF(AND(I97=4%,J97=0%,K97=7%,L97=10%),14%,0%))), 0% )))) -> 0 | N97: =H97-(H97*M97) -> 7843.56
A98: CFQ7TTC0HBSL | B98: 1 | C98: Dataverse Log Capacity add-on | D98: P1Y | E98: Annual | F98: Commercial | G98: 9960 | H98: 7470 | I98: =IF(COUNTIFS(Addendum!C:C,A98,Addendum!D:D,IF(ISNUMBER(B98),TEXT(B98,"0000"),B98),Addendum!E:E,"X")>0,4%,0) -> 0 | J98: =IF(COUNTIFS(Addendum!C:C,A98,Addendum!D:D,IF(ISNUMBER(B98),TEXT(B98,"0000"),B98),Addendum!F:F,"X")>0,2.5%,0) -> 0 | K98: =IF(COUNTIFS(Addendum!C:C,A98,Addendum!D:D,IF(ISNUMBER(B98),TEXT(B98,"0000"),B98),Addendum!G:G,"X")>0,7%,0) -> 0 | L98: =IF(COUNTIFS(Addendum!C:C,A98,Addendum!D:D,IF(ISNUMBER(B98),TEXT(B98,"0000"),B98),Addendum!I:I,"X")>0,10%,0) -> 0 | M98: =IF(AND(I98=0%,J98=0%,K98=0%,L98=0%),0%, IF(OR(TRIM(E98)="OneTime",TRIM(D98)=""),0%, IF( OR( TRIM(D98)="P1M", AND(TRIM(D98)="P1Y",TRIM(E98)="Monthly"), AND(TRIM(D98)="P3Y",TRIM(E98)="Monthly") ), IF(AND(I98=4%,J98=0%,K98=0%,L98=0%),1%, IF(AND(I98=4%,J98=2.5%,K98=0%,L98=10%),2%, IF(AND(I98=4%,J98=0%,K98=7%,L98=10%),3%,0%))), IF( OR( AND(TRIM(D98)="P1Y",TRIM(E98)="Annual"), AND(TRIM(D98)="P3Y",TRIM(E98)="Annual"), AND(TRIM(D98)="P3Y",TRIM(E98)="Triennial") ), IF(AND(I98=4%,J98=0%,K98=0%,L98=0%),3%, IF(AND(I98=4%,J98=2.5%,K98=0%,L98=10%),10%, IF(AND(I98=4%,J98=0%,K98=7%,L98=10%),14%,0%))), 0% )))) -> 0 | N98: =H98-(H98*M98) -> 7470
A99: CFQ7TTC0HBSL | B99: 000G | C99: Dataverse Log Capacity add-on (Non-Profit Pricing) | D99: P1Y | E99: Annual | F99: Charity | G99: 6960 | H99: 6264 | I99: =IF(COUNTIFS(Addendum!C:C,A99,Addendum!D:D,IF(ISNUMBER(B99),TEXT(B99,"0000"),B99),Addendum!E:E,"X")>0,4%,0) -> 0 | J99: =IF(COUNTIFS(Addendum!C:C,A99,Addendum!D:D,IF(ISNUMBER(B99),TEXT(B99,"0000"),B99),Addendum!F:F,"X")>0,2.5%,0) -> 0 | K99: =IF(COUNTIFS(Addendum!C:C,A99,Addendum!D:D,IF(ISNUMBER(B99),TEXT(B99,"0000"),B99),Addendum!G:G,"X")>0,7%,0) -> 0 | L99: =IF(COUNTIFS(Addendum!C:C,A99,Addendum!D:D,IF(ISNUMBER(B99),TEXT(B99,"0000"),B99),Addendum!I:I,"X")>0,10%,0) -> 0 | M99: =IF(AND(I99=0%,J99=0%,K99=0%,L99=0%),0%, IF(OR(TRIM(E99)="OneTime",TRIM(D99)=""),0%, IF( OR( TRIM(D99)="P1M", AND(TRIM(D99)="P1Y",TRIM(E99)="Monthly"), AND(TRIM(D99)="P3Y",TRIM(E99)="Monthly") ), IF(AND(I99=4%,J99=0%,K99=0%,L99=0%),1%, IF(AND(I99=4%,J99=2.5%,K99=0%,L99=10%),2%, IF(AND(I99=4%,J99=0%,K99=7%,L99=10%),3%,0%))), IF( OR( AND(TRIM(D99)="P1Y",TRIM(E99)="Annual"), AND(TRIM(D99)="P3Y",TRIM(E99)="Annual"), AND(TRIM(D99)="P3Y",TRIM(E99)="Triennial") ), IF(AND(I99=4%,J99=0%,K99=0%,L99=0%),3%, IF(AND(I99=4%,J99=2.5%,K99=0%,L99=10%),10%, IF(AND(I99=4%,J99=0%,K99=7%,L99=10%),14%,0%))), 0% )))) -> 0 | N99: =H99-(H99*M99) -> 6264
A100: CFQ7TTC0HBSL | B100: 000H | C100: Dataverse Log Capacity add-on (Education Pricing) | D100: P1Y | E100: Monthly | F100: Education | G100: 7308 | H100: 5481 | I100: =IF(COUNTIFS(Addendum!C:C,A100,Addendum!D:D,IF(ISNUMBER(B100),TEXT(B100,"0000"),B100),Addendum!E:E,"X")>0,4%,0) -> 0 | J100: =IF(COUNTIFS(Addendum!C:C,A100,Addendum!D:D,IF(ISNUMBER(B100),TEXT(B100,"0000"),B100),Addendum!F:F,"X")>0,2.5%,0) -> 0 | K100: =IF(COUNTIFS(Addendum!C:C,A100,Addendum!D:D,IF(ISNUMBER(B100),TEXT(B100,"0000"),B100),Addendum!G:G,"X")>0,7%,0) -> 0 | L100: =IF(COUNTIFS(Addendum!C:C,A100,Addendum!D:D,IF(ISNUMBER(B100),TEXT(B100,"0000"),B100),Addendum!I:I,"X")>0,10%,0) -> 0 | M100: =IF(AND(I100=0%,J100=0%,K100=0%,L100=0%),0%, IF(OR(TRIM(E100)="OneTime",TRIM(D100)=""),0%, IF( OR( TRIM(D100)="P1M", AND(TRIM(D100)="P1Y",TRIM(E100)="Monthly"), AND(TRIM(D100)="P3Y",TRIM(E100)="Monthly") ), IF(AND(I100=4%,J100=0%,K100=0%,L100=0%),1%, IF(AND(I100=4%,J100=2.5%,K100=0%,L100=10%),2%, IF(AND(I100=4%,J100=0%,K100=7%,L100=10%),3%,0%))), IF( OR( AND(TRIM(D100)="P1Y",TRIM(E100)="Annual"), AND(TRIM(D100)="P3Y",TRIM(E100)="Annual"), AND(TRIM(D100)="P3Y",TRIM(E100)="Triennial") ), IF(AND(I100=4%,J100=0%,K100=0%,L100=0%),3%, IF(AND(I100=4%,J100=2.5%,K100=0%,L100=10%),10%, IF(AND(I100=4%,J100=0%,K100=7%,L100=10%),14%,0%))), 0% )))) -> 0 | N100: =H100-(H100*M100) -> 5481
A101: CFQ7TTC0HBSL | B101: 000H | C101: Dataverse Log Capacity add-on (Education Pricing) | D101: P1Y | E101: Annual | F101: Education | G101: 6960 | H101: 5220 | I101: =IF(COUNTIFS(Addendum!C:C,A101,Addendum!D:D,IF(ISNUMBER(B101),TEXT(B101,"0000"),B101),Addendum!E:E,"X")>0,4%,0) -> 0 | J101: =IF(COUNTIFS(Addendum!C:C,A101,Addendum!D:D,IF(ISNUMBER(B101),TEXT(B101,"0000"),B101),Addendum!F:F,"X")>0,2.5%,0) -> 0 | K101: =IF(COUNTIFS(Addendum!C:C,A101,Addendum!D:D,IF(ISNUMBER(B101),TEXT(B101,"0000"),B101),Addendum!G:G,"X")>0,7%,0) -> 0 | L101: =IF(COUNTIFS(Addendum!C:C,A101,Addendum!D:D,IF(ISNUMBER(B101),TEXT(B101,"0000"),B101),Addendum!I:I,"X")>0,10%,0) -> 0 | M101: =IF(AND(I101=0%,J101=0%,K101=0%,L101=0%),0%, IF(OR(TRIM(E101)="OneTime",TRIM(D101)=""),0%, IF( OR( TRIM(D101)="P1M", AND(TRIM(D101)="P1Y",TRIM(E101)="Monthly"), AND(TRIM(D101)="P3Y",TRIM(E101)="Monthly") ), IF(AND(I101=4%,J101=0%,K101=0%,L101=0%),1%, IF(AND(I101=4%,J101=2.5%,K101=0%,L101=10%),2%, IF(AND(I101=4%,J101=0%,K101=7%,L101=10%),3%,0%))), IF( OR( AND(TRIM(D101)="P1Y",TRIM(E101)="Annual"), AND(TRIM(D101)="P3Y",TRIM(E101)="Annual"), AND(TRIM(D101)="P3Y",TRIM(E101)="Triennial") ), IF(AND(I101=4%,J101=0%,K101=0%,L101=0%),3%, IF(AND(I101=4%,J101=2.5%,K101=0%,L101=10%),10%, IF(AND(I101=4%,J101=0%,K101=7%,L101=10%),14%,0%))), 0% )))) -> 0 | N101: =H101-(H101*M101) -> 5220
A102: CFQ7TTC0HBSL | B102: 000G | C102: Dataverse Log Capacity add-on (Non-Profit Pricing) | D102: P1M | E102: Monthly | F102: Charity | G102: 696 | H102: 626.4 | I102: =IF(COUNTIFS(Addendum!C:C,A102,Addendum!D:D,IF(ISNUMBER(B102),TEXT(B102,"0000"),B102),Addendum!E:E,"X")>0,4%,0) -> 0 | J102: =IF(COUNTIFS(Addendum!C:C,A102,Addendum!D:D,IF(ISNUMBER(B102),TEXT(B102,"0000"),B102),Addendum!F:F,"X")>0,2.5%,0) -> 0 | K102: =IF(COUNTIFS(Addendum!C:C,A102,Addendum!D:D,IF(ISNUMBER(B102),TEXT(B102,"0000"),B102),Addendum!G:G,"X")>0,7%,0) -> 0 | L102: =IF(COUNTIFS(Addendum!C:C,A102,Addendum!D:D,IF(ISNUMBER(B102),TEXT(B102,"0000"),B102),Addendum!I:I,"X")>0,10%,0) -> 0 | M102: =IF(AND(I102=0%,J102=0%,K102=0%,L102=0%),0%, IF(OR(TRIM(E102)="OneTime",TRIM(D102)=""),0%, IF( OR( TRIM(D102)="P1M", AND(TRIM(D102)="P1Y",TRIM(E102)="Monthly"), AND(TRIM(D102)="P3Y",TRIM(E102)="Monthly") ), IF(AND(I102=4%,J102=0%,K102=0%,L102=0%),1%, IF(AND(I102=4%,J102=2.5%,K102=0%,L102=10%),2%, IF(AND(I102=4%,J102=0%,K102=7%,L102=10%),3%,0%))), IF( OR( AND(TRIM(D102)="P1Y",TRIM(E102)="Annual"), AND(TRIM(D102)="P3Y",TRIM(E102)="Annual"), AND(TRIM(D102)="P3Y",TRIM(E102)="Triennial") ), IF(AND(I102=4%,J102=0%,K102=0%,L102=0%),3%, IF(AND(I102=4%,J102=2.5%,K102=0%,L102=10%),10%, IF(AND(I102=4%,J102=0%,K102=7%,L102=10%),14%,0%))), 0% )))) -> 0 | N102: =H102-(H102*M102) -> 626.4
A103: CFQ7TTC0HBSL | B103: 000H | C103: Dataverse Log Capacity add-on (Education Pricing) | D103: P1M | E103: Monthly | F103: Education | G103: 696 | H103: 522 | I103: =IF(COUNTIFS(Addendum!C:C,A103,Addendum!D:D,IF(ISNUMBER(B103),TEXT(B103,"0000"),B103),Addendum!E:E,"X")>0,4%,0) -> 0 | J103: =IF(COUNTIFS(Addendum!C:C,A103,Addendum!D:D,IF(ISNUMBER(B103),TEXT(B103,"0000"),B103),Addendum!F:F,"X")>0,2.5%,0) -> 0 | K103: =IF(COUNTIFS(Addendum!C:C,A103,Addendum!D:D,IF(ISNUMBER(B103),TEXT(B103,"0000"),B103),Addendum!G:G,"X")>0,7%,0) -> 0 | L103: =IF(COUNTIFS(Addendum!C:C,A103,Addendum!D:D,IF(ISNUMBER(B103),TEXT(B103,"0000"),B103),Addendum!I:I,"X")>0,10%,0) -> 0 | M103: =IF(AND(I103=0%,J103=0%,K103=0%,L103=0%),0%, IF(OR(TRIM(E103)="OneTime",TRIM(D103)=""),0%, IF( OR( TRIM(D103)="P1M", AND(TRIM(D103)="P1Y",TRIM(E103)="Monthly"), AND(TRIM(D103)="P3Y",TRIM(E103)="Monthly") ), IF(AND(I103=4%,J103=0%,K103=0%,L103=0%),1%, IF(AND(I103=4%,J103=2.5%,K103=0%,L103=10%),2%, IF(AND(I103=4%,J103=0%,K103=7%,L103=10%),3%,0%))), IF( OR( AND(TRIM(D103)="P1Y",TRIM(E103)="Annual"), AND(TRIM(D103)="P3Y",TRIM(E103)="Annual"), AND(TRIM(D103)="P3Y",TRIM(E103)="Triennial") ), IF(AND(I103=4%,J103=0%,K103=0%,L103=0%),3%, IF(AND(I103=4%,J103=2.5%,K103=0%,L103=10%),10%, IF(AND(I103=4%,J103=0%,K103=7%,L103=10%),14%,0%))), 0% )))) -> 0 | N103: =H103-(H103*M103) -> 522
A104: CFQ7TTC0LHXR | B104: 000B | C104: Dynamics 365 Operations-Order Lines (Education Pricing) | D104: P1M | E104: Monthly | F104: Education | G104: 34944 | H104: 24460.8 | I104: =IF(COUNTIFS(Addendum!C:C,A104,Addendum!D:D,IF(ISNUMBER(B104),TEXT(B104,"0000"),B104),Addendum!E:E,"X")>0,4%,0) -> 0 | J104: =IF(COUNTIFS(Addendum!C:C,A104,Addendum!D:D,IF(ISNUMBER(B104),TEXT(B104,"0000"),B104),Addendum!F:F,"X")>0,2.5%,0) -> 0 | K104: =IF(COUNTIFS(Addendum!C:C,A104,Addendum!D:D,IF(ISNUMBER(B104),TEXT(B104,"0000"),B104),Addendum!G:G,"X")>0,7%,0) -> 0 | L104: =IF(COUNTIFS(Addendum!C:C,A104,Addendum!D:D,IF(ISNUMBER(B104),TEXT(B104,"0000"),B104),Addendum!I:I,"X")>0,10%,0) -> 0 | M104: =IF(AND(I104=0%,J104=0%,K104=0%,L104=0%),0%, IF(OR(TRIM(E104)="OneTime",TRIM(D104)=""),0%, IF( OR( TRIM(D104)="P1M", AND(TRIM(D104)="P1Y",TRIM(E104)="Monthly"), AND(TRIM(D104)="P3Y",TRIM(E104)="Monthly") ), IF(AND(I104=4%,J104=0%,K104=0%,L104=0%),1%, IF(AND(I104=4%,J104=2.5%,K104=0%,L104=10%),2%, IF(AND(I104=4%,J104=0%,K104=7%,L104=10%),3%,0%))), IF( OR( AND(TRIM(D104)="P1Y",TRIM(E104)="Annual"), AND(TRIM(D104)="P3Y",TRIM(E104)="Annual"), AND(TRIM(D104)="P3Y",TRIM(E104)="Triennial") ), IF(AND(I104=4%,J104=0%,K104=0%,L104=0%),3%, IF(AND(I104=4%,J104=2.5%,K104=0%,L104=10%),10%, IF(AND(I104=4%,J104=0%,K104=7%,L104=10%),14%,0%))), 0% )))) -> 0 | N104: =H104-(H104*M104) -> 24460.8
A105: CFQ7TTC0LHXR | B105: 1 | C105: Dynamics 365 Operations – Order Lines | D105: P1M | E105: Monthly | F105: Commercial | G105: 49914 | H105: 34939.8 | I105: =IF(COUNTIFS(Addendum!C:C,A105,Addendum!D:D,IF(ISNUMBER(B105),TEXT(B105,"0000"),B105),Addendum!E:E,"X")>0,4%,0) -> 0 | J105: =IF(COUNTIFS(Addendum!C:C,A105,Addendum!D:D,IF(ISNUMBER(B105),TEXT(B105,"0000"),B105),Addendum!F:F,"X")>0,2.5%,0) -> 0 | K105: =IF(COUNTIFS(Addendum!C:C,A105,Addendum!D:D,IF(ISNUMBER(B105),TEXT(B105,"0000"),B105),Addendum!G:G,"X")>0,7%,0) -> 0 | L105: =IF(COUNTIFS(Addendum!C:C,A105,Addendum!D:D,IF(ISNUMBER(B105),TEXT(B105,"0000"),B105),Addendum!I:I,"X")>0,10%,0) -> 0 | M105: =IF(AND(I105=0%,J105=0%,K105=0%,L105=0%),0%, IF(OR(TRIM(E105)="OneTime",TRIM(D105)=""),0%, IF( OR( TRIM(D105)="P1M", AND(TRIM(D105)="P1Y",TRIM(E105)="Monthly"), AND(TRIM(D105)="P3Y",TRIM(E105)="Monthly") ), IF(AND(I105=4%,J105=0%,K105=0%,L105=0%),1%, IF(AND(I105=4%,J105=2.5%,K105=0%,L105=10%),2%, IF(AND(I105=4%,J105=0%,K105=7%,L105=10%),3%,0%))), IF( OR( AND(TRIM(D105)="P1Y",TRIM(E105)="Annual"), AND(TRIM(D105)="P3Y",TRIM(E105)="Annual"), AND(TRIM(D105)="P3Y",TRIM(E105)="Triennial") ), IF(AND(I105=4%,J105=0%,K105=0%,L105=0%),3%, IF(AND(I105=4%,J105=2.5%,K105=0%,L105=10%),10%, IF(AND(I105=4%,J105=0%,K105=7%,L105=10%),14%,0%))), 0% )))) -> 0 | N105: =H105-(H105*M105) -> 34939.8
A106: CFQ7TTC0LHXR | B106: 1 | C106: Dynamics 365 Operations – Order Lines | D106: P1Y | E106: Annual | F106: Commercial | G106: 499140 | H106: 349398 | I106: =IF(COUNTIFS(Addendum!C:C,A106,Addendum!D:D,IF(ISNUMBER(B106),TEXT(B106,"0000"),B106),Addendum!E:E,"X")>0,4%,0) -> 0 | J106: =IF(COUNTIFS(Addendum!C:C,A106,Addendum!D:D,IF(ISNUMBER(B106),TEXT(B106,"0000"),B106),Addendum!F:F,"X")>0,2.5%,0) -> 0 | K106: =IF(COUNTIFS(Addendum!C:C,A106,Addendum!D:D,IF(ISNUMBER(B106),TEXT(B106,"0000"),B106),Addendum!G:G,"X")>0,7%,0) -> 0 | L106: =IF(COUNTIFS(Addendum!C:C,A106,Addendum!D:D,IF(ISNUMBER(B106),TEXT(B106,"0000"),B106),Addendum!I:I,"X")>0,10%,0) -> 0 | M106: =IF(AND(I106=0%,J106=0%,K106=0%,L106=0%),0%, IF(OR(TRIM(E106)="OneTime",TRIM(D106)=""),0%, IF( OR( TRIM(D106)="P1M", AND(TRIM(D106)="P1Y",TRIM(E106)="Monthly"), AND(TRIM(D106)="P3Y",TRIM(E106)="Monthly") ), IF(AND(I106=4%,J106=0%,K106=0%,L106=0%),1%, IF(AND(I106=4%,J106=2.5%,K106=0%,L106=10%),2%, IF(AND(I106=4%,J106=0%,K106=7%,L106=10%),3%,0%))), IF( OR( AND(TRIM(D106)="P1Y",TRIM(E106)="Annual"), AND(TRIM(D106)="P3Y",TRIM(E106)="Annual"), AND(TRIM(D106)="P3Y",TRIM(E106)="Triennial") ), IF(AND(I106=4%,J106=0%,K106=0%,L106=0%),3%, IF(AND(I106=4%,J106=2.5%,K106=0%,L106=10%),10%, IF(AND(I106=4%,J106=0%,K106=7%,L106=10%),14%,0%))), 0% )))) -> 0 | N106: =H106-(H106*M106) -> 349398
A107: CFQ7TTC0LHXR | B107: 1 | C107: Dynamics 365 Operations – Order Lines | D107: P1Y | E107: Monthly | F107: Commercial | G107: 524097 | H107: 366868 | I107: =IF(COUNTIFS(Addendum!C:C,A107,Addendum!D:D,IF(ISNUMBER(B107),TEXT(B107,"0000"),B107),Addendum!E:E,"X")>0,4%,0) -> 0 | J107: =IF(COUNTIFS(Addendum!C:C,A107,Addendum!D:D,IF(ISNUMBER(B107),TEXT(B107,"0000"),B107),Addendum!F:F,"X")>0,2.5%,0) -> 0 | K107: =IF(COUNTIFS(Addendum!C:C,A107,Addendum!D:D,IF(ISNUMBER(B107),TEXT(B107,"0000"),B107),Addendum!G:G,"X")>0,7%,0) -> 0 | L107: =IF(COUNTIFS(Addendum!C:C,A107,Addendum!D:D,IF(ISNUMBER(B107),TEXT(B107,"0000"),B107),Addendum!I:I,"X")>0,10%,0) -> 0 | M107: =IF(AND(I107=0%,J107=0%,K107=0%,L107=0%),0%, IF(OR(TRIM(E107)="OneTime",TRIM(D107)=""),0%, IF( OR( TRIM(D107)="P1M", AND(TRIM(D107)="P1Y",TRIM(E107)="Monthly"), AND(TRIM(D107)="P3Y",TRIM(E107)="Monthly") ), IF(AND(I107=4%,J107=0%,K107=0%,L107=0%),1%, IF(AND(I107=4%,J107=2.5%,K107=0%,L107=10%),2%, IF(AND(I107=4%,J107=0%,K107=7%,L107=10%),3%,0%))), IF( OR( AND(TRIM(D107)="P1Y",TRIM(E107)="Annual"), AND(TRIM(D107)="P3Y",TRIM(E107)="Annual"), AND(TRIM(D107)="P3Y",TRIM(E107)="Triennial") ), IF(AND(I107=4%,J107=0%,K107=0%,L107=0%),3%, IF(AND(I107=4%,J107=2.5%,K107=0%,L107=10%),10%, IF(AND(I107=4%,J107=0%,K107=7%,L107=10%),14%,0%))), 0% )))) -> 0 | N107: =H107-(H107*M107) -> 366868
A108: CFQ7TTC0LHXR | B108: 000G | C108: Dynamics 365 Operations – Order Lines (Non-Profit Pricing) | D108: P1Y | E108: Monthly | F108: Charity | G108: 131040 | H108: 117936 | I108: =IF(COUNTIFS(Addendum!C:C,A108,Addendum!D:D,IF(ISNUMBER(B108),TEXT(B108,"0000"),B108),Addendum!E:E,"X")>0,4%,0) -> 0 | J108: =IF(COUNTIFS(Addendum!C:C,A108,Addendum!D:D,IF(ISNUMBER(B108),TEXT(B108,"0000"),B108),Addendum!F:F,"X")>0,2.5%,0) -> 0 | K108: =IF(COUNTIFS(Addendum!C:C,A108,Addendum!D:D,IF(ISNUMBER(B108),TEXT(B108,"0000"),B108),Addendum!G:G,"X")>0,7%,0) -> 0 | L108: =IF(COUNTIFS(Addendum!C:C,A108,Addendum!D:D,IF(ISNUMBER(B108),TEXT(B108,"0000"),B108),Addendum!I:I,"X")>0,10%,0) -> 0 | M108: =IF(AND(I108=0%,J108=0%,K108=0%,L108=0%),0%, IF(OR(TRIM(E108)="OneTime",TRIM(D108)=""),0%, IF( OR( TRIM(D108)="P1M", AND(TRIM(D108)="P1Y",TRIM(E108)="Monthly"), AND(TRIM(D108)="P3Y",TRIM(E108)="Monthly") ), IF(AND(I108=4%,J108=0%,K108=0%,L108=0%),1%, IF(AND(I108=4%,J108=2.5%,K108=0%,L108=10%),2%, IF(AND(I108=4%,J108=0%,K108=7%,L108=10%),3%,0%))), IF( OR( AND(TRIM(D108)="P1Y",TRIM(E108)="Annual"), AND(TRIM(D108)="P3Y",TRIM(E108)="Annual"), AND(TRIM(D108)="P3Y",TRIM(E108)="Triennial") ), IF(AND(I108=4%,J108=0%,K108=0%,L108=0%),3%, IF(AND(I108=4%,J108=2.5%,K108=0%,L108=10%),10%, IF(AND(I108=4%,J108=0%,K108=7%,L108=10%),14%,0%))), 0% )))) -> 0 | N108: =H108-(H108*M108) -> 117936
A109: CFQ7TTC0LHXR | B109: 000B | C109: Dynamics 365 Operations-Order Lines (Education Pricing) | D109: P1Y | E109: Monthly | F109: Education | G109: 366912 | H109: 256838.4 | I109: =IF(COUNTIFS(Addendum!C:C,A109,Addendum!D:D,IF(ISNUMBER(B109),TEXT(B109,"0000"),B109),Addendum!E:E,"X")>0,4%,0) -> 0 | J109: =IF(COUNTIFS(Addendum!C:C,A109,Addendum!D:D,IF(ISNUMBER(B109),TEXT(B109,"0000"),B109),Addendum!F:F,"X")>0,2.5%,0) -> 0 | K109: =IF(COUNTIFS(Addendum!C:C,A109,Addendum!D:D,IF(ISNUMBER(B109),TEXT(B109,"0000"),B109),Addendum!G:G,"X")>0,7%,0) -> 0 | L109: =IF(COUNTIFS(Addendum!C:C,A109,Addendum!D:D,IF(ISNUMBER(B109),TEXT(B109,"0000"),B109),Addendum!I:I,"X")>0,10%,0) -> 0 | M109: =IF(AND(I109=0%,J109=0%,K109=0%,L109=0%),0%, IF(OR(TRIM(E109)="OneTime",TRIM(D109)=""),0%, IF( OR( TRIM(D109)="P1M", AND(TRIM(D109)="P1Y",TRIM(E109)="Monthly"), AND(TRIM(D109)="P3Y",TRIM(E109)="Monthly") ), IF(AND(I109=4%,J109=0%,K109=0%,L109=0%),1%, IF(AND(I109=4%,J109=2.5%,K109=0%,L109=10%),2%, IF(AND(I109=4%,J109=0%,K109=7%,L109=10%),3%,0%))), IF( OR( AND(TRIM(D109)="P1Y",TRIM(E109)="Annual"), AND(TRIM(D109)="P3Y",TRIM(E109)="Annual"), AND(TRIM(D109)="P3Y",TRIM(E109)="Triennial") ), IF(AND(I109=4%,J109=0%,K109=0%,L109=0%),3%, IF(AND(I109=4%,J109=2.5%,K109=0%,L109=10%),10%, IF(AND(I109=4%,J109=0%,K109=7%,L109=10%),14%,0%))), 0% )))) -> 0 | N109: =H109-(H109*M109) -> 256838.4
A110: CFQ7TTC0LHXR | B110: 000B | C110: Dynamics 365 Operations-Order Lines (Education Pricing) | D110: P1Y | E110: Annual | F110: Education | G110: 349440 | H110: 244608 | I110: =IF(COUNTIFS(Addendum!C:C,A110,Addendum!D:D,IF(ISNUMBER(B110),TEXT(B110,"0000"),B110),Addendum!E:E,"X")>0,4%,0) -> 0 | J110: =IF(COUNTIFS(Addendum!C:C,A110,Addendum!D:D,IF(ISNUMBER(B110),TEXT(B110,"0000"),B110),Addendum!F:F,"X")>0,2.5%,0) -> 0 | K110: =IF(COUNTIFS(Addendum!C:C,A110,Addendum!D:D,IF(ISNUMBER(B110),TEXT(B110,"0000"),B110),Addendum!G:G,"X")>0,7%,0) -> 0 | L110: =IF(COUNTIFS(Addendum!C:C,A110,Addendum!D:D,IF(ISNUMBER(B110),TEXT(B110,"0000"),B110),Addendum!I:I,"X")>0,10%,0) -> 0 | M110: =IF(AND(I110=0%,J110=0%,K110=0%,L110=0%),0%, IF(OR(TRIM(E110)="OneTime",TRIM(D110)=""),0%, IF( OR( TRIM(D110)="P1M", AND(TRIM(D110)="P1Y",TRIM(E110)="Monthly"), AND(TRIM(D110)="P3Y",TRIM(E110)="Monthly") ), IF(AND(I110=4%,J110=0%,K110=0%,L110=0%),1%, IF(AND(I110=4%,J110=2.5%,K110=0%,L110=10%),2%, IF(AND(I110=4%,J110=0%,K110=7%,L110=10%),3%,0%))), IF( OR( AND(TRIM(D110)="P1Y",TRIM(E110)="Annual"), AND(TRIM(D110)="P3Y",TRIM(E110)="Annual"), AND(TRIM(D110)="P3Y",TRIM(E110)="Triennial") ), IF(AND(I110=4%,J110=0%,K110=0%,L110=0%),3%, IF(AND(I110=4%,J110=2.5%,K110=0%,L110=10%),10%, IF(AND(I110=4%,J110=0%,K110=7%,L110=10%),14%,0%))), 0% )))) -> 0 | N110: =H110-(H110*M110) -> 244608
A111: CFQ7TTC0LHXR | B111: 000G | C111: Dynamics 365 Operations – Order Lines (Non-Profit Pricing) | D111: P1M | E111: Monthly | F111: Charity | G111: 12480 | H111: 11232 | I111: =IF(COUNTIFS(Addendum!C:C,A111,Addendum!D:D,IF(ISNUMBER(B111),TEXT(B111,"0000"),B111),Addendum!E:E,"X")>0,4%,0) -> 0 | J111: =IF(COUNTIFS(Addendum!C:C,A111,Addendum!D:D,IF(ISNUMBER(B111),TEXT(B111,"0000"),B111),Addendum!F:F,"X")>0,2.5%,0) -> 0 | K111: =IF(COUNTIFS(Addendum!C:C,A111,Addendum!D:D,IF(ISNUMBER(B111),TEXT(B111,"0000"),B111),Addendum!G:G,"X")>0,7%,0) -> 0 | L111: =IF(COUNTIFS(Addendum!C:C,A111,Addendum!D:D,IF(ISNUMBER(B111),TEXT(B111,"0000"),B111),Addendum!I:I,"X")>0,10%,0) -> 0 | M111: =IF(AND(I111=0%,J111=0%,K111=0%,L111=0%),0%, IF(OR(TRIM(E111)="OneTime",TRIM(D111)=""),0%, IF( OR( TRIM(D111)="P1M", AND(TRIM(D111)="P1Y",TRIM(E111)="Monthly"), AND(TRIM(D111)="P3Y",TRIM(E111)="Monthly") ), IF(AND(I111=4%,J111=0%,K111=0%,L111=0%),1%, IF(AND(I111=4%,J111=2.5%,K111=0%,L111=10%),2%, IF(AND(I111=4%,J111=0%,K111=7%,L111=10%),3%,0%))), IF( OR( AND(TRIM(D111)="P1Y",TRIM(E111)="Annual"), AND(TRIM(D111)="P3Y",TRIM(E111)="Annual"), AND(TRIM(D111)="P3Y",TRIM(E111)="Triennial") ), IF(AND(I111=4%,J111=0%,K111=0%,L111=0%),3%, IF(AND(I111=4%,J111=2.5%,K111=0%,L111=10%),10%, IF(AND(I111=4%,J111=0%,K111=7%,L111=10%),14%,0%))), 0% )))) -> 0 | N111: =H111-(H111*M111) -> 11232
A112: CFQ7TTC0LHXR | B112: 000G | C112: Dynamics 365 Operations – Order Lines (Non-Profit Pricing) | D112: P1Y | E112: Annual | F112: Charity | G112: 124800 | H112: 112320 | I112: =IF(COUNTIFS(Addendum!C:C,A112,Addendum!D:D,IF(ISNUMBER(B112),TEXT(B112,"0000"),B112),Addendum!E:E,"X")>0,4%,0) -> 0 | J112: =IF(COUNTIFS(Addendum!C:C,A112,Addendum!D:D,IF(ISNUMBER(B112),TEXT(B112,"0000"),B112),Addendum!F:F,"X")>0,2.5%,0) -> 0 | K112: =IF(COUNTIFS(Addendum!C:C,A112,Addendum!D:D,IF(ISNUMBER(B112),TEXT(B112,"0000"),B112),Addendum!G:G,"X")>0,7%,0) -> 0 | L112: =IF(COUNTIFS(Addendum!C:C,A112,Addendum!D:D,IF(ISNUMBER(B112),TEXT(B112,"0000"),B112),Addendum!I:I,"X")>0,10%,0) -> 0 | M112: =IF(AND(I112=0%,J112=0%,K112=0%,L112=0%),0%, IF(OR(TRIM(E112)="OneTime",TRIM(D112)=""),0%, IF( OR( TRIM(D112)="P1M", AND(TRIM(D112)="P1Y",TRIM(E112)="Monthly"), AND(TRIM(D112)="P3Y",TRIM(E112)="Monthly") ), IF(AND(I112=4%,J112=0%,K112=0%,L112=0%),1%, IF(AND(I112=4%,J112=2.5%,K112=0%,L112=10%),2%, IF(AND(I112=4%,J112=0%,K112=7%,L112=10%),3%,0%))), IF( OR( AND(TRIM(D112)="P1Y",TRIM(E112)="Annual"), AND(TRIM(D112)="P3Y",TRIM(E112)="Annual"), AND(TRIM(D112)="P3Y",TRIM(E112)="Triennial") ), IF(AND(I112=4%,J112=0%,K112=0%,L112=0%),3%, IF(AND(I112=4%,J112=2.5%,K112=0%,L112=10%),10%, IF(AND(I112=4%,J112=0%,K112=7%,L112=10%),14%,0%))), 0% )))) -> 0 | N112: =H112-(H112*M112) -> 112320
A113: CFQ7TTC0LHWJ | B113: 1 | C113: Dynamics 365 Asset Management Addl Assets | D113: P1M | E113: Monthly | F113: Commercial | G113: 9984 | H113: 6988.8 | I113: =IF(COUNTIFS(Addendum!C:C,A113,Addendum!D:D,IF(ISNUMBER(B113),TEXT(B113,"0000"),B113),Addendum!E:E,"X")>0,4%,0) -> 0 | J113: =IF(COUNTIFS(Addendum!C:C,A113,Addendum!D:D,IF(ISNUMBER(B113),TEXT(B113,"0000"),B113),Addendum!F:F,"X")>0,2.5%,0) -> 0 | K113: =IF(COUNTIFS(Addendum!C:C,A113,Addendum!D:D,IF(ISNUMBER(B113),TEXT(B113,"0000"),B113),Addendum!G:G,"X")>0,7%,0) -> 0 | L113: =IF(COUNTIFS(Addendum!C:C,A113,Addendum!D:D,IF(ISNUMBER(B113),TEXT(B113,"0000"),B113),Addendum!I:I,"X")>0,10%,0) -> 0 | M113: =IF(AND(I113=0%,J113=0%,K113=0%,L113=0%),0%, IF(OR(TRIM(E113)="OneTime",TRIM(D113)=""),0%, IF( OR( TRIM(D113)="P1M", AND(TRIM(D113)="P1Y",TRIM(E113)="Monthly"), AND(TRIM(D113)="P3Y",TRIM(E113)="Monthly") ), IF(AND(I113=4%,J113=0%,K113=0%,L113=0%),1%, IF(AND(I113=4%,J113=2.5%,K113=0%,L113=10%),2%, IF(AND(I113=4%,J113=0%,K113=7%,L113=10%),3%,0%))), IF( OR( AND(TRIM(D113)="P1Y",TRIM(E113)="Annual"), AND(TRIM(D113)="P3Y",TRIM(E113)="Annual"), AND(TRIM(D113)="P3Y",TRIM(E113)="Triennial") ), IF(AND(I113=4%,J113=0%,K113=0%,L113=0%),3%, IF(AND(I113=4%,J113=2.5%,K113=0%,L113=10%),10%, IF(AND(I113=4%,J113=0%,K113=7%,L113=10%),14%,0%))), 0% )))) -> 0 | N113: =H113-(H113*M113) -> 6988.8
A114: CFQ7TTC0LHWJ | B114: 1 | C114: Dynamics 365 Asset Management Addl Assets | D114: P3Y | E114: Monthly | F114: Commercial | G114: 314496 | H114: 220147.2 | I114: =IF(COUNTIFS(Addendum!C:C,A114,Addendum!D:D,IF(ISNUMBER(B114),TEXT(B114,"0000"),B114),Addendum!E:E,"X")>0,4%,0) -> 0 | J114: =IF(COUNTIFS(Addendum!C:C,A114,Addendum!D:D,IF(ISNUMBER(B114),TEXT(B114,"0000"),B114),Addendum!F:F,"X")>0,2.5%,0) -> 0 | K114: =IF(COUNTIFS(Addendum!C:C,A114,Addendum!D:D,IF(ISNUMBER(B114),TEXT(B114,"0000"),B114),Addendum!G:G,"X")>0,7%,0) -> 0 | L114: =IF(COUNTIFS(Addendum!C:C,A114,Addendum!D:D,IF(ISNUMBER(B114),TEXT(B114,"0000"),B114),Addendum!I:I,"X")>0,10%,0) -> 0 | M114: =IF(AND(I114=0%,J114=0%,K114=0%,L114=0%),0%, IF(OR(TRIM(E114)="OneTime",TRIM(D114)=""),0%, IF( OR( TRIM(D114)="P1M", AND(TRIM(D114)="P1Y",TRIM(E114)="Monthly"), AND(TRIM(D114)="P3Y",TRIM(E114)="Monthly") ), IF(AND(I114=4%,J114=0%,K114=0%,L114=0%),1%, IF(AND(I114=4%,J114=2.5%,K114=0%,L114=10%),2%, IF(AND(I114=4%,J114=0%,K114=7%,L114=10%),3%,0%))), IF( OR( AND(TRIM(D114)="P1Y",TRIM(E114)="Annual"), AND(TRIM(D114)="P3Y",TRIM(E114)="Annual"), AND(TRIM(D114)="P3Y",TRIM(E114)="Triennial") ), IF(AND(I114=4%,J114=0%,K114=0%,L114=0%),3%, IF(AND(I114=4%,J114=2.5%,K114=0%,L114=10%),10%, IF(AND(I114=4%,J114=0%,K114=7%,L114=10%),14%,0%))), 0% )))) -> 0 | N114: =H114-(H114*M114) -> 220147.2
A115: CFQ7TTC0LHWJ | B115: 000C | C115: Dynamics 365 Asset Management Addl Assets (Education Faculty Pricing) | D115: P1Y | E115: Monthly | F115: Education | G115: 73395 | H115: 51376.56 | I115: =IF(COUNTIFS(Addendum!C:C,A115,Addendum!D:D,IF(ISNUMBER(B115),TEXT(B115,"0000"),B115),Addendum!E:E,"X")>0,4%,0) -> 0 | J115: =IF(COUNTIFS(Addendum!C:C,A115,Addendum!D:D,IF(ISNUMBER(B115),TEXT(B115,"0000"),B115),Addendum!F:F,"X")>0,2.5%,0) -> 0 | K115: =IF(COUNTIFS(Addendum!C:C,A115,Addendum!D:D,IF(ISNUMBER(B115),TEXT(B115,"0000"),B115),Addendum!G:G,"X")>0,7%,0) -> 0 | L115: =IF(COUNTIFS(Addendum!C:C,A115,Addendum!D:D,IF(ISNUMBER(B115),TEXT(B115,"0000"),B115),Addendum!I:I,"X")>0,10%,0) -> 0 | M115: =IF(AND(I115=0%,J115=0%,K115=0%,L115=0%),0%, IF(OR(TRIM(E115)="OneTime",TRIM(D115)=""),0%, IF( OR( TRIM(D115)="P1M", AND(TRIM(D115)="P1Y",TRIM(E115)="Monthly"), AND(TRIM(D115)="P3Y",TRIM(E115)="Monthly") ), IF(AND(I115=4%,J115=0%,K115=0%,L115=0%),1%, IF(AND(I115=4%,J115=2.5%,K115=0%,L115=10%),2%, IF(AND(I115=4%,J115=0%,K115=7%,L115=10%),3%,0%))), IF( OR( AND(TRIM(D115)="P1Y",TRIM(E115)="Annual"), AND(TRIM(D115)="P3Y",TRIM(E115)="Annual"), AND(TRIM(D115)="P3Y",TRIM(E115)="Triennial") ), IF(AND(I115=4%,J115=0%,K115=0%,L115=0%),3%, IF(AND(I115=4%,J115=2.5%,K115=0%,L115=10%),10%, IF(AND(I115=4%,J115=0%,K115=7%,L115=10%),14%,0%))), 0% )))) -> 0 | N115: =H115-(H115*M115) -> 51376.56
A116: CFQ7TTC0LHWJ | B116: 1 | C116: Dynamics 365 Asset Management Addl Assets | D116: P1Y | E116: Annual | F116: Commercial | G116: 99840 | H116: 69888 | I116: =IF(COUNTIFS(Addendum!C:C,A116,Addendum!D:D,IF(ISNUMBER(B116),TEXT(B116,"0000"),B116),Addendum!E:E,"X")>0,4%,0) -> 0 | J116: =IF(COUNTIFS(Addendum!C:C,A116,Addendum!D:D,IF(ISNUMBER(B116),TEXT(B116,"0000"),B116),Addendum!F:F,"X")>0,2.5%,0) -> 0 | K116: =IF(COUNTIFS(Addendum!C:C,A116,Addendum!D:D,IF(ISNUMBER(B116),TEXT(B116,"0000"),B116),Addendum!G:G,"X")>0,7%,0) -> 0 | L116: =IF(COUNTIFS(Addendum!C:C,A116,Addendum!D:D,IF(ISNUMBER(B116),TEXT(B116,"0000"),B116),Addendum!I:I,"X")>0,10%,0) -> 0 | M116: =IF(AND(I116=0%,J116=0%,K116=0%,L116=0%),0%, IF(OR(TRIM(E116)="OneTime",TRIM(D116)=""),0%, IF( OR( TRIM(D116)="P1M", AND(TRIM(D116)="P1Y",TRIM(E116)="Monthly"), AND(TRIM(D116)="P3Y",TRIM(E116)="Monthly") ), IF(AND(I116=4%,J116=0%,K116=0%,L116=0%),1%, IF(AND(I116=4%,J116=2.5%,K116=0%,L116=10%),2%, IF(AND(I116=4%,J116=0%,K116=7%,L116=10%),3%,0%))), IF( OR( AND(TRIM(D116)="P1Y",TRIM(E116)="Annual"), AND(TRIM(D116)="P3Y",TRIM(E116)="Annual"), AND(TRIM(D116)="P3Y",TRIM(E116)="Triennial") ), IF(AND(I116=4%,J116=0%,K116=0%,L116=0%),3%, IF(AND(I116=4%,J116=2.5%,K116=0%,L116=10%),10%, IF(AND(I116=4%,J116=0%,K116=7%,L116=10%),14%,0%))), 0% )))) -> 0 | N116: =H116-(H116*M116) -> 69888
A117: CFQ7TTC0LHWJ | B117: 000C | C117: Dynamics 365 Asset Management Addl Assets (Education Faculty Pricing) | D117: P1Y | E117: Annual | F117: Education | G117: 69900 | H117: 48930 | I117: =IF(COUNTIFS(Addendum!C:C,A117,Addendum!D:D,IF(ISNUMBER(B117),TEXT(B117,"0000"),B117),Addendum!E:E,"X")>0,4%,0) -> 0 | J117: =IF(COUNTIFS(Addendum!C:C,A117,Addendum!D:D,IF(ISNUMBER(B117),TEXT(B117,"0000"),B117),Addendum!F:F,"X")>0,2.5%,0) -> 0 | K117: =IF(COUNTIFS(Addendum!C:C,A117,Addendum!D:D,IF(ISNUMBER(B117),TEXT(B117,"0000"),B117),Addendum!G:G,"X")>0,7%,0) -> 0 | L117: =IF(COUNTIFS(Addendum!C:C,A117,Addendum!D:D,IF(ISNUMBER(B117),TEXT(B117,"0000"),B117),Addendum!I:I,"X")>0,10%,0) -> 0 | M117: =IF(AND(I117=0%,J117=0%,K117=0%,L117=0%),0%, IF(OR(TRIM(E117)="OneTime",TRIM(D117)=""),0%, IF( OR( TRIM(D117)="P1M", AND(TRIM(D117)="P1Y",TRIM(E117)="Monthly"), AND(TRIM(D117)="P3Y",TRIM(E117)="Monthly") ), IF(AND(I117=4%,J117=0%,K117=0%,L117=0%),1%, IF(AND(I117=4%,J117=2.5%,K117=0%,L117=10%),2%, IF(AND(I117=4%,J117=0%,K117=7%,L117=10%),3%,0%))), IF( OR( AND(TRIM(D117)="P1Y",TRIM(E117)="Annual"), AND(TRIM(D117)="P3Y",TRIM(E117)="Annual"), AND(TRIM(D117)="P3Y",TRIM(E117)="Triennial") ), IF(AND(I117=4%,J117=0%,K117=0%,L117=0%),3%, IF(AND(I117=4%,J117=2.5%,K117=0%,L117=10%),10%, IF(AND(I117=4%,J117=0%,K117=7%,L117=10%),14%,0%))), 0% )))) -> 0 | N117: =H117-(H117*M117) -> 48930
A118: CFQ7TTC0LHWJ | B118: 000B | C118: Dynamics 365 Asset Management Addl Assets (Non-Profit Pricing) | D118: P1Y | E118: Annual | F118: Charity | G118: 69900 | H118: 62910 | I118: =IF(COUNTIFS(Addendum!C:C,A118,Addendum!D:D,IF(ISNUMBER(B118),TEXT(B118,"0000"),B118),Addendum!E:E,"X")>0,4%,0) -> 0 | J118: =IF(COUNTIFS(Addendum!C:C,A118,Addendum!D:D,IF(ISNUMBER(B118),TEXT(B118,"0000"),B118),Addendum!F:F,"X")>0,2.5%,0) -> 0 | K118: =IF(COUNTIFS(Addendum!C:C,A118,Addendum!D:D,IF(ISNUMBER(B118),TEXT(B118,"0000"),B118),Addendum!G:G,"X")>0,7%,0) -> 0 | L118: =IF(COUNTIFS(Addendum!C:C,A118,Addendum!D:D,IF(ISNUMBER(B118),TEXT(B118,"0000"),B118),Addendum!I:I,"X")>0,10%,0) -> 0 | M118: =IF(AND(I118=0%,J118=0%,K118=0%,L118=0%),0%, IF(OR(TRIM(E118)="OneTime",TRIM(D118)=""),0%, IF( OR( TRIM(D118)="P1M", AND(TRIM(D118)="P1Y",TRIM(E118)="Monthly"), AND(TRIM(D118)="P3Y",TRIM(E118)="Monthly") ), IF(AND(I118=4%,J118=0%,K118=0%,L118=0%),1%, IF(AND(I118=4%,J118=2.5%,K118=0%,L118=10%),2%, IF(AND(I118=4%,J118=0%,K118=7%,L118=10%),3%,0%))), IF( OR( AND(TRIM(D118)="P1Y",TRIM(E118)="Annual"), AND(TRIM(D118)="P3Y",TRIM(E118)="Annual"), AND(TRIM(D118)="P3Y",TRIM(E118)="Triennial") ), IF(AND(I118=4%,J118=0%,K118=0%,L118=0%),3%, IF(AND(I118=4%,J118=2.5%,K118=0%,L118=10%),10%, IF(AND(I118=4%,J118=0%,K118=7%,L118=10%),14%,0%))), 0% )))) -> 0 | N118: =H118-(H118*M118) -> 62910
A119: CFQ7TTC0LHWJ | B119: 000B | C119: Dynamics 365 Asset Management Addl Assets (Non-Profit Pricing) | D119: P1M | E119: Monthly | F119: Charity | G119: 6990 | H119: 6291 | I119: =IF(COUNTIFS(Addendum!C:C,A119,Addendum!D:D,IF(ISNUMBER(B119),TEXT(B119,"0000"),B119),Addendum!E:E,"X")>0,4%,0) -> 0 | J119: =IF(COUNTIFS(Addendum!C:C,A119,Addendum!D:D,IF(ISNUMBER(B119),TEXT(B119,"0000"),B119),Addendum!F:F,"X")>0,2.5%,0) -> 0 | K119: =IF(COUNTIFS(Addendum!C:C,A119,Addendum!D:D,IF(ISNUMBER(B119),TEXT(B119,"0000"),B119),Addendum!G:G,"X")>0,7%,0) -> 0 | L119: =IF(COUNTIFS(Addendum!C:C,A119,Addendum!D:D,IF(ISNUMBER(B119),TEXT(B119,"0000"),B119),Addendum!I:I,"X")>0,10%,0) -> 0 | M119: =IF(AND(I119=0%,J119=0%,K119=0%,L119=0%),0%, IF(OR(TRIM(E119)="OneTime",TRIM(D119)=""),0%, IF( OR( TRIM(D119)="P1M", AND(TRIM(D119)="P1Y",TRIM(E119)="Monthly"), AND(TRIM(D119)="P3Y",TRIM(E119)="Monthly") ), IF(AND(I119=4%,J119=0%,K119=0%,L119=0%),1%, IF(AND(I119=4%,J119=2.5%,K119=0%,L119=10%),2%, IF(AND(I119=4%,J119=0%,K119=7%,L119=10%),3%,0%))), IF( OR( AND(TRIM(D119)="P1Y",TRIM(E119)="Annual"), AND(TRIM(D119)="P3Y",TRIM(E119)="Annual"), AND(TRIM(D119)="P3Y",TRIM(E119)="Triennial") ), IF(AND(I119=4%,J119=0%,K119=0%,L119=0%),3%, IF(AND(I119=4%,J119=2.5%,K119=0%,L119=10%),10%, IF(AND(I119=4%,J119=0%,K119=7%,L119=10%),14%,0%))), 0% )))) -> 0 | N119: =H119-(H119*M119) -> 6291
A120: CFQ7TTC0LHWJ | B120: 000C | C120: Dynamics 365 Asset Management Addl Assets (Education Faculty Pricing) | D120: P1M | E120: Monthly | F120: Education | G120: 6990 | H120: 4893 | I120: =IF(COUNTIFS(Addendum!C:C,A120,Addendum!D:D,IF(ISNUMBER(B120),TEXT(B120,"0000"),B120),Addendum!E:E,"X")>0,4%,0) -> 0 | J120: =IF(COUNTIFS(Addendum!C:C,A120,Addendum!D:D,IF(ISNUMBER(B120),TEXT(B120,"0000"),B120),Addendum!F:F,"X")>0,2.5%,0) -> 0 | K120: =IF(COUNTIFS(Addendum!C:C,A120,Addendum!D:D,IF(ISNUMBER(B120),TEXT(B120,"0000"),B120),Addendum!G:G,"X")>0,7%,0) -> 0 | L120: =IF(COUNTIFS(Addendum!C:C,A120,Addendum!D:D,IF(ISNUMBER(B120),TEXT(B120,"0000"),B120),Addendum!I:I,"X")>0,10%,0) -> 0 | M120: =IF(AND(I120=0%,J120=0%,K120=0%,L120=0%),0%, IF(OR(TRIM(E120)="OneTime",TRIM(D120)=""),0%, IF( OR( TRIM(D120)="P1M", AND(TRIM(D120)="P1Y",TRIM(E120)="Monthly"), AND(TRIM(D120)="P3Y",TRIM(E120)="Monthly") ), IF(AND(I120=4%,J120=0%,K120=0%,L120=0%),1%, IF(AND(I120=4%,J120=2.5%,K120=0%,L120=10%),2%, IF(AND(I120=4%,J120=0%,K120=7%,L120=10%),3%,0%))), IF( OR( AND(TRIM(D120)="P1Y",TRIM(E120)="Annual"), AND(TRIM(D120)="P3Y",TRIM(E120)="Annual"), AND(TRIM(D120)="P3Y",TRIM(E120)="Triennial") ), IF(AND(I120=4%,J120=0%,K120=0%,L120=0%),3%, IF(AND(I120=4%,J120=2.5%,K120=0%,L120=10%),10%, IF(AND(I120=4%,J120=0%,K120=7%,L120=10%),14%,0%))), 0% )))) -> 0 | N120: =H120-(H120*M120) -> 4893
A121: CFQ7TTC0LHWJ | B121: 1 | C121: Dynamics 365 Asset Management Addl Assets | D121: P3Y | E121: Triennial | F121: Commercial | G121: 299520 | H121: 209664 | I121: =IF(COUNTIFS(Addendum!C:C,A121,Addendum!D:D,IF(ISNUMBER(B121),TEXT(B121,"0000"),B121),Addendum!E:E,"X")>0,4%,0) -> 0 | J121: =IF(COUNTIFS(Addendum!C:C,A121,Addendum!D:D,IF(ISNUMBER(B121),TEXT(B121,"0000"),B121),Addendum!F:F,"X")>0,2.5%,0) -> 0 | K121: =IF(COUNTIFS(Addendum!C:C,A121,Addendum!D:D,IF(ISNUMBER(B121),TEXT(B121,"0000"),B121),Addendum!G:G,"X")>0,7%,0) -> 0 | L121: =IF(COUNTIFS(Addendum!C:C,A121,Addendum!D:D,IF(ISNUMBER(B121),TEXT(B121,"0000"),B121),Addendum!I:I,"X")>0,10%,0) -> 0 | M121: =IF(AND(I121=0%,J121=0%,K121=0%,L121=0%),0%, IF(OR(TRIM(E121)="OneTime",TRIM(D121)=""),0%, IF( OR( TRIM(D121)="P1M", AND(TRIM(D121)="P1Y",TRIM(E121)="Monthly"), AND(TRIM(D121)="P3Y",TRIM(E121)="Monthly") ), IF(AND(I121=4%,J121=0%,K121=0%,L121=0%),1%, IF(AND(I121=4%,J121=2.5%,K121=0%,L121=10%),2%, IF(AND(I121=4%,J121=0%,K121=7%,L121=10%),3%,0%))), IF( OR( AND(TRIM(D121)="P1Y",TRIM(E121)="Annual"), AND(TRIM(D121)="P3Y",TRIM(E121)="Annual"), AND(TRIM(D121)="P3Y",TRIM(E121)="Triennial") ), IF(AND(I121=4%,J121=0%,K121=0%,L121=0%),3%, IF(AND(I121=4%,J121=2.5%,K121=0%,L121=10%),10%, IF(AND(I121=4%,J121=0%,K121=7%,L121=10%),14%,0%))), 0% )))) -> 0 | N121: =H121-(H121*M121) -> 209664
A122: CFQ7TTC0LHWJ | B122: 000B | C122: Dynamics 365 Asset Management Addl Assets (Non-Profit Pricing) | D122: P1Y | E122: Monthly | F122: Charity | G122: 73395 | H122: 66055.56 | I122: =IF(COUNTIFS(Addendum!C:C,A122,Addendum!D:D,IF(ISNUMBER(B122),TEXT(B122,"0000"),B122),Addendum!E:E,"X")>0,4%,0) -> 0 | J122: =IF(COUNTIFS(Addendum!C:C,A122,Addendum!D:D,IF(ISNUMBER(B122),TEXT(B122,"0000"),B122),Addendum!F:F,"X")>0,2.5%,0) -> 0 | K122: =IF(COUNTIFS(Addendum!C:C,A122,Addendum!D:D,IF(ISNUMBER(B122),TEXT(B122,"0000"),B122),Addendum!G:G,"X")>0,7%,0) -> 0 | L122: =IF(COUNTIFS(Addendum!C:C,A122,Addendum!D:D,IF(ISNUMBER(B122),TEXT(B122,"0000"),B122),Addendum!I:I,"X")>0,10%,0) -> 0 | M122: =IF(AND(I122=0%,J122=0%,K122=0%,L122=0%),0%, IF(OR(TRIM(E122)="OneTime",TRIM(D122)=""),0%, IF( OR( TRIM(D122)="P1M", AND(TRIM(D122)="P1Y",TRIM(E122)="Monthly"), AND(TRIM(D122)="P3Y",TRIM(E122)="Monthly") ), IF(AND(I122=4%,J122=0%,K122=0%,L122=0%),1%, IF(AND(I122=4%,J122=2.5%,K122=0%,L122=10%),2%, IF(AND(I122=4%,J122=0%,K122=7%,L122=10%),3%,0%))), IF( OR( AND(TRIM(D122)="P1Y",TRIM(E122)="Annual"), AND(TRIM(D122)="P3Y",TRIM(E122)="Annual"), AND(TRIM(D122)="P3Y",TRIM(E122)="Triennial") ), IF(AND(I122=4%,J122=0%,K122=0%,L122=0%),3%, IF(AND(I122=4%,J122=2.5%,K122=0%,L122=10%),10%, IF(AND(I122=4%,J122=0%,K122=7%,L122=10%),14%,0%))), 0% )))) -> 0 | N122: =H122-(H122*M122) -> 66055.56
A123: CFQ7TTC0LHWJ | B123: 1 | C123: Dynamics 365 Asset Management Addl Assets | D123: P3Y | E123: Annual | F123: Commercial | G123: 299520 | H123: 209664 | I123: =IF(COUNTIFS(Addendum!C:C,A123,Addendum!D:D,IF(ISNUMBER(B123),TEXT(B123,"0000"),B123),Addendum!E:E,"X")>0,4%,0) -> 0 | J123: =IF(COUNTIFS(Addendum!C:C,A123,Addendum!D:D,IF(ISNUMBER(B123),TEXT(B123,"0000"),B123),Addendum!F:F,"X")>0,2.5%,0) -> 0 | K123: =IF(COUNTIFS(Addendum!C:C,A123,Addendum!D:D,IF(ISNUMBER(B123),TEXT(B123,"0000"),B123),Addendum!G:G,"X")>0,7%,0) -> 0 | L123: =IF(COUNTIFS(Addendum!C:C,A123,Addendum!D:D,IF(ISNUMBER(B123),TEXT(B123,"0000"),B123),Addendum!I:I,"X")>0,10%,0) -> 0 | M123: =IF(AND(I123=0%,J123=0%,K123=0%,L123=0%),0%, IF(OR(TRIM(E123)="OneTime",TRIM(D123)=""),0%, IF( OR( TRIM(D123)="P1M", AND(TRIM(D123)="P1Y",TRIM(E123)="Monthly"), AND(TRIM(D123)="P3Y",TRIM(E123)="Monthly") ), IF(AND(I123=4%,J123=0%,K123=0%,L123=0%),1%, IF(AND(I123=4%,J123=2.5%,K123=0%,L123=10%),2%, IF(AND(I123=4%,J123=0%,K123=7%,L123=10%),3%,0%))), IF( OR( AND(TRIM(D123)="P1Y",TRIM(E123)="Annual"), AND(TRIM(D123)="P3Y",TRIM(E123)="Annual"), AND(TRIM(D123)="P3Y",TRIM(E123)="Triennial") ), IF(AND(I123=4%,J123=0%,K123=0%,L123=0%),3%, IF(AND(I123=4%,J123=2.5%,K123=0%,L123=10%),10%, IF(AND(I123=4%,J123=0%,K123=7%,L123=10%),14%,0%))), 0% )))) -> 0 | N123: =H123-(H123*M123) -> 209664
A124: CFQ7TTC0LHWJ | B124: 1 | C124: Dynamics 365 Asset Management Addl Assets | D124: P1Y | E124: Monthly | F124: Commercial | G124: 104832 | H124: 73382.4 | I124: =IF(COUNTIFS(Addendum!C:C,A124,Addendum!D:D,IF(ISNUMBER(B124),TEXT(B124,"0000"),B124),Addendum!E:E,"X")>0,4%,0) -> 0 | J124: =IF(COUNTIFS(Addendum!C:C,A124,Addendum!D:D,IF(ISNUMBER(B124),TEXT(B124,"0000"),B124),Addendum!F:F,"X")>0,2.5%,0) -> 0 | K124: =IF(COUNTIFS(Addendum!C:C,A124,Addendum!D:D,IF(ISNUMBER(B124),TEXT(B124,"0000"),B124),Addendum!G:G,"X")>0,7%,0) -> 0 | L124: =IF(COUNTIFS(Addendum!C:C,A124,Addendum!D:D,IF(ISNUMBER(B124),TEXT(B124,"0000"),B124),Addendum!I:I,"X")>0,10%,0) -> 0 | M124: =IF(AND(I124=0%,J124=0%,K124=0%,L124=0%),0%, IF(OR(TRIM(E124)="OneTime",TRIM(D124)=""),0%, IF( OR( TRIM(D124)="P1M", AND(TRIM(D124)="P1Y",TRIM(E124)="Monthly"), AND(TRIM(D124)="P3Y",TRIM(E124)="Monthly") ), IF(AND(I124=4%,J124=0%,K124=0%,L124=0%),1%, IF(AND(I124=4%,J124=2.5%,K124=0%,L124=10%),2%, IF(AND(I124=4%,J124=0%,K124=7%,L124=10%),3%,0%))), IF( OR( AND(TRIM(D124)="P1Y",TRIM(E124)="Annual"), AND(TRIM(D124)="P3Y",TRIM(E124)="Annual"), AND(TRIM(D124)="P3Y",TRIM(E124)="Triennial") ), IF(AND(I124=4%,J124=0%,K124=0%,L124=0%),3%, IF(AND(I124=4%,J124=2.5%,K124=0%,L124=10%),10%, IF(AND(I124=4%,J124=0%,K124=7%,L124=10%),14%,0%))), 0% )))) -> 0 | N124: =H124-(H124*M124) -> 73382.4
A125: CFQ7TTC0HD7P | B125: 3 | C125: Dynamics 365 Business Central Additional Environment Addon (Education Faculty Pricing) | D125: P1Y | E125: Annual | F125: Education | G125: 164700 | H125: 115290 | I125: =IF(COUNTIFS(Addendum!C:C,A125,Addendum!D:D,IF(ISNUMBER(B125),TEXT(B125,"0000"),B125),Addendum!E:E,"X")>0,4%,0) -> 0 | J125: =IF(COUNTIFS(Addendum!C:C,A125,Addendum!D:D,IF(ISNUMBER(B125),TEXT(B125,"0000"),B125),Addendum!F:F,"X")>0,2.5%,0) -> 0 | K125: =IF(COUNTIFS(Addendum!C:C,A125,Addendum!D:D,IF(ISNUMBER(B125),TEXT(B125,"0000"),B125),Addendum!G:G,"X")>0,7%,0) -> 0 | L125: =IF(COUNTIFS(Addendum!C:C,A125,Addendum!D:D,IF(ISNUMBER(B125),TEXT(B125,"0000"),B125),Addendum!I:I,"X")>0,10%,0) -> 0 | M125: =IF(AND(I125=0%,J125=0%,K125=0%,L125=0%),0%, IF(OR(TRIM(E125)="OneTime",TRIM(D125)=""),0%, IF( OR( TRIM(D125)="P1M", AND(TRIM(D125)="P1Y",TRIM(E125)="Monthly"), AND(TRIM(D125)="P3Y",TRIM(E125)="Monthly") ), IF(AND(I125=4%,J125=0%,K125=0%,L125=0%),1%, IF(AND(I125=4%,J125=2.5%,K125=0%,L125=10%),2%, IF(AND(I125=4%,J125=0%,K125=7%,L125=10%),3%,0%))), IF( OR( AND(TRIM(D125)="P1Y",TRIM(E125)="Annual"), AND(TRIM(D125)="P3Y",TRIM(E125)="Annual"), AND(TRIM(D125)="P3Y",TRIM(E125)="Triennial") ), IF(AND(I125=4%,J125=0%,K125=0%,L125=0%),3%, IF(AND(I125=4%,J125=2.5%,K125=0%,L125=10%),10%, IF(AND(I125=4%,J125=0%,K125=7%,L125=10%),14%,0%))), 0% )))) -> 0 | N125: =H125-(H125*M125) -> 115290
A126: CFQ7TTC0HD7P | B126: 1 | C126: Dynamics 365 Business Central Additional Environment Addon | D126: P1M | E126: Monthly | F126: Commercial | G126: 29952 | H126: 20966.4 | I126: =IF(COUNTIFS(Addendum!C:C,A126,Addendum!D:D,IF(ISNUMBER(B126),TEXT(B126,"0000"),B126),Addendum!E:E,"X")>0,4%,0) -> 0 | J126: =IF(COUNTIFS(Addendum!C:C,A126,Addendum!D:D,IF(ISNUMBER(B126),TEXT(B126,"0000"),B126),Addendum!F:F,"X")>0,2.5%,0) -> 0 | K126: =IF(COUNTIFS(Addendum!C:C,A126,Addendum!D:D,IF(ISNUMBER(B126),TEXT(B126,"0000"),B126),Addendum!G:G,"X")>0,7%,0) -> 0 | L126: =IF(COUNTIFS(Addendum!C:C,A126,Addendum!D:D,IF(ISNUMBER(B126),TEXT(B126,"0000"),B126),Addendum!I:I,"X")>0,10%,0) -> 0 | M126: =IF(AND(I126=0%,J126=0%,K126=0%,L126=0%),0%, IF(OR(TRIM(E126)="OneTime",TRIM(D126)=""),0%, IF( OR( TRIM(D126)="P1M", AND(TRIM(D126)="P1Y",TRIM(E126)="Monthly"), AND(TRIM(D126)="P3Y",TRIM(E126)="Monthly") ), IF(AND(I126=4%,J126=0%,K126=0%,L126=0%),1%, IF(AND(I126=4%,J126=2.5%,K126=0%,L126=10%),2%, IF(AND(I126=4%,J126=0%,K126=7%,L126=10%),3%,0%))), IF( OR( AND(TRIM(D126)="P1Y",TRIM(E126)="Annual"), AND(TRIM(D126)="P3Y",TRIM(E126)="Annual"), AND(TRIM(D126)="P3Y",TRIM(E126)="Triennial") ), IF(AND(I126=4%,J126=0%,K126=0%,L126=0%),3%, IF(AND(I126=4%,J126=2.5%,K126=0%,L126=10%),10%, IF(AND(I126=4%,J126=0%,K126=7%,L126=10%),14%,0%))), 0% )))) -> 0 | N126: =H126-(H126*M126) -> 20966.4
A127: CFQ7TTC0HD7P | B127: 4 | C127: Dynamics 365 Business Central Additional Environment Addon (Non-Profit Pricing) | D127: P1Y | E127: Annual | F127: Charity | G127: 119820 | H127: 107838 | I127: =IF(COUNTIFS(Addendum!C:C,A127,Addendum!D:D,IF(ISNUMBER(B127),TEXT(B127,"0000"),B127),Addendum!E:E,"X")>0,4%,0) -> 0 | J127: =IF(COUNTIFS(Addendum!C:C,A127,Addendum!D:D,IF(ISNUMBER(B127),TEXT(B127,"0000"),B127),Addendum!F:F,"X")>0,2.5%,0) -> 0 | K127: =IF(COUNTIFS(Addendum!C:C,A127,Addendum!D:D,IF(ISNUMBER(B127),TEXT(B127,"0000"),B127),Addendum!G:G,"X")>0,7%,0) -> 0 | L127: =IF(COUNTIFS(Addendum!C:C,A127,Addendum!D:D,IF(ISNUMBER(B127),TEXT(B127,"0000"),B127),Addendum!I:I,"X")>0,10%,0) -> 0 | M127: =IF(AND(I127=0%,J127=0%,K127=0%,L127=0%),0%, IF(OR(TRIM(E127)="OneTime",TRIM(D127)=""),0%, IF( OR( TRIM(D127)="P1M", AND(TRIM(D127)="P1Y",TRIM(E127)="Monthly"), AND(TRIM(D127)="P3Y",TRIM(E127)="Monthly") ), IF(AND(I127=4%,J127=0%,K127=0%,L127=0%),1%, IF(AND(I127=4%,J127=2.5%,K127=0%,L127=10%),2%, IF(AND(I127=4%,J127=0%,K127=7%,L127=10%),3%,0%))), IF( OR( AND(TRIM(D127)="P1Y",TRIM(E127)="Annual"), AND(TRIM(D127)="P3Y",TRIM(E127)="Annual"), AND(TRIM(D127)="P3Y",TRIM(E127)="Triennial") ), IF(AND(I127=4%,J127=0%,K127=0%,L127=0%),3%, IF(AND(I127=4%,J127=2.5%,K127=0%,L127=10%),10%, IF(AND(I127=4%,J127=0%,K127=7%,L127=10%),14%,0%))), 0% )))) -> 0 | N127: =H127-(H127*M127) -> 107838
A128: CFQ7TTC0HD7P | B128: 3 | C128: Dynamics 365 Business Central Additional Environment Addon (Education Faculty Pricing) | D128: P1M | E128: Monthly | F128: Education | G128: 16470 | H128: 11529 | I128: =IF(COUNTIFS(Addendum!C:C,A128,Addendum!D:D,IF(ISNUMBER(B128),TEXT(B128,"0000"),B128),Addendum!E:E,"X")>0,4%,0) -> 0 | J128: =IF(COUNTIFS(Addendum!C:C,A128,Addendum!D:D,IF(ISNUMBER(B128),TEXT(B128,"0000"),B128),Addendum!F:F,"X")>0,2.5%,0) -> 0 | K128: =IF(COUNTIFS(Addendum!C:C,A128,Addendum!D:D,IF(ISNUMBER(B128),TEXT(B128,"0000"),B128),Addendum!G:G,"X")>0,7%,0) -> 0 | L128: =IF(COUNTIFS(Addendum!C:C,A128,Addendum!D:D,IF(ISNUMBER(B128),TEXT(B128,"0000"),B128),Addendum!I:I,"X")>0,10%,0) -> 0 | M128: =IF(AND(I128=0%,J128=0%,K128=0%,L128=0%),0%, IF(OR(TRIM(E128)="OneTime",TRIM(D128)=""),0%, IF( OR( TRIM(D128)="P1M", AND(TRIM(D128)="P1Y",TRIM(E128)="Monthly"), AND(TRIM(D128)="P3Y",TRIM(E128)="Monthly") ), IF(AND(I128=4%,J128=0%,K128=0%,L128=0%),1%, IF(AND(I128=4%,J128=2.5%,K128=0%,L128=10%),2%, IF(AND(I128=4%,J128=0%,K128=7%,L128=10%),3%,0%))), IF( OR( AND(TRIM(D128)="P1Y",TRIM(E128)="Annual"), AND(TRIM(D128)="P3Y",TRIM(E128)="Annual"), AND(TRIM(D128)="P3Y",TRIM(E128)="Triennial") ), IF(AND(I128=4%,J128=0%,K128=0%,L128=0%),3%, IF(AND(I128=4%,J128=2.5%,K128=0%,L128=10%),10%, IF(AND(I128=4%,J128=0%,K128=7%,L128=10%),14%,0%))), 0% )))) -> 0 | N128: =H128-(H128*M128) -> 11529
A129: CFQ7TTC0HD7P | B129: 1 | C129: Dynamics 365 Business Central Additional Environment Addon | D129: P1Y | E129: Monthly | F129: Commercial | G129: 314496 | H129: 220147.2 | I129: =IF(COUNTIFS(Addendum!C:C,A129,Addendum!D:D,IF(ISNUMBER(B129),TEXT(B129,"0000"),B129),Addendum!E:E,"X")>0,4%,0) -> 0 | J129: =IF(COUNTIFS(Addendum!C:C,A129,Addendum!D:D,IF(ISNUMBER(B129),TEXT(B129,"0000"),B129),Addendum!F:F,"X")>0,2.5%,0) -> 0 | K129: =IF(COUNTIFS(Addendum!C:C,A129,Addendum!D:D,IF(ISNUMBER(B129),TEXT(B129,"0000"),B129),Addendum!G:G,"X")>0,7%,0) -> 0 | L129: =IF(COUNTIFS(Addendum!C:C,A129,Addendum!D:D,IF(ISNUMBER(B129),TEXT(B129,"0000"),B129),Addendum!I:I,"X")>0,10%,0) -> 0 | M129: =IF(AND(I129=0%,J129=0%,K129=0%,L129=0%),0%, IF(OR(TRIM(E129)="OneTime",TRIM(D129)=""),0%, IF( OR( TRIM(D129)="P1M", AND(TRIM(D129)="P1Y",TRIM(E129)="Monthly"), AND(TRIM(D129)="P3Y",TRIM(E129)="Monthly") ), IF(AND(I129=4%,J129=0%,K129=0%,L129=0%),1%, IF(AND(I129=4%,J129=2.5%,K129=0%,L129=10%),2%, IF(AND(I129=4%,J129=0%,K129=7%,L129=10%),3%,0%))), IF( OR( AND(TRIM(D129)="P1Y",TRIM(E129)="Annual"), AND(TRIM(D129)="P3Y",TRIM(E129)="Annual"), AND(TRIM(D129)="P3Y",TRIM(E129)="Triennial") ), IF(AND(I129=4%,J129=0%,K129=0%,L129=0%),3%, IF(AND(I129=4%,J129=2.5%,K129=0%,L129=10%),10%, IF(AND(I129=4%,J129=0%,K129=7%,L129=10%),14%,0%))), 0% )))) -> 0 | N129: =H129-(H129*M129) -> 220147.2
A130: CFQ7TTC0HD7P | B130: 4 | C130: Dynamics 365 Business Central Additional Environment Addon (Non-Profit Pricing) | D130: P1Y | E130: Monthly | F130: Charity | G130: 125811 | H130: 113230 | I130: =IF(COUNTIFS(Addendum!C:C,A130,Addendum!D:D,IF(ISNUMBER(B130),TEXT(B130,"0000"),B130),Addendum!E:E,"X")>0,4%,0) -> 0 | J130: =IF(COUNTIFS(Addendum!C:C,A130,Addendum!D:D,IF(ISNUMBER(B130),TEXT(B130,"0000"),B130),Addendum!F:F,"X")>0,2.5%,0) -> 0 | K130: =IF(COUNTIFS(Addendum!C:C,A130,Addendum!D:D,IF(ISNUMBER(B130),TEXT(B130,"0000"),B130),Addendum!G:G,"X")>0,7%,0) -> 0 | L130: =IF(COUNTIFS(Addendum!C:C,A130,Addendum!D:D,IF(ISNUMBER(B130),TEXT(B130,"0000"),B130),Addendum!I:I,"X")>0,10%,0) -> 0 | M130: =IF(AND(I130=0%,J130=0%,K130=0%,L130=0%),0%, IF(OR(TRIM(E130)="OneTime",TRIM(D130)=""),0%, IF( OR( TRIM(D130)="P1M", AND(TRIM(D130)="P1Y",TRIM(E130)="Monthly"), AND(TRIM(D130)="P3Y",TRIM(E130)="Monthly") ), IF(AND(I130=4%,J130=0%,K130=0%,L130=0%),1%, IF(AND(I130=4%,J130=2.5%,K130=0%,L130=10%),2%, IF(AND(I130=4%,J130=0%,K130=7%,L130=10%),3%,0%))), IF( OR( AND(TRIM(D130)="P1Y",TRIM(E130)="Annual"), AND(TRIM(D130)="P3Y",TRIM(E130)="Annual"), AND(TRIM(D130)="P3Y",TRIM(E130)="Triennial") ), IF(AND(I130=4%,J130=0%,K130=0%,L130=0%),3%, IF(AND(I130=4%,J130=2.5%,K130=0%,L130=10%),10%, IF(AND(I130=4%,J130=0%,K130=7%,L130=10%),14%,0%))), 0% )))) -> 0 | N130: =H130-(H130*M130) -> 113230
A131: CFQ7TTC0HD7P | B131: 1 | C131: Dynamics 365 Business Central Additional Environment Addon | D131: P1Y | E131: Annual | F131: Commercial | G131: 299520 | H131: 209664 | I131: =IF(COUNTIFS(Addendum!C:C,A131,Addendum!D:D,IF(ISNUMBER(B131),TEXT(B131,"0000"),B131),Addendum!E:E,"X")>0,4%,0) -> 0 | J131: =IF(COUNTIFS(Addendum!C:C,A131,Addendum!D:D,IF(ISNUMBER(B131),TEXT(B131,"0000"),B131),Addendum!F:F,"X")>0,2.5%,0) -> 0 | K131: =IF(COUNTIFS(Addendum!C:C,A131,Addendum!D:D,IF(ISNUMBER(B131),TEXT(B131,"0000"),B131),Addendum!G:G,"X")>0,7%,0) -> 0 | L131: =IF(COUNTIFS(Addendum!C:C,A131,Addendum!D:D,IF(ISNUMBER(B131),TEXT(B131,"0000"),B131),Addendum!I:I,"X")>0,10%,0) -> 0 | M131: =IF(AND(I131=0%,J131=0%,K131=0%,L131=0%),0%, IF(OR(TRIM(E131)="OneTime",TRIM(D131)=""),0%, IF( OR( TRIM(D131)="P1M", AND(TRIM(D131)="P1Y",TRIM(E131)="Monthly"), AND(TRIM(D131)="P3Y",TRIM(E131)="Monthly") ), IF(AND(I131=4%,J131=0%,K131=0%,L131=0%),1%, IF(AND(I131=4%,J131=2.5%,K131=0%,L131=10%),2%, IF(AND(I131=4%,J131=0%,K131=7%,L131=10%),3%,0%))), IF( OR( AND(TRIM(D131)="P1Y",TRIM(E131)="Annual"), AND(TRIM(D131)="P3Y",TRIM(E131)="Annual"), AND(TRIM(D131)="P3Y",TRIM(E131)="Triennial") ), IF(AND(I131=4%,J131=0%,K131=0%,L131=0%),3%, IF(AND(I131=4%,J131=2.5%,K131=0%,L131=10%),10%, IF(AND(I131=4%,J131=0%,K131=7%,L131=10%),14%,0%))), 0% )))) -> 0 | N131: =H131-(H131*M131) -> 209664
A132: CFQ7TTC0HD7P | B132: 4 | C132: Dynamics 365 Business Central Additional Environment Addon (Non-Profit Pricing) | D132: P1M | E132: Monthly | F132: Charity | G132: 11982 | H132: 10783.8 | I132: =IF(COUNTIFS(Addendum!C:C,A132,Addendum!D:D,IF(ISNUMBER(B132),TEXT(B132,"0000"),B132),Addendum!E:E,"X")>0,4%,0) -> 0 | J132: =IF(COUNTIFS(Addendum!C:C,A132,Addendum!D:D,IF(ISNUMBER(B132),TEXT(B132,"0000"),B132),Addendum!F:F,"X")>0,2.5%,0) -> 0 | K132: =IF(COUNTIFS(Addendum!C:C,A132,Addendum!D:D,IF(ISNUMBER(B132),TEXT(B132,"0000"),B132),Addendum!G:G,"X")>0,7%,0) -> 0 | L132: =IF(COUNTIFS(Addendum!C:C,A132,Addendum!D:D,IF(ISNUMBER(B132),TEXT(B132,"0000"),B132),Addendum!I:I,"X")>0,10%,0) -> 0 | M132: =IF(AND(I132=0%,J132=0%,K132=0%,L132=0%),0%, IF(OR(TRIM(E132)="OneTime",TRIM(D132)=""),0%, IF( OR( TRIM(D132)="P1M", AND(TRIM(D132)="P1Y",TRIM(E132)="Monthly"), AND(TRIM(D132)="P3Y",TRIM(E132)="Monthly") ), IF(AND(I132=4%,J132=0%,K132=0%,L132=0%),1%, IF(AND(I132=4%,J132=2.5%,K132=0%,L132=10%),2%, IF(AND(I132=4%,J132=0%,K132=7%,L132=10%),3%,0%))), IF( OR( AND(TRIM(D132)="P1Y",TRIM(E132)="Annual"), AND(TRIM(D132)="P3Y",TRIM(E132)="Annual"), AND(TRIM(D132)="P3Y",TRIM(E132)="Triennial") ), IF(AND(I132=4%,J132=0%,K132=0%,L132=0%),3%, IF(AND(I132=4%,J132=2.5%,K132=0%,L132=10%),10%, IF(AND(I132=4%,J132=0%,K132=7%,L132=10%),14%,0%))), 0% )))) -> 0 | N132: =H132-(H132*M132) -> 10783.8
A133: CFQ7TTC0HD7P | B133: 3 | C133: Dynamics 365 Business Central Additional Environment Addon (Education Faculty Pricing) | D133: P1Y | E133: Monthly | F133: Education | G133: 172935 | H133: 121054.6 | I133: =IF(COUNTIFS(Addendum!C:C,A133,Addendum!D:D,IF(ISNUMBER(B133),TEXT(B133,"0000"),B133),Addendum!E:E,"X")>0,4%,0) -> 0 | J133: =IF(COUNTIFS(Addendum!C:C,A133,Addendum!D:D,IF(ISNUMBER(B133),TEXT(B133,"0000"),B133),Addendum!F:F,"X")>0,2.5%,0) -> 0 | K133: =IF(COUNTIFS(Addendum!C:C,A133,Addendum!D:D,IF(ISNUMBER(B133),TEXT(B133,"0000"),B133),Addendum!G:G,"X")>0,7%,0) -> 0 | L133: =IF(COUNTIFS(Addendum!C:C,A133,Addendum!D:D,IF(ISNUMBER(B133),TEXT(B133,"0000"),B133),Addendum!I:I,"X")>0,10%,0) -> 0 | M133: =IF(AND(I133=0%,J133=0%,K133=0%,L133=0%),0%, IF(OR(TRIM(E133)="OneTime",TRIM(D133)=""),0%, IF( OR( TRIM(D133)="P1M", AND(TRIM(D133)="P1Y",TRIM(E133)="Monthly"), AND(TRIM(D133)="P3Y",TRIM(E133)="Monthly") ), IF(AND(I133=4%,J133=0%,K133=0%,L133=0%),1%, IF(AND(I133=4%,J133=2.5%,K133=0%,L133=10%),2%, IF(AND(I133=4%,J133=0%,K133=7%,L133=10%),3%,0%))), IF( OR( AND(TRIM(D133)="P1Y",TRIM(E133)="Annual"), AND(TRIM(D133)="P3Y",TRIM(E133)="Annual"), AND(TRIM(D133)="P3Y",TRIM(E133)="Triennial") ), IF(AND(I133=4%,J133=0%,K133=0%,L133=0%),3%, IF(AND(I133=4%,J133=2.5%,K133=0%,L133=10%),10%, IF(AND(I133=4%,J133=0%,K133=7%,L133=10%),14%,0%))), 0% )))) -> 0 | N133: =H133-(H133*M133) -> 121054.6
A134: CFQ7TTC0HD3R | B134: 7 | C134: Dynamics 365 Business Central Database Capacity (Education Faculty Pricing) | D134: P1M | E134: Monthly | F134: Education | G134: 552 | H134: 386.4 | I134: =IF(COUNTIFS(Addendum!C:C,A134,Addendum!D:D,IF(ISNUMBER(B134),TEXT(B134,"0000"),B134),Addendum!E:E,"X")>0,4%,0) -> 0 | J134: =IF(COUNTIFS(Addendum!C:C,A134,Addendum!D:D,IF(ISNUMBER(B134),TEXT(B134,"0000"),B134),Addendum!F:F,"X")>0,2.5%,0) -> 0 | K134: =IF(COUNTIFS(Addendum!C:C,A134,Addendum!D:D,IF(ISNUMBER(B134),TEXT(B134,"0000"),B134),Addendum!G:G,"X")>0,7%,0) -> 0 | L134: =IF(COUNTIFS(Addendum!C:C,A134,Addendum!D:D,IF(ISNUMBER(B134),TEXT(B134,"0000"),B134),Addendum!I:I,"X")>0,10%,0) -> 0 | M134: =IF(AND(I134=0%,J134=0%,K134=0%,L134=0%),0%, IF(OR(TRIM(E134)="OneTime",TRIM(D134)=""),0%, IF( OR( TRIM(D134)="P1M", AND(TRIM(D134)="P1Y",TRIM(E134)="Monthly"), AND(TRIM(D134)="P3Y",TRIM(E134)="Monthly") ), IF(AND(I134=4%,J134=0%,K134=0%,L134=0%),1%, IF(AND(I134=4%,J134=2.5%,K134=0%,L134=10%),2%, IF(AND(I134=4%,J134=0%,K134=7%,L134=10%),3%,0%))), IF( OR( AND(TRIM(D134)="P1Y",TRIM(E134)="Annual"), AND(TRIM(D134)="P3Y",TRIM(E134)="Annual"), AND(TRIM(D134)="P3Y",TRIM(E134)="Triennial") ), IF(AND(I134=4%,J134=0%,K134=0%,L134=0%),3%, IF(AND(I134=4%,J134=2.5%,K134=0%,L134=10%),10%, IF(AND(I134=4%,J134=0%,K134=7%,L134=10%),14%,0%))), 0% )))) -> 0 | N134: =H134-(H134*M134) -> 386.4
...

Sheet Outcome Sheet
A2: ProductId | B2: SkuId | C2: SkuTitle | D2: TermDuration | E2: BillingPlan | F2: ERP Price | G2: UnitPrice | H2: Expectec Disti Price to Skysecure
A3: CFQ7TTC0HL8Z | B3: 1 | C3: 10-Year Audit Log Retention Add On | D3: P1Y | E3: Monthly | F3: 2079 | G3: 1663.2 | H3: ='Calculation Sheet'!N3 -> 1646.568
A4: CFQ7TTC0HL8Z | B4: 1 | C4: 10-Year Audit Log Retention Add On | D4: P1Y | E4: Annual | F4: 1980 | G4: 1584 | H4: ='Calculation Sheet'!N4 -> 1536.48
A5: CFQ7TTC0HL8Z | B5: 5 | C5: 10-Year Audit Log Retention Add On for FLW | D5: P1Y | E5: Monthly | F5: 1386 | G5: 1108.8 | H5: ='Calculation Sheet'!N5 -> 1097.712
A6: CFQ7TTC0HL8Z | B6: 4 | C6: 10-Year Audit Log Retention Add On (Education Pricing) | D6: P1Y | E6: Annual | F6: 1980 | G6: 1584 | H6: ='Calculation Sheet'!N6 -> 1536.48
A7: CFQ7TTC0HL8Z | B7: 5 | C7: 10-Year Audit Log Retention Add On for FLW | D7: P1Y | E7: Annual | F7: 1320 | G7: 1056 | H7: ='Calculation Sheet'!N7 -> 1024.32
A8: CFQ7TTC0HL8Z | B8: 1 | C8: 10-Year Audit Log Retention Add On | D8: P1M | E8: Monthly | F8: 198 | G8: 158.4 | H8: ='Calculation Sheet'!N8 -> 156.816
A9: CFQ7TTC0HL8Z | B9: 4 | C9: 10-Year Audit Log Retention Add On (Education Pricing) | D9: P1M | E9: Monthly | F9: 198 | G9: 158.4 | H9: ='Calculation Sheet'!N9 -> 156.816
A10: CFQ7TTC0HL8Z | B10: 5 | C10: 10-Year Audit Log Retention Add On for FLW | D10: P1M | E10: Monthly | F10: 132 | G10: 105.6 | H10: ='Calculation Sheet'!N10 -> 104.544
A11: CFQ7TTC0HL8Z | B11: 4 | C11: 10-Year Audit Log Retention Add On (Education Pricing) | D11: P1Y | E11: Monthly | F11: 2079 | G11: 1663.2 | H11: ='Calculation Sheet'!N11 -> 1646.568
A12: CFQ7TTC0RN26 | B12: 1 | C12: Advanced Data Residency | D12: P1Y | E12: Monthly | F12: 2079 | G12: 1663.2 | H12: ='Calculation Sheet'!N12 -> 1663.2
A13: CFQ7TTC0RN26 | B13: 1 | C13: Advanced Data Residency | D13: P3Y | E13: Triennial | F13: 5940 | G13: 4752 | H13: ='Calculation Sheet'!N13 -> 4752
A14: CFQ7TTC0RN26 | B14: 1 | C14: Advanced Data Residency | D14: P1Y | E14: Annual | F14: 1980 | G14: 1584 | H14: ='Calculation Sheet'!N14 -> 1584
A15: CFQ7TTC0RN26 | B15: 1 | C15: Advanced Data Residency | D15: P3Y | E15: Annual | F15: 5940 | G15: 4752 | H15: ='Calculation Sheet'!N15 -> 4752
A16: CFQ7TTC0HDK0 | B16: 000B | C16: Advanced Communications (Non-Profit Pricing) | D16: P1Y | E16: Monthly | F16: 5040 | G16: 4536 | H16: ='Calculation Sheet'!N16 -> 4490.64
A17: CFQ7TTC0HDK0 | B17: 000D | C17: Advanced Communications (Education Student Pricing) | D17: P1Y | E17: Monthly | F17: 1890 | G17: 1512 | H17: ='Calculation Sheet'!N17 -> 1496.88
A18: CFQ7TTC0HDK0 | B18: 000C | C18: Advanced Communications (Education Faculty Pricing) | D18: P1Y | E18: Monthly | F18: 2520 | G18: 2016 | H18: ='Calculation Sheet'!N18 -> 1995.84
A19: CFQ7TTC0HDK0 | B19: 000C | C19: Advanced Communications (Education Faculty Pricing) | D19: P1Y | E19: Annual | F19: 2400 | G19: 1920 | H19: ='Calculation Sheet'!N19 -> 1862.4
A20: CFQ7TTC0HDK0 | B20: 000B | C20: Advanced Communications (Non-Profit Pricing) | D20: P1M | E20: Monthly | F20: 480 | G20: 432 | H20: ='Calculation Sheet'!N20 -> 427.68
A21: CFQ7TTC0HDK0 | B21: 000D | C21: Advanced Communications (Education Student Pricing) | D21: P1M | E21: Monthly | F21: 180 | G21: 144 | H21: ='Calculation Sheet'!N21 -> 142.56
A22: CFQ7TTC0HDK0 | B22: 1 | C22: Advanced Communications | D22: P1M | E22: Monthly | F22: 1200 | G22: 960 | H22: ='Calculation Sheet'!N22 -> 950.4
A23: CFQ7TTC0HDK0 | B23: 000B | C23: Advanced Communications (Non-Profit Pricing) | D23: P1Y | E23: Annual | F23: 4800 | G23: 4320 | H23: ='Calculation Sheet'!N23 -> 4190.4
A24: CFQ7TTC0HDK0 | B24: 1 | C24: Advanced Communications | D24: P1Y | E24: Annual | F24: 12000 | G24: 9600 | H24: ='Calculation Sheet'!N24 -> 9312
A25: CFQ7TTC0HDK0 | B25: 1 | C25: Advanced Communications | D25: P1Y | E25: Monthly | F25: 12600 | G25: 10080 | H25: ='Calculation Sheet'!N25 -> 9979.2
A26: CFQ7TTC0HDK0 | B26: 000D | C26: Advanced Communications (Education Student Pricing) | D26: P1Y | E26: Annual | F26: 1800 | G26: 1440 | H26: ='Calculation Sheet'!N26 -> 1396.8
A27: CFQ7TTC0HDK0 | B27: 000C | C27: Advanced Communications (Education Faculty Pricing) | D27: P1M | E27: Monthly | F27: 240 | G27: 192 | H27: ='Calculation Sheet'!N27 -> 190.08
A28: CFQ7TTC0LHQD | B28: 4 | C28: Advanced eDiscovery Storage (Education Faculty Pricing) | D28: P1M | E28: Monthly | F28: 1998 | G28: 1598.4 | H28: ='Calculation Sheet'!N28 -> 1598.4
A29: CFQ7TTC0LHQD | B29: 4 | C29: Advanced eDiscovery Storage (Education Faculty Pricing) | D29: P1Y | E29: Monthly | F29: 20979 | G29: 16783.2 | H29: ='Calculation Sheet'!N29 -> 16783.2
A30: CFQ7TTC0LHQD | B30: 4 | C30: Advanced eDiscovery Storage (Education Faculty Pricing) | D30: P1Y | E30: Annual | F30: 19980 | G30: 15984 | H30: ='Calculation Sheet'!N30 -> 15984
A31: CFQ7TTC0LHQD | B31: 1 | C31: Advanced eDiscovery Storage | D31: P1Y | E31: Monthly | F31: 104832 | G31: 83865.6 | H31: ='Calculation Sheet'!N31 -> 83865.6
A32: CFQ7TTC0LHQD | B32: 5 | C32: Advanced eDiscovery Storage (Non-Profit Pricing) | D32: P1Y | E32: Monthly | F32: 41958 | G32: 37762.2 | H32: ='Calculation Sheet'!N32 -> 37762.2
A33: CFQ7TTC0LHQD | B33: 1 | C33: Advanced eDiscovery Storage | D33: P1Y | E33: Annual | F33: 99840 | G33: 79872 | H33: ='Calculation Sheet'!N33 -> 79872
A34: CFQ7TTC0LHQD | B34: 5 | C34: Advanced eDiscovery Storage (Non-Profit Pricing) | D34: P1M | E34: Monthly | F34: 3996 | G34: 3596.4 | H34: ='Calculation Sheet'!N34 -> 3596.4
A35: CFQ7TTC0LHQD | B35: 5 | C35: Advanced eDiscovery Storage (Non-Profit Pricing) | D35: P1Y | E35: Annual | F35: 39960 | G35: 35964 | H35: ='Calculation Sheet'!N35 -> 35964
A36: CFQ7TTC0LHQD | B36: 1 | C36: Advanced eDiscovery Storage | D36: P1M | E36: Monthly | F36: 9984 | G36: 7987.2 | H36: ='Calculation Sheet'!N36 -> 7987.2
A37: CFQ7TTC10RSN | B37: 3 | C37: Microsoft Defender and Purview Suites for Microsoft 365 Business Premium | D37: P1Y | E37: Monthly | F37: 15750 | G37: 12600 | H37: ='Calculation Sheet'!N37 -> 12348
A38: CFQ7TTC10RSN | B38: 1 | C38: Microsoft Defender Suite for Microsoft 365 Business Premium | D38: P1Y | E38: Monthly | F38: 10458 | G38: 8366.4 | H38: ='Calculation Sheet'!N38 -> 8199.072
A39: CFQ7TTC10RSN | B39: 7 | C39: Microsoft Purview Suite for Microsoft 365 Business Premium (Non-Profit Pricing) | D39: P1Y | E39: Monthly | F39: 4221 | G39: 3798.96 | H39: ='Calculation Sheet'!N39 -> 3722.9808
... A73: CFQ7TTC0LHRL | B73: 2 | C73: Dataverse Database Capacity add-on | D73: P1Y | E73: Annual | F73: 39960 | G73: 29970 | H73: ='Calculation Sheet'!N73 -> 29970
A74: CFQ7TTC0LHRL | B74: 000H | C74: Dataverse Database Capacity add-on (Education Pricing) | D74: P1M | E74: Monthly | F74: 2796 | G74: 2097 | H74: ='Calculation Sheet'!N74 -> 2097
A75: CFQ7TTC0LHRL | B75: 2 | C75: Dataverse Database Capacity add-on | D75: P1M | E75: Monthly | F75: 3996 | G75: 2997 | H75: ='Calculation Sheet'!N75 -> 2997
A76: CFQ7TTC0LHRL | B76: 000J | C76: Dataverse Database Capacity add-on (Non-Profit Pricing) | D76: P1Y | E76: Monthly | F76: 29358 | G76: 26422.2 | H76: ='Calculation Sheet'!N76 -> 26422.2
A77: CFQ7TTC0LHRL | B77: 2 | C77: Dataverse Database Capacity add-on | D77: P1Y | E77: Monthly | F77: 41958 | G77: 31468.56 | H77: ='Calculation Sheet'!N77 -> 31468.56
A78: CFQ7TTC0LHRL | B78: 000H | C78: Dataverse Database Capacity add-on (Education Pricing) | D78: P1Y | E78: Monthly | F78: 29358 | G78: 22018.56 | H78: ='Calculation Sheet'!N78 -> 22018.56
A79: CFQ7TTC0LHRL | B79: 000J | C79: Dataverse Database Capacity add-on (Non-Profit Pricing) | D79: P1M | E79: Monthly | F79: 2796 | G79: 2516.4 | H79: ='Calculation Sheet'!N79 -> 2516.4
A80: CFQ7TTC0LHRL | B80: 000H | C80: Dataverse Database Capacity add-on (Education Pricing) | D80: P1Y | E80: Annual | F80: 27960 | G80: 20970 | H80: ='Calculation Sheet'!N80 -> 20970
A81: CFQ7TTC0LHRL | B81: 000J | C81: Dataverse Database Capacity add-on (Non-Profit Pricing) | D81: P1Y | E81: Annual | F81: 27960 | G81: 25164 | H81: ='Calculation Sheet'!N81 -> 25164
A82: CFQ7TTC0NCD7 | B82: 3 | C82: Dataverse Database Capacity add-on Tier 2 (Min 1000GB) | D82: P1M | E82: Monthly | F82: 2994 | G82: 2245.5 | H82: ='Calculation Sheet'!N82 -> 2245.5
A83: CFQ7TTC0NCD7 | B83: 3 | C83: Dataverse Database Capacity add-on Tier 2 (Min 1000GB) | D83: P1Y | E83: Annual | F83: 29940 | G83: 22455 | H83: ='Calculation Sheet'!N83 -> 22455
A84: CFQ7TTC0NCD7 | B84: 3 | C84: Dataverse Database Capacity add-on Tier 2 (Min 1000GB) | D84: P1Y | E84: Monthly | F84: 31437 | G84: 23577.72 | H84: ='Calculation Sheet'!N84 -> 23577.72
A85: CFQ7TTC0NCD7 | B85: 2 | C85: Dataverse Database Capacity add-on Tier 2 (Min 1000GB) | D85: P1M | E85: None | F85: 0 | G85: 0 | H85: ='Calculation Sheet'!N85 -> 0
A86: CFQ7TTC0LHQ3 | B86: 1 | C86: Dataverse File Capacity add-on | D86: P1Y | E86: Monthly | F86: 2079 | G86: 1559.28 | H86: ='Calculation Sheet'!N86 -> 1559.28
A87: CFQ7TTC0LHQ3 | B87: 000G | C87: Dataverse File Capacity add-on (Non-Profit Pricing) | D87: P1Y | E87: Monthly | F87: 1449 | G87: 1304.16 | H87: ='Calculation Sheet'!N87 -> 1304.16
A88: CFQ7TTC0LHQ3 | B88: 1 | C88: Dataverse File Capacity add-on | D88: P1Y | E88: Annual | F88: 1980 | G88: 1485 | H88: ='Calculation Sheet'!N88 -> 1485
A89: CFQ7TTC0LHQ3 | B89: 000G | C89: Dataverse File Capacity add-on (Non-Profit Pricing) | D89: P1Y | E89: Annual | F89: 1380 | G89: 1242 | H89: ='Calculation Sheet'!N89 -> 1242
A90: CFQ7TTC0LHQ3 | B90: 000H | C90: Dataverse File Capacity add-on (Education Pricing) | D90: P1Y | E90: Annual | F90: 1380 | G90: 1035 | H90: ='Calculation Sheet'!N90 -> 1035
A91: CFQ7TTC0LHQ3 | B91: 000H | C91: Dataverse File Capacity add-on (Education Pricing) | D91: P1Y | E91: Monthly | F91: 1449 | G91: 1086.72 | H91: ='Calculation Sheet'!N91 -> 1086.72
A92: CFQ7TTC0LHQ3 | B92: 1 | C92: Dataverse File Capacity add-on | D92: P1M | E92: Monthly | F92: 198 | G92: 148.5 | H92: ='Calculation Sheet'!N92 -> 148.5
A93: CFQ7TTC0LHQ3 | B93: 000G | C93: Dataverse File Capacity add-on (Non-Profit Pricing) | D93: P1M | E93: Monthly | F93: 138 | G93: 124.2 | H93: ='Calculation Sheet'!N93 -> 124.2
A94: CFQ7TTC0LHQ3 | B94: 000H | C94: Dataverse File Capacity add-on (Education Pricing) | D94: P1M | E94: Monthly | F94: 138 | G94: 103.5 | H94: ='Calculation Sheet'!N94 -> 103.5
A95: CFQ7TTC0HBSL | B95: 000G | C95: Dataverse Log Capacity add-on (Non-Profit Pricing) | D95: P1Y | E95: Monthly | F95: 7308 | G95: 6577.2 | H95: ='Calculation Sheet'!N95 -> 6577.2
A96: CFQ7TTC0HBSL | B96: 1 | C96: Dataverse Log Capacity add-on | D96: P1M | E96: Monthly | F96: 996 | G96: 747 | H96: ='Calculation Sheet'!N96 -> 747
A97: CFQ7TTC0HBSL | B97: 1 | C97: Dataverse Log Capacity add-on | D97: P1Y | E97: Monthly | F97: 10458 | G97: 7843.56 | H97: ='Calculation Sheet'!N97 -> 7843.56
A98: CFQ7TTC0HBSL | B98: 1 | C98: Dataverse Log Capacity add-on | D98: P1Y | E98: Annual | F98: 9960 | G98: 7470 | H98: ='Calculation Sheet'!N98 -> 7470
A99: CFQ7TTC0HBSL | B99: 000G | C99: Dataverse Log Capacity add-on (Non-Profit Pricing) | D99: P1Y | E99: Annual | F99: 6960 | G99: 6264 | H99: ='Calculation Sheet'!N99 -> 6264
A100: CFQ7TTC0HBSL | B100: 000H | C100: Dataverse Log Capacity add-on (Education Pricing) | D100: P1Y | E100: Monthly | F100: 7308 | G100: 5481 | H100: ='Calculation Sheet'!N100 -> 5481
A101: CFQ7TTC0HBSL | B101: 000H | C101: Dataverse Log Capacity add-on (Education Pricing) | D101: P1Y | E101: Annual | F101: 6960 | G101: 5220 | H101: ='Calculation Sheet'!N101 -> 5220
A102: CFQ7TTC0HBSL | B102: 000G | C102: Dataverse Log Capacity add-on (Non-Profit Pricing) | D102: P1M | E102: Monthly | F102: 696 | G102: 626.4 | H102: ='Calculation Sheet'!N102 -> 626.4
A103: CFQ7TTC0HBSL | B103: 000H | C103: Dataverse Log Capacity add-on (Education Pricing) | D103: P1M | E103: Monthly | F103: 696 | G103: 522 | H103: ='Calculation Sheet'!N103 -> 522
A104: CFQ7TTC0LHXR | B104: 000B | C104: Dynamics 365 Operations-Order Lines (Education Pricing) | D104: P1M | E104: Monthly | F104: 34944 | G104: 24460.8 | H104: ='Calculation Sheet'!N104 -> 24460.8
A105: CFQ7TTC0LHXR | B105: 1 | C105: Dynamics 365 Operations – Order Lines | D105: P1M | E105: Monthly | F105: 49914 | G105: 34939.8 | H105: ='Calculation Sheet'!N105 -> 34939.8
A106: CFQ7TTC0LHXR | B106: 1 | C106: Dynamics 365 Operations – Order Lines | D106: P1Y | E106: Annual | F106: 499140 | G106: 349398 | H106: ='Calculation Sheet'!N106 -> 349398
A107: CFQ7TTC0LHXR | B107: 1 | C107: Dynamics 365 Operations – Order Lines | D107: P1Y | E107: Monthly | F107: 524097 | G107: 366868 | H107: ='Calculation Sheet'!N107 -> 366868
A108: CFQ7TTC0LHXR | B108: 000G | C108: Dynamics 365 Operations – Order Lines (Non-Profit Pricing) | D108: P1Y | E108: Monthly | F108: 131040 | G108: 117936 | H108: ='Calculation Sheet'!N108 -> 117936
A109: CFQ7TTC0LHXR | B109: 000B | C109: Dynamics 365 Operations-Order Lines (Education Pricing) | D109: P1Y | E109: Monthly | F109: 366912 | G109: 256838.4 | H109: ='Calculation Sheet'!N109 -> 256838.4
A110: CFQ7TTC0LHXR | B110: 000B | C110: Dynamics 365 Operations-Order Lines (Education Pricing) | D110: P1Y | E110: Annual | F110: 349440 | G110: 244608 | H110: ='Calculation Sheet'!N110 -> 244608
A111: CFQ7TTC0LHXR | B111: 000G | C111: Dynamics 365 Operations – Order Lines (Non-Profit Pricing) | D111: P1M | E111: Monthly | F111: 12480 | G111: 11232 | H111: ='Calculation Sheet'!N111 -> 11232
A112: CFQ7TTC0LHXR | B112: 000G | C112: Dynamics 365 Operations – Order Lines (Non-Profit Pricing) | D112: P1Y | E112: Annual | F112: 124800 | G112: 112320 | H112: ='Calculation Sheet'!N112 -> 112320
A113: CFQ7TTC0LHWJ | B113: 1 | C113: Dynamics 365 Asset Management Addl Assets | D113: P1M | E113: Monthly | F113: 9984 | G113: 6988.8 | H113: ='Calculation Sheet'!N113 -> 6988.8
A114: CFQ7TTC0LHWJ | B114: 1 | C114: Dynamics 365 Asset Management Addl Assets | D114: P3Y | E114: Monthly | F114: 314496 | G114: 220147.2 | H114: ='Calculation Sheet'!N114 -> 220147.2
A115: CFQ7TTC0LHWJ | B115: 000C | C115: Dynamics 365 Asset Management Addl Assets (Education Faculty Pricing) | D115: P1Y | E115: Monthly | F115: 73395 | G115: 51376.56 | H115: ='Calculation Sheet'!N115 -> 51376.56
A116: CFQ7TTC0LHWJ | B116: 1 | C116: Dynamics 365 Asset Management Addl Assets | D116: P1Y | E116: Annual | F116: 99840 | G116: 69888 | H116: ='Calculation Sheet'!N116 -> 69888
A117: CFQ7TTC0LHWJ | B117: 000C | C117: Dynamics 365 Asset Management Addl Assets (Education Faculty Pricing) | D117: P1Y | E117: Annual | F117: 69900 | G117: 48930 | H117: ='Calculation Sheet'!N117 -> 48930
A118: CFQ7TTC0LHWJ | B118: 000B | C118: Dynamics 365 Asset Management Addl Assets (Non-Profit Pricing) | D118: P1Y | E118: Annual | F118: 69900 | G118: 62910 | H118: ='Calculation Sheet'!N118 -> 62910
A119: CFQ7TTC0LHWJ | B119: 000B | C119: Dynamics 365 Asset Management Addl Assets (Non-Profit Pricing) | D119: P1M | E119: Monthly | F119: 6990 | G119: 6291 | H119: ='Calculation Sheet'!N119 -> 6291
A120: CFQ7TTC0LHWJ | B120: 000C | C120: Dynamics 365 Asset Management Addl Assets (Education Faculty Pricing) | D120: P1M | E120: Monthly | F120: 6990 | G120: 4893 | H120: ='Calculation Sheet'!N120 -> 4893
A121: CFQ7TTC0LHWJ | B121: 1 | C121: Dynamics 365 Asset Management Addl Assets | D121: P3Y | E121: Triennial | F121: 299520 | G121: 209664 | H121: ='Calculation Sheet'!N121 -> 209664
A122: CFQ7TTC0LHWJ | B122: 000B | C122: Dynamics 365 Asset Management Addl Assets (Non-Profit Pricing) | D122: P1Y | E122: Monthly | F122: 73395 | G122: 66055.56 | H122: ='Calculation Sheet'!N122 -> 66055.56
A123: CFQ7TTC0LHWJ | B123: 1 | C123: Dynamics 365 Asset Management Addl Assets | D123: P3Y | E123: Annual | F123: 299520 | G123: 209664 | H123: ='Calculation Sheet'!N123 -> 209664
A124: CFQ7TTC0LHWJ | B124: 1 | C124: Dynamics 365 Asset Management Addl Assets | D124: P1Y | E124: Monthly | F124: 104832 | G124: 73382.4 | H124: ='Calculation Sheet'!N124 -> 73382.4
A125: CFQ7TTC0HD7P | B125: 3 | C125: Dynamics 365 Business Central Additional Environment Addon (Education Faculty Pricing) | D125: P1Y | E125: Annual | F125: 164700 | G125: 115290 | H125: ='Calculation Sheet'!N125 -> 115290
A126: CFQ7TTC0HD7P | B126: 1 | C126: Dynamics 365 Business Central Additional Environment Addon | D126: P1M | E126: Monthly | F126: 29952 | G126: 20966.4 | H126: ='Calculation Sheet'!N126 -> 20966.4
A127: CFQ7TTC0HD7P | B127: 4 | C127: Dynamics 365 Business Central Additional Environment Addon (Non-Profit Pricing) | D127: P1Y | E127: Annual | F127: 119820 | G127: 107838 | H127: ='Calculation Sheet'!N127 -> 107838
A128: CFQ7TTC0HD7P | B128: 3 | C128: Dynamics 365 Business Central Additional Environment Addon (Education Faculty Pricing) | D128: P1M | E128: Monthly | F128: 16470 | G128: 11529 | H128: ='Calculation Sheet'!N128 -> 11529
A129: CFQ7TTC0HD7P | B129: 1 | C129: Dynamics 365 Business Central Additional Environment Addon | D129: P1Y | E129: Monthly | F129: 314496 | G129: 220147.2 | H129: ='Calculation Sheet'!N129 -> 220147.2
A130: CFQ7TTC0HD7P | B130: 4 | C130: Dynamics 365 Business Central Additional Environment Addon (Non-Profit Pricing) | D130: P1Y | E130: Monthly | F130: 125811 | G130: 113230 | H130: ='Calculation Sheet'!N130 -> 113230
A131: CFQ7TTC0HD7P | B131: 1 | C131: Dynamics 365 Business Central Additional Environment Addon | D131: P1Y | E131: Annual | F131: 299520 | G131: 209664 | H131: ='Calculation Sheet'!N131 -> 209664
A132: CFQ7TTC0HD7P | B132: 4 | C132: Dynamics 365 Business Central Additional Environment Addon (Non-Profit Pricing) | D132: P1M | E132: Monthly | F132: 11982 | G132: 10783.8 | H132: ='Calculation Sheet'!N132 -> 10783.8
A133: CFQ7TTC0HD7P | B133: 3 | C133: Dynamics 365 Business Central Additional Environment Addon (Education Faculty Pricing) | D133: P1Y | E133: Monthly | F133: 172935 | G133: 121054.6 | H133: ='Calculation Sheet'!N133 -> 121054.6
A134: CFQ7TTC0HD3R | B134: 7 | C134: Dynamics 365 Business Central Database Capacity (Education Faculty Pricing) | D134: P1M | E134: Monthly | F134: 552 | G134: 386.4 | H134: ='Calculation Sheet'!N134 -> 386.4
...
